Workbook

Sheet Assumptions
A1: NutriSync — Assumptions (All blue cells are inputs. Change here; all scenario sheets update.)
A2: Category | B2: Assumption | C2: Conservative | D2: Realistic | E2: Ambitious
A3: PRICING
A4: PRICING | B4: B2C basic price/mo (€) | C4: 4.99 | D4: 4.99 | E4: 4.99
A5: PRICING | B5: B2C premium price/mo (€) — launches M13 | C5: 12.99 | D5: 12.99 | E5: 12.99
A6: PRICING | B6: B2B price Y1 (€/employee/mo) | C6: 3.99 | D6: 3.99 | E6: 3.99
A7: PRICING | B7: B2B price Y2+ renewal (€/employee/mo) | C7: 5.99 | D7: 5.99 | E7: 5.99
A8: FUNNEL
A9: FUNNEL | B9: New organic free users M1 | C9: 320 | D9: 350 | E9: 420
A10: FUNNEL | B10: Organic new-user growth rate (%/mo) | C10: 0.18 | D10: 0.19 | E10: 0.2
A11: FUNNEL | B11: Free-to-paid conversion (one-off % per month new free users) | C11: 0.12 | D11: 0.14 | E11: 0.13
A12: FUNNEL | B12: Paid social budget Y1 (€/mo, from M4) | C12: 9000 | D12: 11000 | E12: 14000
A13: FUNNEL | B13: Paid social budget Y2 (€/mo) | C13: 18000 | D13: 28000 | E13: 25000
A14: FUNNEL | B14: Paid social budget Y3 (€/mo) | C14: 18000 | D14: 21000 | E14: 38000
A15: FUNNEL | B15: CAC — paid social Y1 (€/paying subscriber) | C15: 20 | D15: 15 | E15: 12
A16: FUNNEL | B16: CAC — paid social Y2+ (€/paying subscriber) | C16: 24 | D16: 18 | E16: 14
A17: CHURN
A18: CHURN | B18: Base monthly churn Y1 (average fitness app = 9.2%) | C18: 0.09 | D18: 0.08 | E18: 0.07
A19: CHURN | B19: Base monthly churn Y2 | C19: 0.08 | D19: 0.07 | E19: 0.06
A20: CHURN | B20: Base monthly churn Y3 | C20: 0.065 | D20: 0.055 | E20: 0.05
A21: CHURN | B21: Wearable adoption ramp (%-pts/mo from M4) | C21: 0.015 | D21: 0.02 | E21: 0.025
A22: CHURN | B22: Wearable adoption cap (% of paid users) | C22: 0.3 | D22: 0.4 | E22: 0.5
A23: CHURN | B23: Wearable churn reduction (vs base; 30–40% defensible) | C23: 0.3 | D23: 0.35 | E23: 0.4
A24: PREMIUM
A25: PREMIUM | B25: Premium launch month | C25: 13 | D25: 13 | E25: 12
A26: PREMIUM | B26: Premium upgrade rate (%/mo of basic base, post-launch) | C26: 0.0075 | D26: 0.01 | E26: 0.015
A27: PREMIUM | B27: Premium monthly churn | C27: 0.04 | D27: 0.035 | E27: 0.03
A28: B2B
A29: B2B | B29: New B2B contracts/mo Y1 (from M6) | C29: 1.5 | D29: 1.7 | E29: 2
A30: B2B | B30: New B2B contracts/mo Y2 | C30: 3 | D30: 1.7 | E30: 5.3
A31: B2B | B31: New B2B contracts/mo Y3 | C31: 3.5 | D31: 3.6 | E31: 3.6
A32: B2B | B32: Avg employees per B2B contract | C32: 120 | D32: 150 | E32: 175
A33: B2B | B33: B2B annual logo churn | C33: 0.2 | D33: 0.18 | E33: 0.15
A34: OTHER REV
A35: OTHER REV | B35: Events net €/mo Y1 (from M3) | C35: 500 | D35: 750 | E35: 1000
A36: OTHER REV | B36: Events net €/mo Y2 | C36: 1000 | D36: 1500 | E36: 2000
A37: OTHER REV | B37: Events net €/mo Y3 | C37: 1500 | D37: 2000 | E37: 3000
A38: OTHER REV | B38: Brand partnerships €/mo Y3 (conservative = 0) | C38: 0 | D38: 2000 | E38: 3500
A39: OTHER REV | B39: Clinical referral fee (€/contract signed/mo, from M6) | C39: 300 | D39: 400 | E39: 500
A40: FEES
A41: FEES | B41: App store fee — Small Business Programme (UNDER $1M proceeds) | C41: 0.15 | D41: 0.15 | E41: 0.15
A42: FEES | B42: App store fee — standard (ABOVE $1M proceeds threshold) | C42: 0.3 | D42: 0.3 | E42: 0.3
A43: FEES | B43: TTM B2C revenue threshold for 30% rate (€) | C43: 865000 | D43: 865000 | E43: 865000
A44: FEES | B44: Stripe fee on B2B revenue | C44: 0.014 | D44: 0.014 | E44: 0.014
A45: AI COSTS
A46: AI COSTS | B46: AI API base €/mo (from M6) | C46: 400 | D46: 400 | E46: 400
A47: AI COSTS | B47: AI API additional € per 500 paying users | C47: 50 | D47: 50 | E47: 50
A48: AI COSTS | B48: AI API monthly cap (€) | C48: 3500 | D48: 3500 | E48: 3500
A49: DEEP TECH
A50: DEEP TECH | B50: HealthKit + Health Connect build (one-off, spread M4–6) | C50: 8000 | D50: 8000 | E50: 8000
A51: DEEP TECH | B51: Oura Ring integration (one-off M15) | C51: 5000 | D51: 5000 | E51: 5000
A52: DEEP TECH | B52: Predictive AI dev cost/mo (M20–M23) | C52: 3000 | D52: 3000 | E52: 3000
A53: PEOPLE
A54: PEOPLE | B54: Founder stipends total/mo Y1 | C54: 900 | D54: 900 | E54: 900
A55: PEOPLE | B55: Founder stipends total/mo Y2 | C55: 9000 | D55: 9000 | E55: 9000
A56: PEOPLE | B56: Team salaries €/mo M3–M6 | C56: 5000 | D56: 6000 | E56: 7000
A57: PEOPLE | B57: Team salaries €/mo M7–M12 | C57: 9000 | D57: 11000 | E57: 13000
A58: PEOPLE | B58: Team salaries €/mo Y2 | C58: 30000 | D58: 38000 | E58: 46000
A59: PEOPLE | B59: Team salaries €/mo Y3 | C59: 48000 | D59: 85000 | E59: 105000
A60: PEOPLE | B60: Marketing content/tools base €/mo Y1 (excl. paid social) | C60: 1200 | D60: 1500 | E60: 2000
A61: PEOPLE | B61: Marketing content/tools base €/mo Y2 | C61: 2000 | D61: 2500 | E61: 3000
A62: PEOPLE | B62: Marketing content/tools base €/mo Y3 | C62: 3000 | D62: 3500 | E62: 4000
A63: PEOPLE | B63: Clinical partnerships cost €/mo Y1 (from M3) | C63: 900 | D63: 900 | E63: 900
A64: PEOPLE | B64: Clinical partnerships cost €/mo Y2 | C64: 1500 | D64: 1500 | E64: 1500
A65: PEOPLE | B65: Clinical partnerships cost €/mo Y3 | C65: 2200 | D65: 2200 | E65: 2200
... A67: PEOPLE | B67: Legal & admin €/mo M4+ (maintenance) | C67: 350 | D67: 350 | E67: 350
A68: INFRA
A69: INFRA | B69: Infrastructure base €/mo | C69: 600 | D69: 600 | E69: 700
A70: INFRA | B70: Infrastructure variable (€ per 400 users) | C70: 150 | D70: 150 | E70: 150
A71: INFRA | B71: Infrastructure monthly cap (€) | C71: 18000 | D71: 18000 | E71: 18000
A72: FUNDING
A73: FUNDING | B73: Pre-seed cash raised (M1) | C73: 350000 | D73: 350000 | E73: 350000
A74: FUNDING | B74: Seed round injection month | C74: 13 | D74: 13 | E74: 13
A75: FUNDING | B75: Seed round amount (€) | C75: 1500000 | D75: 3000000 | E75: 5000000
A76: PEOPLE | B76: Founder stipends total/mo Y3 | C76: 12000 | D76: 12000 | E76: 12000

Sheet Conservative
A1: NutriSync — Conservative Scenario | All inputs from Assumptions sheet | Blue = inputs, Black = formulas
A2: METRIC | B2: M1 | C2: M2 | D2: M3 | E2: M4 | F2: M5 | G2: M6 | H2: M7 | I2: M8 | J2: M9 | K2: M10 | L2: M11 | M2: M12 | N2: M13 | O2: M14 | P2: M15 | Q2: M16 | R2: M17 | S2: M18 | T2: M19 | U2: M20 | V2: M21 | W2: M22 | X2: M23 | Y2: M24 | Z2: M25 | AA2: M26 | AB2: M27 | AC2: M28 | AD2: M29 | AE2: M30 | AF2: M31 | AG2: M32 | AH2: M33 | AI2: M34 | AJ2: M35 | AK2: M36 | AL2: Y1 Total | AM2: Y2 Total | AN2: Y3 Total | AO2: Notes / Formula
A3: Year | B3: 1 | C3: 1 | D3: 1 | E3: 1 | F3: 1 | G3: 1 | H3: 1 | I3: 1 | J3: 1 | K3: 1 | L3: 1 | M3: 1 | N3: 2 | O3: 2 | P3: 2 | Q3: 2 | R3: 2 | S3: 2 | T3: 2 | U3: 2 | V3: 2 | W3: 2 | X3: 2 | Y3: 2 | Z3: 3 | AA3: 3 | AB3: 3 | AC3: 3 | AD3: 3 | AE3: 3 | AF3: 3 | AG3: 3 | AH3: 3 | AI3: 3 | AJ3: 3 | AK3: 3
A4: SECTION 1 — USER PROJECTIONS
A5: New organic free users/mo | B5: =Assumptions!C9 -> 320 | C5: =B5*(1+Assumptions!C10) -> 377.6 | D5: =C5*(1+Assumptions!C10) -> 445.568 | E5: =D5*(1+Assumptions!C10) -> 525.77024 | F5: =E5*(1+Assumptions!C10) -> 620.40888 | G5: =F5*(1+Assumptions!C10) -> 732.08248 | H5: =G5*(1+Assumptions!C10) -> 863.85733 | I5: =H5*(1+Assumptions!C10) -> 1019.3516 | J5: =I5*(1+Assumptions!C10) -> 1202.8349 | K5: =J5*(1+Assumptions!C10) -> 1419.3452 | L5: =K5*(1+Assumptions!C10) -> 1674.8274 | M5: =L5*(1+Assumptions!C10) -> 1976.2963 | N5: =M5*(1+Assumptions!C10) -> 2332.0296 | O5: =N5*(1+Assumptions!C10) -> 2751.795 | P5: =O5*(1+Assumptions!C10) -> 3247.1181 | Q5: =P5*(1+Assumptions!C10) -> 3831.5993 | R5: =Q5*(1+Assumptions!C10) -> 4521.2872 | S5: =R5*(1+Assumptions!C10) -> 5335.1189 | T5: =S5*(1+Assumptions!C10) -> 6295.4403 | U5: =T5*(1+Assumptions!C10) -> 7428.6196 | V5: =U5*(1+Assumptions!C10) -> 8765.7711 | W5: =V5*(1+Assumptions!C10) -> 10343.61 | X5: =W5*(1+Assumptions!C10) -> 12205.46 | Y5: =X5*(1+Assumptions!C10) -> 14402.442 | Z5: =Y5*(1+Assumptions!C10) -> 16994.882 | AA5: =Z5*(1+Assumptions!C10) -> 20053.961 | AB5: =AA5*(1+Assumptions!C10) -> 23663.674 | AC5: =AB5*(1+Assumptions!C10) -> 27923.135 | AD5: =AC5*(1+Assumptions!C10) -> 32949.299 | AE5: =AD5*(1+Assumptions!C10) -> 38880.173 | AF5: =AE5*(1+Assumptions!C10) -> 45878.604 | AG5: =AF5*(1+Assumptions!C10) -> 54136.753 | AH5: =AG5*(1+Assumptions!C10) -> 63881.369 | AI5: =AH5*(1+Assumptions!C10) -> 75380.015 | AJ5: =AI5*(1+Assumptions!C10) -> 88948.418 | AK5: =AJ5*(1+Assumptions!C10) -> 104959.13 | AL5: =SUM(B5:M5) -> 11177.942 | AM5: =SUM(N5:Y5) -> 81460.291 | AN5: =SUM(Z5:AK5) -> 593649.42 | AO5: Compounds from M1 at organic growth rate.
A6: → New paid: organic conversion (one-off per month's new free users) | B6: =B5*Assumptions!C11 -> 38.4 | C6: =C5*Assumptions!C11 -> 45.312 | D6: =D5*Assumptions!C11 -> 53.46816 | E6: =E5*Assumptions!C11 -> 63.092429 | F6: =F5*Assumptions!C11 -> 74.449066 | G6: =G5*Assumptions!C11 -> 87.849898 | H6: =H5*Assumptions!C11 -> 103.66288 | I6: =I5*Assumptions!C11 -> 122.3222 | J6: =J5*Assumptions!C11 -> 144.34019 | K6: =K5*Assumptions!C11 -> 170.32143 | L6: =L5*Assumptions!C11 -> 200.97929 | M6: =M5*Assumptions!C11 -> 237.15556 | N6: =N5*Assumptions!C11 -> 279.84356 | O6: =O5*Assumptions!C11 -> 330.2154 | P6: =P5*Assumptions!C11 -> 389.65417 | Q6: =Q5*Assumptions!C11 -> 459.79192 | R6: =R5*Assumptions!C11 -> 542.55446 | S6: =S5*Assumptions!C11 -> 640.21427 | T6: =T5*Assumptions!C11 -> 755.45284 | U6: =U5*Assumptions!C11 -> 891.43435 | V6: =V5*Assumptions!C11 -> 1051.8925 | W6: =W5*Assumptions!C11 -> 1241.2332 | X6: =X5*Assumptions!C11 -> 1464.6552 | Y6: =Y5*Assumptions!C11 -> 1728.2931 | Z6: =Z5*Assumptions!C11 -> 2039.3858 | AA6: =AA5*Assumptions!C11 -> 2406.4753 | AB6: =AB5*Assumptions!C11 -> 2839.6408 | AC6: =AC5*Assumptions!C11 -> 3350.7762 | AD6: =AD5*Assumptions!C11 -> 3953.9159 | AE6: =AE5*Assumptions!C11 -> 4665.6208 | AF6: =AF5*Assumptions!C11 -> 5505.4325 | AG6: =AG5*Assumptions!C11 -> 6496.4104 | AH6: =AH5*Assumptions!C11 -> 7665.7642 | AI6: =AI5*Assumptions!C11 -> 9045.6018 | AJ6: =AJ5*Assumptions!C11 -> 10673.81 | AK6: =AK5*Assumptions!C11 -> 12595.096 | AL6: =SUM(B6:M6) -> 1341.3531 | AM6: =SUM(N6:Y6) -> 9775.2349 | AN6: =SUM(Z6:AK6) -> 71237.93 | AO6: 5–8% one-off per month (NOT monthly to pool). Benchmark: RevenueCat H&F median 6.9%.
A7: → New paid: paid social (budget ÷ CAC) | B7: =0 -> 0 | C7: =0 -> 0 | D7: =0 -> 0 | E7: =Assumptions!C12/Assumptions!C15 -> 450 | F7: =Assumptions!C12/Assumptions!C15 -> 450 | G7: =Assumptions!C12/Assumptions!C15 -> 450 | H7: =Assumptions!C12/Assumptions!C15 -> 450 | I7: =Assumptions!C12/Assumptions!C15 -> 450 | J7: =Assumptions!C12/Assumptions!C15 -> 450 | K7: =Assumptions!C12/Assumptions!C15 -> 450 | L7: =Assumptions!C12/Assumptions!C15 -> 450 | M7: =Assumptions!C12/Assumptions!C15 -> 450 | N7: =Assumptions!C13/Assumptions!C16 -> 750 | O7: =Assumptions!C13/Assumptions!C16 -> 750 | P7: =Assumptions!C13/Assumptions!C16 -> 750 | Q7: =Assumptions!C13/Assumptions!C16 -> 750 | R7: =Assumptions!C13/Assumptions!C16 -> 750 | S7: =Assumptions!C13/Assumptions!C16 -> 750 | T7: =Assumptions!C13/Assumptions!C16 -> 750 | U7: =Assumptions!C13/Assumptions!C16 -> 750 | V7: =Assumptions!C13/Assumptions!C16 -> 750 | W7: =Assumptions!C13/Assumptions!C16 -> 750 | X7: =Assumptions!C13/Assumptions!C16 -> 750 | Y7: =Assumptions!C13/Assumptions!C16 -> 750 | Z7: =Assumptions!C14/Assumptions!C16 -> 750 | AA7: =Assumptions!C14/Assumptions!C16 -> 750 | AB7: =Assumptions!C14/Assumptions!C16 -> 750 | AC7: =Assumptions!C14/Assumptions!C16 -> 750 | AD7: =Assumptions!C14/Assumptions!C16 -> 750 | AE7: =Assumptions!C14/Assumptions!C16 -> 750 | AF7: =Assumptions!C14/Assumptions!C16 -> 750 | AG7: =Assumptions!C14/Assumptions!C16 -> 750 | AH7: =Assumptions!C14/Assumptions!C16 -> 750 | AI7: =Assumptions!C14/Assumptions!C16 -> 750 | AJ7: =Assumptions!C14/Assumptions!C16 -> 750 | AK7: =Assumptions!C14/Assumptions!C16 -> 750 | AL7: =SUM(B7:M7) -> 4050 | AM7: =SUM(N7:Y7) -> 9000 | AN7: =SUM(Z7:AK7) -> 9000 | AO7: Budget / CAC. CAC corrected: €20 Y1 conservative (not €6–8; install alone $3.70–4.70).
A8: % of paid users with wearable connected | B8: =0 -> 0 | C8: =0 -> 0 | D8: =0 -> 0 | E8: =MIN(Assumptions!C22,1*Assumptions!C21) -> 0.015 | F8: =MIN(Assumptions!C22,2*Assumptions!C21) -> 0.03 | G8: =MIN(Assumptions!C22,3*Assumptions!C21) -> 0.045 | H8: =MIN(Assumptions!C22,4*Assumptions!C21) -> 0.06 | I8: =MIN(Assumptions!C22,5*Assumptions!C21) -> 0.075 | J8: =MIN(Assumptions!C22,6*Assumptions!C21) -> 0.09 | K8: =MIN(Assumptions!C22,7*Assumptions!C21) -> 0.105 | L8: =MIN(Assumptions!C22,8*Assumptions!C21) -> 0.12 | M8: =MIN(Assumptions!C22,9*Assumptions!C21) -> 0.135 | N8: =MIN(Assumptions!C22,10*Assumptions!C21) -> 0.15 | O8: =MIN(Assumptions!C22,11*Assumptions!C21) -> 0.165 | P8: =MIN(Assumptions!C22,12*Assumptions!C21) -> 0.18 | Q8: =MIN(Assumptions!C22,13*Assumptions!C21) -> 0.195 | R8: =MIN(Assumptions!C22,14*Assumptions!C21) -> 0.21 | S8: =MIN(Assumptions!C22,15*Assumptions!C21) -> 0.225 | T8: =MIN(Assumptions!C22,16*Assumptions!C21) -> 0.24 | U8: =MIN(Assumptions!C22,17*Assumptions!C21) -> 0.255 | V8: =MIN(Assumptions!C22,18*Assumptions!C21) -> 0.27 | W8: =MIN(Assumptions!C22,19*Assumptions!C21) -> 0.285 | X8: =MIN(Assumptions!C22,20*Assumptions!C21) -> 0.3 | Y8: =MIN(Assumptions!C22,21*Assumptions!C21) -> 0.3 | Z8: =MIN(Assumptions!C22,22*Assumptions!C21) -> 0.3 | AA8: =MIN(Assumptions!C22,23*Assumptions!C21) -> 0.3 | AB8: =MIN(Assumptions!C22,24*Assumptions!C21) -> 0.3 | AC8: =MIN(Assumptions!C22,25*Assumptions!C21) -> 0.3 | AD8: =MIN(Assumptions!C22,26*Assumptions!C21) -> 0.3 | AE8: =MIN(Assumptions!C22,27*Assumptions!C21) -> 0.3 | AF8: =MIN(Assumptions!C22,28*Assumptions!C21) -> 0.3 | AG8: =MIN(Assumptions!C22,29*Assumptions!C21) -> 0.3 | AH8: =MIN(Assumptions!C22,30*Assumptions!C21) -> 0.3 | AI8: =MIN(Assumptions!C22,31*Assumptions!C21) -> 0.3 | AJ8: =MIN(Assumptions!C22,32*Assumptions!C21) -> 0.3 | AK8: =MIN(Assumptions!C22,33*Assumptions!C21) -> 0.3 | AL8: =M8 -> 0.135 | AM8: =Y8 -> 0.3 | AN8: =AK8 -> 0.3 | AO8: Ramps +1.5–2.5%pts/mo from M4; capped at adoption ceiling.
A9: Blended monthly churn (wearable-adjusted) | B9: =Assumptions!C18*(1-B8*Assumptions!C23) -> 0.09 | C9: =Assumptions!C18*(1-C8*Assumptions!C23) -> 0.09 | D9: =Assumptions!C18*(1-D8*Assumptions!C23) -> 0.09 | E9: =Assumptions!C18*(1-E8*Assumptions!C23) -> 0.089595 | F9: =Assumptions!C18*(1-F8*Assumptions!C23) -> 0.08919 | G9: =Assumptions!C18*(1-G8*Assumptions!C23) -> 0.088785 | H9: =Assumptions!C18*(1-H8*Assumptions!C23) -> 0.08838 | I9: =Assumptions!C18*(1-I8*Assumptions!C23) -> 0.087975 | J9: =Assumptions!C18*(1-J8*Assumptions!C23) -> 0.08757 | K9: =Assumptions!C18*(1-K8*Assumptions!C23) -> 0.087165 | L9: =Assumptions!C18*(1-L8*Assumptions!C23) -> 0.08676 | M9: =Assumptions!C18*(1-M8*Assumptions!C23) -> 0.086355 | N9: =Assumptions!C19*(1-N8*Assumptions!C23) -> 0.0764 | O9: =Assumptions!C19*(1-O8*Assumptions!C23) -> 0.07604 | P9: =Assumptions!C19*(1-P8*Assumptions!C23) -> 0.07568 | Q9: =Assumptions!C19*(1-Q8*Assumptions!C23) -> 0.07532 | R9: =Assumptions!C19*(1-R8*Assumptions!C23) -> 0.07496 | S9: =Assumptions!C19*(1-S8*Assumptions!C23) -> 0.0746 | T9: =Assumptions!C19*(1-T8*Assumptions!C23) -> 0.07424 | U9: =Assumptions!C19*(1-U8*Assumptions!C23) -> 0.07388 | V9: =Assumptions!C19*(1-V8*Assumptions!C23) -> 0.07352 | W9: =Assumptions!C19*(1-W8*Assumptions!C23) -> 0.07316 | X9: =Assumptions!C19*(1-X8*Assumptions!C23) -> 0.0728 | Y9: =Assumptions!C19*(1-Y8*Assumptions!C23) -> 0.0728 | Z9: =Assumptions!C20*(1-Z8*Assumptions!C23) -> 0.05915 | AA9: =Assumptions!C20*(1-AA8*Assumptions!C23) -> 0.05915 | AB9: =Assumptions!C20*(1-AB8*Assumptions!C23) -> 0.05915 | AC9: =Assumptions!C20*(1-AC8*Assumptions!C23) -> 0.05915 | AD9: =Assumptions!C20*(1-AD8*Assumptions!C23) -> 0.05915 | AE9: =Assumptions!C20*(1-AE8*Assumptions!C23) -> 0.05915 | AF9: =Assumptions!C20*(1-AF8*Assumptions!C23) -> 0.05915 | AG9: =Assumptions!C20*(1-AG8*Assumptions!C23) -> 0.05915 | AH9: =Assumptions!C20*(1-AH8*Assumptions!C23) -> 0.05915 | AI9: =Assumptions!C20*(1-AI8*Assumptions!C23) -> 0.05915 | AJ9: =Assumptions!C20*(1-AJ8*Assumptions!C23) -> 0.05915 | AK9: =Assumptions!C20*(1-AK8*Assumptions!C23) -> 0.05915 | AL9: =AVERAGE(B9:M9) -> 0.08848125 | AM9: =AVERAGE(N9:Y9) -> 0.07445 | AN9: =AVERAGE(Z9:AK9) -> 0.05915 | AO9: base × (1 − wearable% × reduction_factor).
A10: Premium upgrades from basic (M13+) | B10: =0 -> 0 | C10: =0 -> 0 | D10: =0 -> 0 | E10: =0 -> 0 | F10: =0 -> 0 | G10: =0 -> 0 | H10: =0 -> 0 | I10: =0 -> 0 | ... M10: =0 -> 0 | N10: =M11*Assumptions!C26 -> 29.167483 | O10: =N11*Assumptions!C26 -> 34.444158 | P10: =O11*Assumptions!C26 -> 39.668308 | Q10: =P11*Assumptions!C26 -> 44.916105 | R10: =Q11*Assumptions!C26 -> 50.269592 | S10: =R11*Assumptions!C26 -> 55.81852 | T10: =S11*Assumptions!C26 -> 61.662427 | U10: =T11*Assumptions!C26 -> 67.913036 | V10: =U11*Assumptions!C26 -> 74.697031 | W10: =V11*Assumptions!C26 -> 82.159271 | X10: =W11*Assumptions!C26 -> 90.466553 | Y10: =X11*Assumptions!C26 -> 99.812003 | Z10: =Y11*Assumptions!C26 -> 110.3843 | AA10: =Z11*Assumptions!C26 -> 123.94758 | AB10: =AA11*Assumptions!C26 -> 139.36004 | AC10: =AB11*Assumptions!C26 -> 156.994 | AD10: =AC11*Assumptions!C26 -> 177.28617 | AE10: =AD11*Assumptions!C26 -> 200.74941 | AF10: =AE11*Assumptions!C26 -> 227.98662 | AG10: =AF11*Assumptions!C26 -> 259.70706 | AH10: =AG11*Assumptions!C26 -> 296.74566 | AI10: =AH11*Assumptions!C26 -> 340.08579 | AJ10: =AI11*Assumptions!C26 -> 390.88609 | AK10: =AJ11*Assumptions!C26 -> 450.51211 | AL10: =SUM(B10:M10) -> 0 | AM10: =SUM(N10:Y10) -> 730.99449 | AN10: =SUM(Z10:AK10) -> 2874.6448 | AO10: 0.75–1.5%/mo of basic base (corrected from 4–8%/mo compounding).
A11: B2C basic subscribers (EoM) | B11: =B6+B7 -> 38.4 | C11: =B11*(1-C9)-C10+C6+C7 -> 80.256 | D11: =C11*(1-D9)-D10+D6+D7 -> 126.50112 | E11: =D11*(1-E9)-E10+E6+E7 -> 628.25968 | F11: =E11*(1-F9)-F10+F6+F7 -> 1096.6743 | G11: =F11*(1-G9)-G10+G6+G7 -> 1537.1559 | H11: =G11*(1-H9)-H10+H6+H7 -> 1954.965 | I11: =H11*(1-I9)-I10+I6+I7 -> 2355.2991 | J11: =I11*(1-J9)-J10+J6+J7 -> 2743.3858 | ... AK11: =AJ11*(1-AK9)-AK10+AK6+AK7 -> 69409.826 | AL11: =M11 -> 3888.9977 | AM11: =Y11 -> 14717.906 | AN11: =AK11 -> 69409.826 | AO11: Prior × (1-churn) - upgrades + new converts.
A12: B2C premium subscribers (EoM — upgrade from basic, not added on top) | B12: =0 -> 0 | C12: =0 -> 0 | D12: =0 -> 0 | E12: =0 -> 0 | F12: =0 -> 0 | G12: =0 -> 0 | H12: =0 -> 0 | I12: =0 -> 0 | ... M12: =0 -> 0 | N12: =N10 -> 29.167483 | O12: =N12*(1-Assumptions!C27)+O10 -> 62.444941 | P12: =O12*(1-Assumptions!C27)+P10 -> 99.615452 | Q12: =P12*(1-Assumptions!C27)+Q10 -> 140.54694 | R12: =Q12*(1-Assumptions!C27)+R10 -> 185.19465 | S12: =R12*(1-Assumptions!C27)+S10 -> 233.60539 | T12: =S12*(1-Assumptions!C27)+T10 -> 285.9236 | U12: =T12*(1-Assumptions!C27)+U10 -> 342.39969 | V12: =U12*(1-Assumptions!C27)+V10 -> 403.40073 | W12: =V12*(1-Assumptions!C27)+W10 -> 469.42398 | X12: =W12*(1-Assumptions!C27)+X10 -> 541.11357 | Y12: =X12*(1-Assumptions!C27)+Y10 -> 619.28103 | Z12: =Y12*(1-Assumptions!C27)+Z10 -> 704.89409 | AA12: =Z12*(1-Assumptions!C27)+AA10 -> 800.6459 | AB12: =AA12*(1-Assumptions!C27)+AB10 -> 907.9801 | AC12: =AB12*(1-Assumptions!C27)+AC10 -> 1028.6549 | AD12: =AC12*(1-Assumptions!C27)+AD10 -> 1164.7949 | AE12: =AD12*(1-Assumptions!C27)+AE10 -> 1318.9525 | AF12: =AE12*(1-Assumptions!C27)+AF10 -> 1494.181 | AG12: =AF12*(1-Assumptions!C27)+AG10 -> 1694.1208 | AH12: =AG12*(1-Assumptions!C27)+AH10 -> 1923.1016 | AI12: =AH12*(1-Assumptions!C27)+AI10 -> 2186.2634 | AJ12: =AI12*(1-Assumptions!C27)+AJ10 -> 2489.6989 | AK12: =AJ12*(1-Assumptions!C27)+AK10 -> 2840.6231 | AL12: =M12 -> 0 | AM12: =Y12 -> 619.28103 | AN12: =AK12 -> 2840.6231 | AO12: Premium users MOVE from basic — no double-counting.
A13: B2B contracts signed (cumulative) | B13: =0 -> 0 | C13: =0 -> 0 | D13: =0 -> 0 | E13: =0 -> 0 | F13: =0 -> 0 | G13: =Assumptions!C29 -> 1.5 | H13: =G13+Assumptions!C29 -> 3 | I13: =H13+Assumptions!C29 -> 4.5 | J13: =I13+Assumptions!C29 -> 6 | K13: =J13+Assumptions!C29 -> 7.5 | L13: =K13+Assumptions!C29 -> 9 | M13: =L13+Assumptions!C29 -> 10.5 | N13: =M13+Assumptions!C30 -> 13.5 | O13: =N13+Assumptions!C30 -> 16.5 | P13: =O13+Assumptions!C30 -> 19.5 | Q13: =P13+Assumptions!C30 -> 22.5 | R13: =Q13+Assumptions!C30 -> 25.5 | S13: =R13+Assumptions!C30 -> 28.5 | T13: =S13+Assumptions!C30 -> 31.5 | U13: =T13+Assumptions!C30 -> 34.5 | V13: =U13+Assumptions!C30 -> 37.5 | W13: =V13+Assumptions!C30 -> 40.5 | X13: =W13+Assumptions!C30 -> 43.5 | Y13: =X13+Assumptions!C30 -> 46.5 | Z13: =Y13+Assumptions!C31 -> 50 | AA13: =Z13+Assumptions!C31 -> 53.5 | AB13: =AA13+Assumptions!C31 -> 57 | AC13: =AB13+Assumptions!C31 -> 60.5 | AD13: =AC13+Assumptions!C31 -> 64 | AE13: =AD13+Assumptions!C31 -> 67.5 | AF13: =AE13+Assumptions!C31 -> 71 | AG13: =AF13+Assumptions!C31 -> 74.5 | AH13: =AG13+Assumptions!C31 -> 78 | AI13: =AH13+Assumptions!C31 -> 81.5 | AJ13: =AI13+Assumptions!C31 -> 85 | AK13: =AJ13+Assumptions!C31 -> 88.5 | AL13: =M13 -> 10.5 | AM13: =Y13 -> 46.5 | AN13: =AK13 -> 88.5
A14: B2B employees active (EoM) | B14: =0 -> 0 | C14: =0 -> 0 | D14: =0 -> 0 | E14: =0 -> 0 | F14: =0 -> 0 | G14: =Assumptions!C29*Assumptions!C32 -> 180 | H14: =G14*(1-(1-(1-Assumptions!C33)^(1/12)))+Assumptions!C29*Assumptions!C32 -> 356.68378 | I14: =H14*(1-(1-(1-Assumptions!C33)^(1/12)))+Assumptions!C29*Assumptions!C32 -> 530.11242 | J14: =I14*(1-(1-(1-Assumptions!C33)^(1/12)))+Assumptions!C29*Assumptions!C32 -> 700.34591 | K14: =J14*(1-(1-(1-Assumptions!C33)^(1/12)))+Assumptions!C29*Assumptions!C32 -> 867.44311 | L14: =K14*(1-(1-(1-Assumptions!C33)^(1/12)))+Assumptions!C29*Assumptions!C32 -> 1031.4618 | M14: =L14*(1-(1-(1-Assumptions!C33)^(1/12)))+Assumptions!C29*Assumptions!C32 -> 1192.4587 | N14: =M14*(1-(1-(1-Assumptions!C33)^(1/12)))+Assumptions!C30*Assumptions!C32 -> 1530.4895 | O14: =N14*(1-(1-(1-Assumptions!C33)^(1/12)))+Assumptions!C30*Assumptions!C32 -> 1862.2925 | P14: =O14*(1-(1-(1-Assumptions!C33)^(1/12)))+Assumptions!C30*Assumptions!C32 -> 2187.9826 | Q14: =P14*(1-(1-(1-Assumptions!C33)^(1/12)))+Assumptions!C30*Assumptions!C32 -> 2507.6724 | R14: =Q14*(1-(1-(1-Assumptions!C33)^(1/12)))+Assumptions!C30*Assumptions!C32 -> 2821.4724 | S14: =R14*(1-(1-(1-Assumptions!C33)^(1/12)))+Assumptions!C30*Assumptions!C32 -> 3129.4911 | T14: =S14*(1-(1-(1-Assumptions!C33)^(1/12)))+Assumptions!C30*Assumptions!C32 -> 3431.835 | U14: =T14*(1-(1-(1-Assumptions!C33)^(1/12)))+Assumptions!C30*Assumptions!C32 -> 3728.6087 | V14: =U14*(1-(1-(1-Assumptions!C33)^(1/12)))+Assumptions!C30*Assumptions!C32 -> 4019.9148 | W14: =V14*(1-(1-(1-Assumptions!C33)^(1/12)))+Assumptions!C30*Assumptions!C32 -> 4305.854 | X14: =W14*(1-(1-(1-Assumptions!C33)^(1/12)))+Assumptions!C30*Assumptions!C32 -> 4586.5252 | Y14: =X14*(1-(1-(1-Assumptions!C33)^(1/12)))+Assumptions!C30*Assumptions!C32 -> 4862.0255 | Z14: =Y14*(1-(1-(1-Assumptions!C33)^(1/12)))+Assumptions!C31*Assumptions!C32 -> 5192.4501 | AA14: =Z14*(1-(1-(1-Assumptions!C33)^(1/12)))+Assumptions!C31*Assumptions!C32 -> 5516.7872 | AB14: =AA14*(1-(1-(1-Assumptions!C33)^(1/12)))+Assumptions!C31*Assumptions!C32 -> 5835.1488 | AC14: =AB14*(1-(1-(1-Assumptions!C33)^(1/12)))+Assumptions!C31*Assumptions!C32 -> 6147.6451 | AD14: =AC14*(1-(1-(1-Assumptions!C33)^(1/12)))+Assumptions!C31*Assumptions!C32 -> 6454.3842 | AE14: =AD14*(1-(1-(1-Assumptions!C33)^(1/12)))+Assumptions!C31*Assumptions!C32 -> 6755.472 | AF14: =AE14*(1-(1-(1-Assumptions!C33)^(1/12)))+Assumptions!C31*Assumptions!C32 -> 7051.0128 | AG14: =AF14*(1-(1-(1-Assumptions!C33)^(1/12)))+Assumptions!C31*Assumptions!C32 -> 7341.1087 | AH14: =AG14*(1-(1-(1-Assumptions!C33)^(1/12)))+Assumptions!C31*Assumptions!C32 -> 7625.86 | AI14: =AH14*(1-(1-(1-Assumptions!C33)^(1/12)))+Assumptions!C31*Assumptions!C32 -> 7905.3652 | AJ14: =AI14*(1-(1-(1-Assumptions!C33)^(1/12)))+Assumptions!C31*Assumptions!C32 -> 8179.7209 | AK14: =AJ14*(1-(1-(1-Assumptions!C33)^(1/12)))+Assumptions!C31*Assumptions!C32 -> 8449.0221 | AL14: =M14 -> 1192.4587 | AM14: =Y14 -> 4862.0255 | AN14: =AK14 -> 8449.0221 | AO14: Prior × (1-monthly logo churn) + new seats.
A15: TOTAL PAYING USERS (EoM) | B15: =B11+B12+B14 -> 38.4 | C15: =C11+C12+C14 -> 80.256 | D15: =D11+D12+D14 -> 126.50112 | E15: =E11+E12+E14 -> 628.25968 | F15: =F11+F12+F14 -> 1096.6743 | G15: =G11+G12+G14 -> 1717.1559 | H15: =H11+H12+H14 -> 2311.6488 | I15: =I11+I12+I14 -> 2885.4116 | ... AK15: =AK11+AK12+AK14 -> 80699.471 | AL15: =M15 -> 5081.4564 | AM15: =Y15 -> 20199.213 | AN15: =AK15 -> 80699.471 | AO15: Basic + premium + B2B. Premium NOT double-counted.
A17: SECTION 2 — REVENUE
A18: B2C basic subscriptions | B18: =B11*Assumptions!C4 -> 191.616 | C18: =(B11+C11)/2*Assumptions!C4 -> 296.04672 | D18: =(C11+D11)/2*Assumptions!C4 -> 515.85901 | E18: =(D11+E11)/2*Assumptions!C4 -> 1883.1282 | F18: =(E11+F11)/2*Assumptions!C4 -> 4303.7102 | G18: =(F11+G11)/2*Assumptions!C4 -> 6571.4064 | H18: =(G11+H11)/2*Assumptions!C4 -> 8712.8417 | I18: =(H11+I11)/2*Assumptions!C4 -> 10754.109 | J18: =(I11+J11)/2*Assumptions!C4 -> 12721.219 | K18: =(J11+K11)/2*Assumptions!C4 -> 14640.575 | L18: =(K11+L11)/2*Assumptions!C4 -> 16539.481 | M18: =(L11+M11)/2*Assumptions!C4 -> 18446.704 | N18: =(M11+N11)/2*Assumptions!C4 -> 21161.472 | O18: =(N11+O11)/2*Assumptions!C4 -> 24654.747 | P18: =(O11+P11)/2*Assumptions!C4 -> 28138.415 | Q18: =(P11+Q11)/2*Assumptions!C4 -> 31665.108 | R18: =(Q11+R11)/2*Assumptions!C4 -> 35291.979 | S18: =(R11+S11)/2*Assumptions!C4 -> 39081.995 | T18: =(S11+T11)/2*Assumptions!C4 -> 43105.437 | U18: =(T11+U11)/2*Assumptions!C4 -> 47441.616 | V18: =(U11+V11)/2*Assumptions!C4 -> 52180.863 | W18: =(V11+W11)/2*Assumptions!C4 -> 57426.858 | X18: =(W11+X11)/2*Assumptions!C4 -> 63299.333 | Y18: =(X11+Y11)/2*Assumptions!C4 -> 69925.302 | Z18: =(Y11+Z11)/2*Assumptions!C4 -> 77954.404 | AA18: =(Z11+AA11)/2*Assumptions!C4 -> 87593.666 | AB18: =(AA11+AB11)/2*Assumptions!C4 -> 98587.108 | AC18: =(AB11+AC11)/2*Assumptions!C4 -> 111203.87 | AD18: =(AC11+AD11)/2*Assumptions!C4 -> 125759.84 | AE18: =(AD11+AE11)/2*Assumptions!C4 -> 142626.19 | AF18: =(AE11+AF11)/2*Assumptions!C4 -> 162239.43 | AG18: =(AF11+AG11)/2*Assumptions!C4 -> 185113.27 | AH18: =(AG11+AH11)/2*Assumptions!C4 -> 211852.6 | AI18: =(AH11+AI11)/2*Assumptions!C4 -> 243169.98 | AJ18: =(AI11+AJ11)/2*Assumptions!C4 -> 279905.13 | AK18: =(AJ11+AK11)/2*Assumptions!C4 -> 323047.88 | AL18: =SUM(B18:M18) -> 95576.696 | AM18: =SUM(N18:Y18) -> 513373.13 | AN18: =SUM(Z18:AK18) -> 2049053.4
A19: B2C premium subscriptions (from M13) | B19: =0 -> 0 | C19: =0 -> 0 | D19: =0 -> 0 | E19: =0 -> 0 | F19: =0 -> 0 | G19: =0 -> 0 | H19: =0 -> 0 | I19: =0 -> 0 | ... M19: =0 -> 0 | N19: =N12*Assumptions!C5 -> 378.8856 | O19: =(N12+O12)/2*Assumptions!C5 -> 595.02269 | P19: =(O12+P12)/2*Assumptions!C5 -> 1052.5823 | Q19: =(P12+Q12)/2*Assumptions!C5 -> 1559.8547 | R19: =(Q12+R12)/2*Assumptions!C5 -> 2115.6916 | S19: =(R12+S12)/2*Assumptions!C5 -> 2720.1063 | T19: =(S12+T12)/2*Assumptions!C5 -> 3374.3408 | U19: =(T12+U12)/2*Assumptions!C5 -> 4080.9598 | V19: =(U12+V12)/2*Assumptions!C5 -> 4843.9737 | W19: =(V12+W12)/2*Assumptions!C5 -> 5668.9965 | X19: =(W12+X12)/2*Assumptions!C5 -> 6563.4414 | Y19: =(X12+Y12)/2*Assumptions!C5 -> 7536.7629 | Z19: =(Y12+Z12)/2*Assumptions!C5 -> 8600.5174 | AA19: =(Z12+AA12)/2*Assumptions!C5 -> 9778.4822 | AB19: =(AA12+AB12)/2*Assumptions!C5 -> 11097.526 | AC19: =(AB12+AC12)/2*Assumptions!C5 -> 12578.444 | AD19: =(AC12+AD12)/2*Assumptions!C5 -> 14246.456 | AE19: =(AD12+AE12)/2*Assumptions!C5 -> 16131.939 | AF19: =(AE12+AF12)/2*Assumptions!C5 -> 18271.302 | AG19: =(AF12+AG12)/2*Assumptions!C5 -> 20708.02 | AH19: =(AG12+AH12)/2*Assumptions!C5 -> 23493.86 | AI19: =(AH12+AI12)/2*Assumptions!C5 -> 26690.326 | AJ19: =(AI12+AJ12)/2*Assumptions!C5 -> 30370.375 | AK19: =(AJ12+AK12)/2*Assumptions!C5 -> 34620.441 | AL19: =SUM(B19:M19) -> 0 | AM19: =SUM(N19:Y19) -> 40490.618 | AN19: =SUM(Z19:AK19) -> 226587.69
A20: B2B corporate wellbeing | B20: =0 -> 0 | C20: =0 -> 0 | D20: =0 -> 0 | E20: =0 -> 0 | F20: =0 -> 0 | G20: =G14*Assumptions!C6 -> 718.2 | H20: =H14*Assumptions!C6 -> 1423.1683 | I20: =I14*Assumptions!C6 -> 2115.1486 | J20: =J14*Assumptions!C6 -> 2794.3802 | K20: =K14*Assumptions!C6 -> 3461.098 | L20: =L14*Assumptions!C6 -> 4115.5326 | M20: =M14*Assumptions!C6 -> 4757.9102 | N20: =N14*Assumptions!C7 -> 9167.6319 | O20: =O14*Assumptions!C7 -> 11155.132 | P20: =P14*Assumptions!C7 -> 13106.016 | Q20: =Q14*Assumptions!C7 -> 15020.958 | R20: =R14*Assumptions!C7 -> 16900.62 | S20: =S14*Assumptions!C7 -> 18745.652 | T20: =T14*Assumptions!C7 -> 20556.692 | U20: =U14*Assumptions!C7 -> 22334.366 | V20: =V14*Assumptions!C7 -> 24079.289 | W20: =W14*Assumptions!C7 -> 25792.065 | X20: =X14*Assumptions!C7 -> 27473.286 | Y20: =Y14*Assumptions!C7 -> 29123.533 | Z20: =Z14*Assumptions!C7 -> 31102.776 | AA20: =AA14*Assumptions!C7 -> 33045.555 | AB20: =AB14*Assumptions!C7 -> 34952.541 | AC20: =AC14*Assumptions!C7 -> 36824.394 | AD20: =AD14*Assumptions!C7 -> 38661.761 | AE20: =AE14*Assumptions!C7 -> 40465.277 | AF20: =AF14*Assumptions!C7 -> 42235.567 | AG20: =AG14*Assumptions!C7 -> 43973.241 | AH20: =AH14*Assumptions!C7 -> 45678.901 | AI20: =AI14*Assumptions!C7 -> 47353.137 | AJ20: =AJ14*Assumptions!C7 -> 48996.528 | AK20: =AK14*Assumptions!C7 -> 50609.642 | AL20: =SUM(B20:M20) -> 19385.438 | AM20: =SUM(N20:Y20) -> 233455.24 | AN20: =SUM(Z20:AK20) -> 493899.32
A21: Events & workshops (net) | B21: =0 -> 0 | C21: =0 -> 0 | D21: =Assumptions!C35 -> 500 | E21: =Assumptions!C35 -> 500 | F21: =Assumptions!C35 -> 500 | G21: =Assumptions!C35 -> 500 | H21: =Assumptions!C35 -> 500 | I21: =Assumptions!C35 -> 500 | J21: =Assumptions!C35 -> 500 | K21: =Assumptions!C35 -> 500 | L21: =Assumptions!C35 -> 500 | M21: =Assumptions!C35 -> 500 | N21: =Assumptions!C36 -> 1000 | O21: =Assumptions!C36 -> 1000 | P21: =Assumptions!C36 -> 1000 | Q21: =Assumptions!C36 -> 1000 | R21: =Assumptions!C36 -> 1000 | S21: =Assumptions!C36 -> 1000 | T21: =Assumptions!C36 -> 1000 | U21: =Assumptions!C36 -> 1000 | V21: =Assumptions!C36 -> 1000 | W21: =Assumptions!C36 -> 1000 | X21: =Assumptions!C36 -> 1000 | Y21: =Assumptions!C36 -> 1000 | Z21: =Assumptions!C37 -> 1500 | AA21: =Assumptions!C37 -> 1500 | AB21: =Assumptions!C37 -> 1500 | AC21: =Assumptions!C37 -> 1500 | AD21: =Assumptions!C37 -> 1500 | AE21: =Assumptions!C37 -> 1500 | AF21: =Assumptions!C37 -> 1500 | AG21: =Assumptions!C37 -> 1500 | AH21: =Assumptions!C37 -> 1500 | AI21: =Assumptions!C37 -> 1500 | AJ21: =Assumptions!C37 -> 1500 | AK21: =Assumptions!C37 -> 1500 | AL21: =SUM(B21:M21) -> 5000 | AM21: =SUM(N21:Y21) -> 12000 | AN21: =SUM(Z21:AK21) -> 18000 | AO21: €420 earned to date → €500 conservative. NOT in MRR.
A22: Clinical B2B referral fees (€/contract/mo, from M6) | B22: =0 -> 0 | C22: =0 -> 0 | D22: =0 -> 0 | E22: =0 -> 0 | F22: =0 -> 0 | G22: =G13*Assumptions!C39 -> 450 | H22: =H13*Assumptions!C39 -> 900 | I22: =I13*Assumptions!C39 -> 1350 | J22: =J13*Assumptions!C39 -> 1800 | K22: =K13*Assumptions!C39 -> 2250 | L22: =L13*Assumptions!C39 -> 2700 | M22: =M13*Assumptions!C39 -> 3150 | N22: =N13*Assumptions!C39 -> 4050 | O22: =O13*Assumptions!C39 -> 4950 | P22: =P13*Assumptions!C39 -> 5850 | Q22: =Q13*Assumptions!C39 -> 6750 | R22: =R13*Assumptions!C39 -> 7650 | S22: =S13*Assumptions!C39 -> 8550 | T22: =T13*Assumptions!C39 -> 9450 | U22: =U13*Assumptions!C39 -> 10350 | V22: =V13*Assumptions!C39 -> 11250 | W22: =W13*Assumptions!C39 -> 12150 | X22: =X13*Assumptions!C39 -> 13050 | Y22: =Y13*Assumptions!C39 -> 13950 | Z22: =Z13*Assumptions!C39 -> 15000 | AA22: =AA13*Assumptions!C39 -> 16050 | AB22: =AB13*Assumptions!C39 -> 17100 | AC22: =AC13*Assumptions!C39 -> 18150 | AD22: =AD13*Assumptions!C39 -> 19200 | AE22: =AE13*Assumptions!C39 -> 20250 | AF22: =AF13*Assumptions!C39 -> 21300 | AG22: =AG13*Assumptions!C39 -> 22350 | AH22: =AH13*Assumptions!C39 -> 23400 | AI22: =AI13*Assumptions!C39 -> 24450 | AJ22: =AJ13*Assumptions!C39 -> 25500 | AK22: =AK13*Assumptions!C39 -> 26550 | AL22: =SUM(B22:M22) -> 12600 | AM22: =SUM(N22:Y22) -> 108000 | AN22: =SUM(Z22:AK22) -> 249300
A23: Brand partnerships (0 in conservative; upside only) | B23: =0 -> 0 | C23: =0 -> 0 | D23: =0 -> 0 | E23: =0 -> 0 | F23: =0 -> 0 | G23: =0 -> 0 | H23: =0 -> 0 | I23: =0 -> 0 | ... Y23: =0 -> 0 | Z23: =Assumptions!C38 -> 0 | AA23: =Assumptions!C38 -> 0 | AB23: =Assumptions!C38 -> 0 | AC23: =Assumptions!C38 -> 0 | AD23: =Assumptions!C38 -> 0 | AE23: =Assumptions!C38 -> 0 | AF23: =Assumptions!C38 -> 0 | AG23: =Assumptions!C38 -> 0 | AH23: =Assumptions!C38 -> 0 | AI23: =Assumptions!C38 -> 0 | AJ23: =Assumptions!C38 -> 0 | AK23: =Assumptions!C38 -> 0 | AL23: =SUM(B23:M23) -> 0 | AM23: =SUM(N23:Y23) -> 0 | AN23: =SUM(Z23:AK23) -> 0
A24: TOTAL REVENUE | B24: =B18+B19+B20+B21+B22+B23 -> 191.616 | C24: =C18+C19+C20+C21+C22+C23 -> 296.04672 | D24: =D18+D19+D20+D21+D22+D23 -> 1015.859 | E24: =E18+E19+E20+E21+E22+E23 -> 2383.1282 | F24: =F18+F19+F20+F21+F22+F23 -> 4803.7102 | G24: =G18+G19+G20+G21+G22+G23 -> 8239.6064 | H24: =H18+H19+H20+H21+H22+H23 -> 11536.01 | I24: =I18+I19+I20+I21+I22+I23 -> 14719.258 | ... AK24: =AK18+AK19+AK20+AK21+AK22+AK23 -> 436327.96 | AL24: =SUM(B24:M24) -> 132562.13 | AM24: =SUM(N24:Y24) -> 907318.98 | AN24: =SUM(Z24:AK24) -> 3036840.4
A25: MRR — recurring only (basic + premium + B2B) | B25: =B18+B19+B20 -> 191.616 | C25: =C18+C19+C20 -> 296.04672 | D25: =D18+D19+D20 -> 515.85901 | E25: =E18+E19+E20 -> 1883.1282 | F25: =F18+F19+F20 -> 4303.7102 | G25: =G18+G19+G20 -> 7289.6064 | H25: =H18+H19+H20 -> 10136.01 | I25: =I18+I19+I20 -> 12869.258 | ... AK25: =AK18+AK19+AK20 -> 408277.96 | AL25: =M25 -> 23204.614 | AM25: =Y25 -> 106585.6 | AN25: =AK25 -> 408277.96 | AO25: Events and clinical fees excluded — VCs strip them.
A26: ARR (MRR × 12) | B26: =B25*12 -> 2299.392 | C26: =C25*12 -> 3552.5606 | D26: =D25*12 -> 6190.3082 | E26: =E25*12 -> 22597.538 | F26: =F25*12 -> 51644.522 | G26: =G25*12 -> 87475.276 | H26: =H25*12 -> 121632.12 | I26: =I25*12 -> 154431.09 | ... AK26: =AK25*12 -> 4899335.5 | AL26: =M26 -> 278455.37 | AM26: =Y26 -> 1279027.2 | AN26: =AK26 -> 4899335.5
A28: SECTION 3 — COSTS
A29: [helper] Trailing-12-month B2C gross revenue (fee-tier test) | B29: =SUM(B18:B18)+SUM(B19:B19) -> 191.616 | C29: =SUM(B18:C18)+SUM(B19:C19) -> 487.66272 | D29: =SUM(B18:D18)+SUM(B19:D19) -> 1003.5217 | E29: =SUM(B18:E18)+SUM(B19:E19) -> 2886.6499 | F29: =SUM(B18:F18)+SUM(B19:F19) -> 7190.3601 | G29: =SUM(B18:G18)+SUM(B19:G19) -> 13761.766 | H29: =SUM(B18:H18)+SUM(B19:H19) -> 22474.608 | I29: =SUM(B18:I18)+SUM(B19:I19) -> 33228.717 | J29: =SUM(B18:J18)+SUM(B19:J19) -> 45949.936 | K29: =SUM(B18:K18)+SUM(B19:K19) -> 60590.511 | L29: =SUM(B18:L18)+SUM(B19:L19) -> 77129.992 | M29: =SUM(B18:M18)+SUM(B19:M19) -> 95576.696 | N29: =SUM(C18:N18)+SUM(C19:N19) -> 116925.44 | O29: =SUM(D18:O18)+SUM(D19:O19) -> 141879.16 | P29: =SUM(E18:P18)+SUM(E19:P19) -> 170554.3 | Q29: =SUM(F18:Q18)+SUM(F19:Q19) -> 201896.13 | R29: =SUM(G18:R18)+SUM(G19:R19) -> 235000.09 | S29: =SUM(H18:S18)+SUM(H19:S19) -> 270230.79 | T29: =SUM(I18:T18)+SUM(I19:T19) -> 307997.72 | ... AK29: =SUM(Z18:AK18)+SUM(Z19:AK19) -> 2275641
A30: App store fees — CORRECTED (15% under $1M; 30% above) | B30: =IF(B29<Assumptions!C43,(B18+B19)*Assumptions!C41,(B18+B19)*Assumptions!C42) -> 28.7424 | C30: =IF(C29<Assumptions!C43,(C18+C19)*Assumptions!C41,(C18+C19)*Assumptions!C42) -> 44.407008 | D30: =IF(D29<Assumptions!C43,(D18+D19)*Assumptions!C41,(D18+D19)*Assumptions!C42) -> 77.378852 | E30: =IF(E29<Assumptions!C43,(E18+E19)*Assumptions!C41,(E18+E19)*Assumptions!C42) -> 282.46923 | F30: =IF(F29<Assumptions!C43,(F18+F19)*Assumptions!C41,(F18+F19)*Assumptions!C42) -> 645.55653 | G30: =IF(G29<Assumptions!C43,(G18+G19)*Assumptions!C41,(G18+G19)*Assumptions!C42) -> 985.71095 | H30: =IF(H29<Assumptions!C43,(H18+H19)*Assumptions!C41,(H18+H19)*Assumptions!C42) -> 1306.9263 | I30: =IF(I29<Assumptions!C43,(I18+I19)*Assumptions!C41,(I18+I19)*Assumptions!C42) -> 1613.1163 | J30: =IF(J29<Assumptions!C43,(J18+J19)*Assumptions!C41,(J18+J19)*Assumptions!C42) -> 1908.1828 | K30: =IF(K29<Assumptions!C43,(K18+K19)*Assumptions!C41,(K18+K19)*Assumptions!C42) -> 2196.0862 | L30: =IF(L29<Assumptions!C43,(L18+L19)*Assumptions!C41,(L18+L19)*Assumptions!C42) -> 2480.9222 | M30: =IF(M29<Assumptions!C43,(M18+M19)*Assumptions!C41,(M18+M19)*Assumptions!C42) -> 2767.0056 | N30: =IF(N29<Assumptions!C43,(N18+N19)*Assumptions!C41,(N18+N19)*Assumptions!C42) -> 3231.0537 | O30: =IF(O29<Assumptions!C43,(O18+O19)*Assumptions!C41,(O18+O19)*Assumptions!C42) -> 3787.4654 | P30: =IF(P29<Assumptions!C43,(P18+P19)*Assumptions!C41,(P18+P19)*Assumptions!C42) -> 4378.6495 | Q30: =IF(Q29<Assumptions!C43,(Q18+Q19)*Assumptions!C41,(Q18+Q19)*Assumptions!C42) -> 4983.7445 | R30: =IF(R29<Assumptions!C43,(R18+R19)*Assumptions!C41,(R18+R19)*Assumptions!C42) -> 5611.1505 | S30: =IF(S29<Assumptions!C43,(S18+S19)*Assumptions!C41,(S18+S19)*Assumptions!C42) -> 6270.3152 | T30: =IF(T29<Assumptions!C43,(T18+T19)*Assumptions!C41,(T18+T19)*Assumptions!C42) -> 6971.9667 | U30: =IF(U29<Assumptions!C43,(U18+U19)*Assumptions!C41,(U18+U19)*Assumptions!C42) -> 7728.3863 | V30: =IF(V29<Assumptions!C43,(V18+V19)*Assumptions!C41,(V18+V19)*Assumptions!C42) -> 8553.7255 | W30: =IF(W29<Assumptions!C43,(W18+W19)*Assumptions!C41,(W18+W19)*Assumptions!C42) -> 9464.3781 | X30: =IF(X29<Assumptions!C43,(X18+X19)*Assumptions!C41,(X18+X19)*Assumptions!C42) -> 10479.416 | Y30: =IF(Y29<Assumptions!C43,(Y18+Y19)*Assumptions!C41,(Y18+Y19)*Assumptions!C42) -> 11619.31 | Z30: =IF(Z29<Assumptions!C43,(Z18+Z19)*Assumptions!C41,(Z18+Z19)*Assumptions!C42) -> 12983.238 | AA30: =IF(AA29<Assumptions!C43,(AA18+AA19)*Assumptions!C41,(AA18+AA19)*Assumptions!C42) -> 14605.822 | AB30: =IF(AB29<Assumptions!C43,(AB18+AB19)*Assumptions!C41,(AB18+AB19)*Assumptions!C42) -> 16452.695 | AC30: =IF(AC29<Assumptions!C43,(AC18+AC19)*Assumptions!C41,(AC18+AC19)*Assumptions!C42) -> 18567.347 | AD30: =IF(AD29<Assumptions!C43,(AD18+AD19)*Assumptions!C41,(AD18+AD19)*Assumptions!C42) -> 42001.888 | AE30: =IF(AE29<Assumptions!C43,(AE18+AE19)*Assumptions!C41,(AE18+AE19)*Assumptions!C42) -> 47627.438 | AF30: =IF(AF29<Assumptions!C43,(AF18+AF19)*Assumptions!C41,(AF18+AF19)*Assumptions!C42) -> 54153.22 | AG30: =IF(AG29<Assumptions!C43,(AG18+AG19)*Assumptions!C41,(AG18+AG19)*Assumptions!C42) -> 61746.387 | AH30: =IF(AH29<Assumptions!C43,(AH18+AH19)*Assumptions!C41,(AH18+AH19)*Assumptions!C42) -> 70603.937 | AI30: =IF(AI29<Assumptions!C43,(AI18+AI19)*Assumptions!C41,(AI18+AI19)*Assumptions!C42) -> 80958.092 | AJ30: =IF(AJ29<Assumptions!C43,(AJ18+AJ19)*Assumptions!C41,(AJ18+AJ19)*Assumptions!C42) -> 93082.652 | AK30: =IF(AK29<Assumptions!C43,(AK18+AK19)*Assumptions!C41,(AK18+AK19)*Assumptions!C42) -> 107300.5 | AL30: =SUM(B30:M30) -> 14336.504 | AM30: =SUM(N30:Y30) -> 83079.562 | AN30: =SUM(Z30:AK30) -> 620083.21 | AO30: CORRECTED: 15% until trailing-12mo B2C > ~$1M; 30% after. Original was backwards.
A31: Payment processing (Stripe 1.4% on B2B) | B31: =B20*Assumptions!C44 -> 0 | C31: =C20*Assumptions!C44 -> 0 | D31: =D20*Assumptions!C44 -> 0 | E31: =E20*Assumptions!C44 -> 0 | F31: =F20*Assumptions!C44 -> 0 | G31: =G20*Assumptions!C44 -> 10.0548 | H31: =H20*Assumptions!C44 -> 19.924356 | I31: =I20*Assumptions!C44 -> 29.61208 | J31: =J20*Assumptions!C44 -> 39.121323 | K31: =K20*Assumptions!C44 -> 48.455372 | L31: =L20*Assumptions!C44 -> 57.617456 | M31: =M20*Assumptions!C44 -> 66.610743 | N31: =N20*Assumptions!C44 -> 128.34685 | O31: =O20*Assumptions!C44 -> 156.17185 | P31: =P20*Assumptions!C44 -> 183.48422 | Q31: =Q20*Assumptions!C44 -> 210.29341 | R31: =R20*Assumptions!C44 -> 236.60867 | S31: =S20*Assumptions!C44 -> 262.43912 | T31: =T20*Assumptions!C44 -> 287.79368 | U31: =U20*Assumptions!C44 -> 312.68112 | V31: =V20*Assumptions!C44 -> 337.11005 | W31: =W20*Assumptions!C44 -> 361.08892 | X31: =X20*Assumptions!C44 -> 384.626 | Y31: =Y20*Assumptions!C44 -> 407.72946 | Z31: =Z20*Assumptions!C44 -> 435.43887 | AA31: =AA20*Assumptions!C44 -> 462.63777 | AB31: =AB20*Assumptions!C44 -> 489.33558 | AC31: =AC20*Assumptions!C44 -> 515.54152 | AD31: =AD20*Assumptions!C44 -> 541.26466 | AE31: =AE20*Assumptions!C44 -> 566.51388 | AF31: =AF20*Assumptions!C44 -> 591.29793 | AG31: =AG20*Assumptions!C44 -> 615.62537 | AH31: =AH20*Assumptions!C44 -> 639.50462 | AI31: =AI20*Assumptions!C44 -> 662.94392 | AJ31: =AJ20*Assumptions!C44 -> 685.95139 | AK31: =AK20*Assumptions!C44 -> 708.53499 | AL31: =SUM(B31:M31) -> 271.39613 | AM31: =SUM(N31:Y31) -> 3268.3734 | AN31: =SUM(Z31:AK31) -> 6914.5905
A32: AI API costs (from M6, scales with users, capped) | B32: =0 -> 0 | C32: =0 -> 0 | D32: =0 -> 0 | E32: =0 -> 0 | F32: =0 -> 0 | G32: =MIN(Assumptions!C48,Assumptions!C46+(G15/500)*Assumptions!C47) -> 571.71559 | H32: =MIN(Assumptions!C48,Assumptions!C46+(H15/500)*Assumptions!C47) -> 631.16488 | I32: =MIN(Assumptions!C48,Assumptions!C46+(I15/500)*Assumptions!C47) -> 688.54116 | J32: =MIN(Assumptions!C48,Assumptions!C46+(J15/500)*Assumptions!C47) -> 744.37317 | K32: =MIN(Assumptions!C48,Assumptions!C46+(K15/500)*Assumptions!C47) -> 799.20231 | L32: =MIN(Assumptions!C48,Assumptions!C46+(L15/500)*Assumptions!C47) -> 853.59325 | M32: =MIN(Assumptions!C48,Assumptions!C46+(M15/500)*Assumptions!C47) -> 908.14564 | N32: =MIN(Assumptions!C48,Assumptions!C46+(N15/500)*Assumptions!C47) -> 1015.2211 | O32: =MIN(Assumptions!C48,Assumptions!C46+(O15/500)*Assumptions!C47) -> 1121.3845 | P32: =MIN(Assumptions!C48,Assumptions!C46+(P15/500)*Assumptions!C47) -> 1227.6412 | Q32: =MIN(Assumptions!C48,Assumptions!C46+(Q15/500)*Assumptions!C47) -> 1335.0832 | R32: =MIN(Assumptions!C48,Assumptions!C46+(R15/500)*Assumptions!C47) -> 1444.9136 | S32: =MIN(Assumptions!C48,Assumptions!C46+(S15/500)*Assumptions!C47) -> 1558.4753 | T32: =MIN(Assumptions!C48,Assumptions!C46+(T15/500)*Assumptions!C47) -> 1677.283 | U32: =MIN(Assumptions!C48,Assumptions!C46+(U15/500)*Assumptions!C47) -> 1803.0612 | V32: =MIN(Assumptions!C48,Assumptions!C46+(V15/500)*Assumptions!C47) -> 1937.7885 | W32: =MIN(Assumptions!C48,Assumptions!C46+(W15/500)*Assumptions!C47) -> 2083.7485 | X32: =MIN(Assumptions!C48,Assumptions!C46+(X15/500)*Assumptions!C47) -> 2243.5906 | Y32: =MIN(Assumptions!C48,Assumptions!C46+(Y15/500)*Assumptions!C47) -> 2419.9213 | Z32: =MIN(Assumptions!C48,Assumptions!C46+(Z15/500)*Assumptions!C47) -> 2642.3688 | AA32: =MIN(Assumptions!C48,Assumptions!C46+(AA15/500)*Assumptions!C47) -> 2889.8771 | AB32: =MIN(Assumptions!C48,Assumptions!C46+(AB15/500)*Assumptions!C47) -> 3167.5662 | AC32: =MIN(Assumptions!C48,Assumptions!C46+(AC15/500)*Assumptions!C47) -> 3481.4456 | AD32: =MIN(Assumptions!C48,Assumptions!C46+(AD15/500)*Assumptions!C47) -> 3500 | AE32: =MIN(Assumptions!C48,Assumptions!C46+(AE15/500)*Assumptions!C47) -> 3500 | AF32: =MIN(Assumptions!C48,Assumptions!C46+(AF15/500)*Assumptions!C47) -> 3500 | AG32: =MIN(Assumptions!C48,Assumptions!C46+(AG15/500)*Assumptions!C47) -> 3500 | AH32: =MIN(Assumptions!C48,Assumptions!C46+(AH15/500)*Assumptions!C47) -> 3500 | AI32: =MIN(Assumptions!C48,Assumptions!C46+(AI15/500)*Assumptions!C47) -> 3500 | AJ32: =MIN(Assumptions!C48,Assumptions!C46+(AJ15/500)*Assumptions!C47) -> 3500 | AK32: =MIN(Assumptions!C48,Assumptions!C46+(AK15/500)*Assumptions!C47) -> 3500 | AL32: =SUM(B32:M32) -> 5196.736 | AM32: =SUM(N32:Y32) -> 19868.112 | AN32: =SUM(Z32:AK32) -> 40181.258
A33: Infrastructure & hosting (base + variable, capped) | B33: =80 -> 80 | C33: =80 -> 80 | D33: =MIN(Assumptions!C71,Assumptions!C69+(D15/400)*Assumptions!C70) -> 647.43792 | E33: =MIN(Assumptions!C71,Assumptions!C69+(E15/400)*Assumptions!C70) -> 835.59738 | F33: =MIN(Assumptions!C71,Assumptions!C69+(F15/400)*Assumptions!C70) -> 1011.2528 | G33: =MIN(Assumptions!C71,Assumptions!C69+(G15/400)*Assumptions!C70) -> 1243.9335 | H33: =MIN(Assumptions!C71,Assumptions!C69+(H15/400)*Assumptions!C70) -> 1466.8683 | I33: =MIN(Assumptions!C71,Assumptions!C69+(I15/400)*Assumptions!C70) -> 1682.0293 | J33: =MIN(Assumptions!C71,Assumptions!C69+(J15/400)*Assumptions!C70) -> 1891.3994 | K33: =MIN(Assumptions!C71,Assumptions!C69+(K15/400)*Assumptions!C70) -> 2097.0087 | L33: =MIN(Assumptions!C71,Assumptions!C69+(L15/400)*Assumptions!C70) -> 2300.9747 | M33: =MIN(Assumptions!C71,Assumptions!C69+(M15/400)*Assumptions!C70) -> 2505.5461 | N33: =MIN(Assumptions!C71,Assumptions!C69+(N15/400)*Assumptions!C70) -> 2907.0792 | O33: =MIN(Assumptions!C71,Assumptions!C69+(O15/400)*Assumptions!C70) -> 3305.192 | P33: =MIN(Assumptions!C71,Assumptions!C69+(P15/400)*Assumptions!C70) -> 3703.6545 | Q33: =MIN(Assumptions!C71,Assumptions!C69+(Q15/400)*Assumptions!C70) -> 4106.5619 | R33: =MIN(Assumptions!C71,Assumptions!C69+(R15/400)*Assumptions!C70) -> 4518.4261 | S33: =MIN(Assumptions!C71,Assumptions!C69+(S15/400)*Assumptions!C70) -> 4944.2825 | T33: =MIN(Assumptions!C71,Assumptions!C69+(T15/400)*Assumptions!C70) -> 5389.8113 | U33: =MIN(Assumptions!C71,Assumptions!C69+(U15/400)*Assumptions!C70) -> 5861.4797 | V33: =MIN(Assumptions!C71,Assumptions!C69+(V15/400)*Assumptions!C70) -> 6366.7069 | W33: =MIN(Assumptions!C71,Assumptions!C69+(W15/400)*Assumptions!C70) -> 6914.0569 | X33: =MIN(Assumptions!C71,Assumptions!C69+(X15/400)*Assumptions!C70) -> 7513.4647 | Y33: =MIN(Assumptions!C71,Assumptions!C69+(Y15/400)*Assumptions!C70) -> 8174.7048 | Z33: =MIN(Assumptions!C71,Assumptions!C69+(Z15/400)*Assumptions!C70) -> 9008.883 | AA33: =MIN(Assumptions!C71,Assumptions!C69+(AA15/400)*Assumptions!C70) -> 9937.0392 | AB33: =MIN(Assumptions!C71,Assumptions!C69+(AB15/400)*Assumptions!C70) -> 10978.373 | AC33: =MIN(Assumptions!C71,Assumptions!C69+(AC15/400)*Assumptions!C70) -> 12155.421 | AD33: =MIN(Assumptions!C71,Assumptions!C69+(AD15/400)*Assumptions!C70) -> 13494.663 | AE33: =MIN(Assumptions!C71,Assumptions!C69+(AE15/400)*Assumptions!C70) -> 15027.24 | AF33: =MIN(Assumptions!C71,Assumptions!C69+(AF15/400)*Assumptions!C70) -> 16789.801 | AG33: =MIN(Assumptions!C71,Assumptions!C69+(AG15/400)*Assumptions!C70) -> 18000 | AH33: =MIN(Assumptions!C71,Assumptions!C69+(AH15/400)*Assumptions!C70) -> 18000 | AI33: =MIN(Assumptions!C71,Assumptions!C69+(AI15/400)*Assumptions!C70) -> 18000 | AJ33: =MIN(Assumptions!C71,Assumptions!C69+(AJ15/400)*Assumptions!C70) -> 18000 | AK33: =MIN(Assumptions!C71,Assumptions!C69+(AK15/400)*Assumptions!C70) -> 18000 | AL33: =SUM(B33:M33) -> 15842.048 | AM33: =SUM(N33:Y33) -> 63705.42 | AN33: =SUM(Z33:AK33) -> 177391.42
A34: Founder stipends ×3 | B34: =Assumptions!C54 -> 900 | C34: =Assumptions!C54 -> 900 | D34: =Assumptions!C54 -> 900 | E34: =Assumptions!C54 -> 900 | F34: =Assumptions!C54 -> 900 | G34: =Assumptions!C54 -> 900 | H34: =Assumptions!C54 -> 900 | I34: =Assumptions!C54 -> 900 | J34: =Assumptions!C54 -> 900 | K34: =Assumptions!C54 -> 900 | L34: =Assumptions!C54 -> 900 | M34: =Assumptions!C54 -> 900 | N34: =Assumptions!C55 -> 9000 | O34: =Assumptions!C55 -> 9000 | P34: =Assumptions!C55 -> 9000 | Q34: =Assumptions!C55 -> 9000 | R34: =Assumptions!C55 -> 9000 | S34: =Assumptions!C55 -> 9000 | T34: =Assumptions!C55 -> 9000 | U34: =Assumptions!C55 -> 9000 | V34: =Assumptions!C55 -> 9000 | W34: =Assumptions!C55 -> 9000 | X34: =Assumptions!C55 -> 9000 | Y34: =Assumptions!C55 -> 9000 | Z34: =Assumptions!C76 -> 12000 | AA34: =Assumptions!C76 -> 12000 | AB34: =Assumptions!C76 -> 12000 | AC34: =Assumptions!C76 -> 12000 | AD34: =Assumptions!C76 -> 12000 | AE34: =Assumptions!C76 -> 12000 | AF34: =Assumptions!C76 -> 12000 | AG34: =Assumptions!C76 -> 12000 | AH34: =Assumptions!C76 -> 12000 | AI34: =Assumptions!C76 -> 12000 | AJ34: =Assumptions!C76 -> 12000 | AK34: =Assumptions!C76 -> 12000 | AL34: =SUM(B34:M34) -> 10800 | AM34: =SUM(N34:Y34) -> 108000 | AN34: =SUM(Z34:AK34) -> 144000
A35: Team salaries & contractors | B35: =0 -> 0 | C35: =0 -> 0 | D35: =Assumptions!C56 -> 5000 | E35: =Assumptions!C56 -> 5000 | F35: =Assumptions!C56 -> 5000 | G35: =Assumptions!C56 -> 5000 | H35: =Assumptions!C57 -> 9000 | I35: =Assumptions!C57 -> 9000 | J35: =Assumptions!C57 -> 9000 | K35: =Assumptions!C57 -> 9000 | L35: =Assumptions!C57 -> 9000 | M35: =Assumptions!C57 -> 9000 | N35: =Assumptions!C58 -> 30000 | O35: =Assumptions!C58 -> 30000 | P35: =Assumptions!C58 -> 30000 | Q35: =Assumptions!C58 -> 30000 | R35: =Assumptions!C58 -> 30000 | S35: =Assumptions!C58 -> 30000 | T35: =Assumptions!C58 -> 30000 | U35: =Assumptions!C58 -> 30000 | V35: =Assumptions!C58 -> 30000 | W35: =Assumptions!C58 -> 30000 | X35: =Assumptions!C58 -> 30000 | Y35: =Assumptions!C58 -> 30000 | Z35: =Assumptions!C59 -> 48000 | AA35: =Assumptions!C59 -> 48000 | AB35: =Assumptions!C59 -> 48000 | AC35: =Assumptions!C59 -> 48000 | AD35: =Assumptions!C59 -> 48000 | AE35: =Assumptions!C59 -> 48000 | AF35: =Assumptions!C59 -> 48000 | AG35: =Assumptions!C59 -> 48000 | AH35: =Assumptions!C59 -> 48000 | AI35: =Assumptions!C59 -> 48000 | AJ35: =Assumptions!C59 -> 48000 | AK35: =Assumptions!C59 -> 48000 | AL35: =SUM(B35:M35) -> 74000 | AM35: =SUM(N35:Y35) -> 360000 | AN35: =SUM(Z35:AK35) -> 576000
A36: Marketing (content/tools base + paid social) | B36: =Assumptions!C60 -> 1200 | C36: =Assumptions!C60 -> 1200 | D36: =Assumptions!C60 -> 1200 | E36: =Assumptions!C60+Assumptions!C12 -> 10200 | F36: =Assumptions!C60+Assumptions!C12 -> 10200 | G36: =Assumptions!C60+Assumptions!C12 -> 10200 | H36: =Assumptions!C60+Assumptions!C12 -> 10200 | I36: =Assumptions!C60+Assumptions!C12 -> 10200 | J36: =Assumptions!C60+Assumptions!C12 -> 10200 | K36: =Assumptions!C60+Assumptions!C12 -> 10200 | L36: =Assumptions!C60+Assumptions!C12 -> 10200 | M36: =Assumptions!C60+Assumptions!C12 -> 10200 | N36: =Assumptions!C61+Assumptions!C13 -> 20000 | O36: =Assumptions!C61+Assumptions!C13 -> 20000 | P36: =Assumptions!C61+Assumptions!C13 -> 20000 | Q36: =Assumptions!C61+Assumptions!C13 -> 20000 | R36: =Assumptions!C61+Assumptions!C13 -> 20000 | S36: =Assumptions!C61+Assumptions!C13 -> 20000 | T36: =Assumptions!C61+Assumptions!C13 -> 20000 | U36: =Assumptions!C61+Assumptions!C13 -> 20000 | V36: =Assumptions!C61+Assumptions!C13 -> 20000 | W36: =Assumptions!C61+Assumptions!C13 -> 20000 | X36: =Assumptions!C61+Assumptions!C13 -> 20000 | Y36: =Assumptions!C61+Assumptions!C13 -> 20000 | Z36: =Assumptions!C62+Assumptions!C14 -> 21000 | AA36: =Assumptions!C62+Assumptions!C14 -> 21000 | AB36: =Assumptions!C62+Assumptions!C14 -> 21000 | AC36: =Assumptions!C62+Assumptions!C14 -> 21000 | AD36: =Assumptions!C62+Assumptions!C14 -> 21000 | AE36: =Assumptions!C62+Assumptions!C14 -> 21000 | AF36: =Assumptions!C62+Assumptions!C14 -> 21000 | AG36: =Assumptions!C62+Assumptions!C14 -> 21000 | AH36: =Assumptions!C62+Assumptions!C14 -> 21000 | AI36: =Assumptions!C62+Assumptions!C14 -> 21000 | AJ36: =Assumptions!C62+Assumptions!C14 -> 21000 | AK36: =Assumptions!C62+Assumptions!C14 -> 21000 | AL36: =SUM(B36:M36) -> 95400 | AM36: =SUM(N36:Y36) -> 240000 | AN36: =SUM(Z36:AK36) -> 252000
A37: Clinical partnerships (cost) | B37: =0 -> 0 | C37: =0 -> 0 | D37: =Assumptions!C63 -> 900 | E37: =Assumptions!C63 -> 900 | F37: =Assumptions!C63 -> 900 | G37: =Assumptions!C63 -> 900 | H37: =Assumptions!C63 -> 900 | I37: =Assumptions!C63 -> 900 | J37: =Assumptions!C63 -> 900 | K37: =Assumptions!C63 -> 900 | L37: =Assumptions!C63 -> 900 | M37: =Assumptions!C63 -> 900 | N37: =Assumptions!C64 -> 1500 | O37: =Assumptions!C64 -> 1500 | P37: =Assumptions!C64 -> 1500 | Q37: =Assumptions!C64 -> 1500 | R37: =Assumptions!C64 -> 1500 | S37: =Assumptions!C64 -> 1500 | T37: =Assumptions!C64 -> 1500 | U37: =Assumptions!C64 -> 1500 | V37: =Assumptions!C64 -> 1500 | W37: =Assumptions!C64 -> 1500 | X37: =Assumptions!C64 -> 1500 | Y37: =Assumptions!C64 -> 1500 | Z37: =Assumptions!C65 -> 2200 | AA37: =Assumptions!C65 -> 2200 | AB37: =Assumptions!C65 -> 2200 | AC37: =Assumptions!C65 -> 2200 | AD37: =Assumptions!C65 -> 2200 | AE37: =Assumptions!C65 -> 2200 | AF37: =Assumptions!C65 -> 2200 | AG37: =Assumptions!C65 -> 2200 | AH37: =Assumptions!C65 -> 2200 | AI37: =Assumptions!C65 -> 2200 | AJ37: =Assumptions!C65 -> 2200 | AK37: =Assumptions!C65 -> 2200 | AL37: =SUM(B37:M37) -> 9000 | AM37: =SUM(N37:Y37) -> 18000 | AN37: =SUM(Z37:AK37) -> 26400
A38: Legal & admin | B38: =Assumptions!C66 -> 800 | C38: =Assumptions!C66 -> 800 | D38: =Assumptions!C66 -> 800 | E38: =Assumptions!C67 -> 350 | F38: =Assumptions!C67 -> 350 | G38: =Assumptions!C67 -> 350 | H38: =Assumptions!C67 -> 350 | I38: =Assumptions!C67 -> 350 | J38: =Assumptions!C67 -> 350 | K38: =Assumptions!C67 -> 350 | L38: =Assumptions!C67 -> 350 | M38: =Assumptions!C67 -> 350 | N38: =Assumptions!C67 -> 350 | O38: =Assumptions!C67 -> 350 | P38: =Assumptions!C67 -> 350 | Q38: =Assumptions!C67 -> 350 | R38: =Assumptions!C67 -> 350 | S38: =Assumptions!C67 -> 350 | T38: =Assumptions!C67 -> 350 | U38: =Assumptions!C67 -> 350 | V38: =Assumptions!C67 -> 350 | W38: =Assumptions!C67 -> 350 | X38: =Assumptions!C67 -> 350 | Y38: =Assumptions!C67 -> 350 | Z38: =Assumptions!C67 -> 350 | AA38: =Assumptions!C67 -> 350 | AB38: =Assumptions!C67 -> 350 | AC38: =Assumptions!C67 -> 350 | AD38: =Assumptions!C67 -> 350 | AE38: =Assumptions!C67 -> 350 | AF38: =Assumptions!C67 -> 350 | AG38: =Assumptions!C67 -> 350 | AH38: =Assumptions!C67 -> 350 | AI38: =Assumptions!C67 -> 350 | AJ38: =Assumptions!C67 -> 350 | AK38: =Assumptions!C67 -> 350 | AL38: =SUM(B38:M38) -> 5550 | AM38: =SUM(N38:Y38) -> 4200 | AN38: =SUM(Z38:AK38) -> 4200
A39: HealthKit + Health Connect build (M4–6, one-off) | B39: =0 -> 0 | C39: =0 -> 0 | D39: =0 -> 0 | E39: =Assumptions!C50/3 -> 2666.6667 | F39: =Assumptions!C50/3 -> 2666.6667 | G39: =Assumptions!C50/3 -> 2666.6667 | H39: =0 -> 0 | I39: =0 -> 0 | J39: =0 -> 0 | K39: =0 -> 0 | L39: =0 -> 0 | M39: =0 -> 0 | N39: =0 -> 0 | O39: =0 -> 0 | ... AK39: =0 -> 0 | AL39: =SUM(B39:M39) -> 8000 | AM39: =SUM(N39:Y39) -> 0 | AN39: =SUM(Z39:AK39) -> 0
A40: Oura Ring integration (M15, one-off) | B40: =0 -> 0 | C40: =0 -> 0 | D40: =0 -> 0 | E40: =0 -> 0 | F40: =0 -> 0 | G40: =0 -> 0 | H40: =0 -> 0 | I40: =0 -> 0 | ... O40: =0 -> 0 | P40: =Assumptions!C51 -> 5000 | Q40: =0 -> 0 | R40: =0 -> 0 | S40: =0 -> 0 | T40: =0 -> 0 | U40: =0 -> 0 | V40: =0 -> 0 | W40: =0 -> 0 | X40: =0 -> 0 | ... AK40: =0 -> 0 | AL40: =SUM(B40:M40) -> 0 | AM40: =SUM(N40:Y40) -> 5000 | AN40: =SUM(Z40:AK40) -> 0
A41: Predictive AI dev (M20–M23, €3K/mo) | B41: =0 -> 0 | C41: =0 -> 0 | D41: =0 -> 0 | E41: =0 -> 0 | F41: =0 -> 0 | G41: =0 -> 0 | H41: =0 -> 0 | I41: =0 -> 0 | ... T41: =0 -> 0 | U41: =Assumptions!C52 -> 3000 | V41: =Assumptions!C52 -> 3000 | W41: =Assumptions!C52 -> 3000 | X41: =Assumptions!C52 -> 3000 | Y41: =0 -> 0 | Z41: =0 -> 0 | AA41: =0 -> 0 | AB41: =0 -> 0 | AC41: =0 -> 0 | AD41: =0 -> 0 | AE41: =0 -> 0 | AF41: =0 -> 0 | ... AK41: =0 -> 0 | AL41: =SUM(B41:M41) -> 0 | AM41: =SUM(N41:Y41) -> 12000 | AN41: =SUM(Z41:AK41) -> 0
A42: TOTAL COSTS | B42: =B30+B31+B32+B33+B34+B35+B36+B37+B38+B39+B40+B41 -> 3008.7424 | C42: =C30+C31+C32+C33+C34+C35+C36+C37+C38+C39+C40+C41 -> 3024.407 | D42: =D30+D31+D32+D33+D34+D35+D36+D37+D38+D39+D40+D41 -> 9524.8168 | E42: =E30+E31+E32+E33+E34+E35+E36+E37+E38+E39+E40+E41 -> 21134.733 | F42: =F30+F31+F32+F33+F34+F35+F36+F37+F38+F39+F40+F41 -> 21673.476 | G42: =G30+G31+G32+G33+G34+G35+G36+G37+G38+G39+G40+G41 -> 22828.081 | H42: =H30+H31+H32+H33+H34+H35+H36+H37+H38+H39+H40+H41 -> 24774.884 | I42: =I30+I31+I32+I33+I34+I35+I36+I37+I38+I39+I40+I41 -> 25363.299 | ... AK42: =AK30+AK31+AK32+AK33+AK34+AK35+AK36+AK37+AK38+AK39+AK40+AK41 -> 213059.03 | AL42: =SUM(B42:M42) -> 238396.68 | AM42: =SUM(N42:Y42) -> 917121.47 | AN42: =SUM(Z42:AK42) -> 1847170.5
A44: SECTION 4 — PROFIT & LOSS & CASH
A45: Gross margin % — FIXED (from annual revenue/COGS sums, not monthly average) | B45: =IF(B24=0,0,(B24-(B30+B31+B32))/B24) -> 0.85 | C45: =IF(C24=0,0,(C24-(C30+C31+C32))/C24) -> 0.85 | D45: =IF(D24=0,0,(D24-(D30+D31+D32))/D24) -> 0.92382914 | E45: =IF(E24=0,0,(E24-(E30+E31+E32))/E24) -> 0.88147124 | F45: =IF(F24=0,0,(F24-(F30+F31+F32))/F24) -> 0.86561293 | G45: =IF(G24=0,0,(G24-(G30+G31+G32))/G24) -> 0.80976259 | H45: =IF(H24=0,0,(H24-(H30+H31+H32))/H24) -> 0.83026926 | I45: =IF(I24=0,0,(I24-(I30+I31+I32))/I24) -> 0.84161772 | ... AK45: =IF(AK24=0,0,(AK24-(AK30+AK31+AK32))/AK24) -> 0.74443758 | AL45: =IF(SUM(B24:M24)=0,0,(SUM(B24:M24)-(SUM(B30:M30)+SUM(B31:M31)+SUM(B32:M32)))/SUM(B24:M24)) -> 0.8506011 | AM45: =IF(SUM(N24:Y24)=0,0,(SUM(N24:Y24)-(SUM(N30:Y30)+SUM(N31:Y31)+SUM(N32:Y32)))/SUM(N24:Y24)) -> 0.88293417 | AN45: =IF(SUM(Z24:AK24)=0,0,(SUM(Z24:AK24)-(SUM(Z30:AK30)+SUM(Z31:AK31)+SUM(Z32:AK32)))/SUM(Z24:AK24)) -> 0.78030486 | AO45: CORRECTED: annual cell = (annual revenue - annual COGS) / annual revenue. Old formula averaged monthly %s → ~6% nonsense.
A46: Net burn / profit (negative = burning) | B46: =B24-B42 -> -2817.1264 | C46: =C24-C42 -> -2728.3603 | D46: =D24-D42 -> -8508.9578 | E46: =E24-E42 -> -18751.605 | F46: =F24-F42 -> -16869.766 | G46: =G24-G42 -> -14588.475 | H46: =H24-H42 -> -13238.874 | I46: =I24-I42 -> -10644.041 | ... AK46: =AK24-AK42 -> 223268.93 | AL46: =SUM(B46:M46) -> -105834.55 | AM46: =SUM(N46:Y46) -> -9802.4836 | AN46: =SUM(Z46:AK46) -> 1189669.9
A47: Financing inflows (pre-seed M1; seed explicit, not in revenue) | B47: =Assumptions!C73 -> 350000 | C47: =IF(2=Assumptions!C74,Assumptions!C75,0) -> 0 | D47: =IF(3=Assumptions!C74,Assumptions!C75,0) -> 0 | E47: =IF(4=Assumptions!C74,Assumptions!C75,0) -> 0 | F47: =IF(5=Assumptions!C74,Assumptions!C75,0) -> 0 | G47: =IF(6=Assumptions!C74,Assumptions!C75,0) -> 0 | H47: =IF(7=Assumptions!C74,Assumptions!C75,0) -> 0 | I47: =IF(8=Assumptions!C74,Assumptions!C75,0) -> 0 | J47: =IF(9=Assumptions!C74,Assumptions!C75,0) -> 0 | K47: =IF(10=Assumptions!C74,Assumptions!C75,0) -> 0 | L47: =IF(11=Assumptions!C74,Assumptions!C75,0) -> 0 | M47: =IF(12=Assumptions!C74,Assumptions!C75,0) -> 0 | N47: =IF(13=Assumptions!C74,Assumptions!C75,0) -> 1500000 | O47: =IF(14=Assumptions!C74,Assumptions!C75,0) -> 0 | P47: =IF(15=Assumptions!C74,Assumptions!C75,0) -> 0 | Q47: =IF(16=Assumptions!C74,Assumptions!C75,0) -> 0 | R47: =IF(17=Assumptions!C74,Assumptions!C75,0) -> 0 | S47: =IF(18=Assumptions!C74,Assumptions!C75,0) -> 0 | T47: =IF(19=Assumptions!C74,Assumptions!C75,0) -> 0 | U47: =IF(20=Assumptions!C74,Assumptions!C75,0) -> 0 | V47: =IF(21=Assumptions!C74,Assumptions!C75,0) -> 0 | W47: =IF(22=Assumptions!C74,Assumptions!C75,0) -> 0 | X47: =IF(23=Assumptions!C74,Assumptions!C75,0) -> 0 | Y47: =IF(24=Assumptions!C74,Assumptions!C75,0) -> 0 | Z47: =IF(25=Assumptions!C74,Assumptions!C75,0) -> 0 | AA47: =IF(26=Assumptions!C74,Assumptions!C75,0) -> 0 | AB47: =IF(27=Assumptions!C74,Assumptions!C75,0) -> 0 | AC47: =IF(28=Assumptions!C74,Assumptions!C75,0) -> 0 | AD47: =IF(29=Assumptions!C74,Assumptions!C75,0) -> 0 | AE47: =IF(30=Assumptions!C74,Assumptions!C75,0) -> 0 | AF47: =IF(31=Assumptions!C74,Assumptions!C75,0) -> 0 | AG47: =IF(32=Assumptions!C74,Assumptions!C75,0) -> 0 | AH47: =IF(33=Assumptions!C74,Assumptions!C75,0) -> 0 | AI47: =IF(34=Assumptions!C74,Assumptions!C75,0) -> 0 | AJ47: =IF(35=Assumptions!C74,Assumptions!C75,0) -> 0 | AK47: =IF(36=Assumptions!C74,Assumptions!C75,0) -> 0 | AL47: =SUM(B47:M47) -> 350000 | AM47: =SUM(N47:Y47) -> 1500000 | AN47: =SUM(Z47:AK47) -> 0 | AO47: Seed shown as explicit injection so runway dependence is honest. NOT revenue.
A48: Ending cash (cumulative) | B48: =B46+B47 -> 347182.87 | C48: =B48+C46+C47 -> 344454.51 | D48: =C48+D46+D47 -> 335945.56 | E48: =D48+E46+E47 -> 317193.95 | F48: =E48+F46+F47 -> 300324.18 | G48: =F48+G46+G47 -> 285735.71 | H48: =G48+H46+H47 -> 272496.84 | I48: =H48+I46+I47 -> 261852.79 | J48: =I48+J46+J47 -> 253735.32 | ... AK48: =AJ48+AK46+AK47 -> 2924032.9 | AL48: =M48 -> 244165.45 | AM48: =Y48 -> 1734363 | AN48: =AK48 -> 2924032.9
A50: SECTION 5 — UNIT ECONOMICS (single consistent method; all linked to assumptions)
A51: LTV — B2C basic (price × (1-app_fee) ÷ Y2 avg churn) | B51: =Assumptions!C4*(1-Assumptions!C41)/AVERAGE(N9:Y9) -> 56.971122 | AO51: ONE consistent formula. Original mixed €42.42 / €40.92 / €34.93 across three lines.
A52: LTV — B2C premium (price × (1-app_fee) ÷ prem churn) | B52: =Assumptions!C5*(1-Assumptions!C41)/Assumptions!C27 -> 276.0375
A53: CAC — paid social Y1 (€) | B53: =Assumptions!C15 -> 20
A54: LTV:CAC — B2C basic paid channel (VC floor: 3×) | B54: =IF(B53=0,0,B51/B53) -> 2.8485561 | AO54: VC floor 3×. Corrected LTV and CAC feed this — one consistent calculation.
A55: Payback period — paid social (months) | B55: =IF(B53=0,0,B53/(Assumptions!C4*(1-Assumptions!C41))) -> 4.715313
A56: CAC — organic Y1 (€4.20 — events €500 + tools €200 ÷ ~167 users) | B56: 4.2
A57: LTV:CAC — organic | B57: =IF(B56=0,0,B51/B56) -> 13.564553

Sheet Realistic
A1: NutriSync — Realistic Scenario | All inputs from Assumptions sheet | Blue = inputs, Black = formulas
A2: METRIC | B2: M1 | C2: M2 | D2: M3 | E2: M4 | F2: M5 | G2: M6 | H2: M7 | I2: M8 | J2: M9 | K2: M10 | L2: M11 | M2: M12 | N2: M13 | O2: M14 | P2: M15 | Q2: M16 | R2: M17 | S2: M18 | T2: M19 | U2: M20 | V2: M21 | W2: M22 | X2: M23 | Y2: M24 | Z2: M25 | AA2: M26 | AB2: M27 | AC2: M28 | AD2: M29 | AE2: M30 | AF2: M31 | AG2: M32 | AH2: M33 | AI2: M34 | AJ2: M35 | AK2: M36 | AL2: Y1 Total | AM2: Y2 Total | AN2: Y3 Total | AO2: Notes / Formula
A3: Year | B3: 1 | C3: 1 | D3: 1 | E3: 1 | F3: 1 | G3: 1 | H3: 1 | I3: 1 | J3: 1 | K3: 1 | L3: 1 | M3: 1 | N3: 2 | O3: 2 | P3: 2 | Q3: 2 | R3: 2 | S3: 2 | T3: 2 | U3: 2 | V3: 2 | W3: 2 | X3: 2 | Y3: 2 | Z3: 3 | AA3: 3 | AB3: 3 | AC3: 3 | AD3: 3 | AE3: 3 | AF3: 3 | AG3: 3 | AH3: 3 | AI3: 3 | AJ3: 3 | AK3: 3
A4: SECTION 1 — USER PROJECTIONS
A5: New organic free users/mo | B5: =Assumptions!D9 -> 350 | C5: =B5*(1+Assumptions!D10) -> 416.5 | D5: =C5*(1+Assumptions!D10) -> 495.635 | E5: =D5*(1+Assumptions!D10) -> 589.80565 | F5: =E5*(1+Assumptions!D10) -> 701.86872 | G5: =F5*(1+Assumptions!D10) -> 835.22378 | H5: =G5*(1+Assumptions!D10) -> 993.9163 | I5: =H5*(1+Assumptions!D10) -> 1182.7604 | J5: =I5*(1+Assumptions!D10) -> 1407.4849 | K5: =J5*(1+Assumptions!D10) -> 1674.907 | L5: =K5*(1+Assumptions!D10) -> 1993.1393 | M5: =L5*(1+Assumptions!D10) -> 2371.8358 | N5: =M5*(1+Assumptions!D10) -> 2822.4846 | O5: =N5*(1+Assumptions!D10) -> 3358.7567 | P5: =O5*(1+Assumptions!D10) -> 3996.9204 | Q5: =P5*(1+Assumptions!D10) -> 4756.3353 | R5: =Q5*(1+Assumptions!D10) -> 5660.039 | S5: =R5*(1+Assumptions!D10) -> 6735.4465 | T5: =S5*(1+Assumptions!D10) -> 8015.1813 | U5: =T5*(1+Assumptions!D10) -> 9538.0657 | V5: =U5*(1+Assumptions!D10) -> 11350.298 | W5: =V5*(1+Assumptions!D10) -> 13506.855 | X5: =W5*(1+Assumptions!D10) -> 16073.157 | Y5: =X5*(1+Assumptions!D10) -> 19127.057 | Z5: =Y5*(1+Assumptions!D10) -> 22761.198 | AA5: =Z5*(1+Assumptions!D10) -> 27085.826 | AB5: =AA5*(1+Assumptions!D10) -> 32232.133 | AC5: =AB5*(1+Assumptions!D10) -> 38356.238 | AD5: =AC5*(1+Assumptions!D10) -> 45643.923 | AE5: =AD5*(1+Assumptions!D10) -> 54316.268 | AF5: =AE5*(1+Assumptions!D10) -> 64636.359 | AG5: =AF5*(1+Assumptions!D10) -> 76917.268 | AH5: =AG5*(1+Assumptions!D10) -> 91531.548 | AI5: =AH5*(1+Assumptions!D10) -> 108922.54 | AJ5: =AI5*(1+Assumptions!D10) -> 129617.83 | AK5: =AJ5*(1+Assumptions!D10) -> 154245.21 | AL5: =SUM(B5:M5) -> 13013.077 | AM5: =SUM(N5:Y5) -> 104940.6 | AN5: =SUM(Z5:AK5) -> 846266.34 | AO5: Compounds from M1 at organic growth rate.
A6: → New paid: organic conversion (one-off per month's new free users) | B6: =B5*Assumptions!D11 -> 49 | C6: =C5*Assumptions!D11 -> 58.31 | D6: =D5*Assumptions!D11 -> 69.3889 | E6: =E5*Assumptions!D11 -> 82.572791 | F6: =F5*Assumptions!D11 -> 98.261621 | G6: =G5*Assumptions!D11 -> 116.93133 | H6: =H5*Assumptions!D11 -> 139.14828 | I6: =I5*Assumptions!D11 -> 165.58646 | J6: =J5*Assumptions!D11 -> 197.04788 | K6: =K5*Assumptions!D11 -> 234.48698 | L6: =L5*Assumptions!D11 -> 279.03951 | M6: =M5*Assumptions!D11 -> 332.05701 | N6: =N5*Assumptions!D11 -> 395.14784 | O6: =O5*Assumptions!D11 -> 470.22593 | P6: =P5*Assumptions!D11 -> 559.56886 | Q6: =Q5*Assumptions!D11 -> 665.88695 | R6: =R5*Assumptions!D11 -> 792.40547 | S6: =S5*Assumptions!D11 -> 942.9625 | T6: =T5*Assumptions!D11 -> 1122.1254 | U6: =U5*Assumptions!D11 -> 1335.3292 | V6: =V5*Assumptions!D11 -> 1589.0418 | W6: =W5*Assumptions!D11 -> 1890.9597 | X6: =X5*Assumptions!D11 -> 2250.242 | Y6: =Y5*Assumptions!D11 -> 2677.788 | Z6: =Z5*Assumptions!D11 -> 3186.5677 | AA6: =AA5*Assumptions!D11 -> 3792.0156 | AB6: =AB5*Assumptions!D11 -> 4512.4986 | AC6: =AC5*Assumptions!D11 -> 5369.8733 | AD6: =AD5*Assumptions!D11 -> 6390.1492 | AE6: =AE5*Assumptions!D11 -> 7604.2776 | AF6: =AF5*Assumptions!D11 -> 9049.0903 | AG6: =AG5*Assumptions!D11 -> 10768.417 | AH6: =AH5*Assumptions!D11 -> 12814.417 | AI6: =AI5*Assumptions!D11 -> 15249.156 | AJ6: =AJ5*Assumptions!D11 -> 18146.496 | AK6: =AK5*Assumptions!D11 -> 21594.33 | AL6: =SUM(B6:M6) -> 1821.8308 | AM6: =SUM(N6:Y6) -> 14691.684 | AN6: =SUM(Z6:AK6) -> 118477.29 | AO6: 5–8% one-off per month (NOT monthly to pool). Benchmark: RevenueCat H&F median 6.9%.
A7: → New paid: paid social (budget ÷ CAC) | B7: =0 -> 0 | C7: =0 -> 0 | D7: =0 -> 0 | E7: =Assumptions!D12/Assumptions!D15 -> 733.33333 | F7: =Assumptions!D12/Assumptions!D15 -> 733.33333 | G7: =Assumptions!D12/Assumptions!D15 -> 733.33333 | H7: =Assumptions!D12/Assumptions!D15 -> 733.33333 | I7: =Assumptions!D12/Assumptions!D15 -> 733.33333 | J7: =Assumptions!D12/Assumptions!D15 -> 733.33333 | K7: =Assumptions!D12/Assumptions!D15 -> 733.33333 | L7: =Assumptions!D12/Assumptions!D15 -> 733.33333 | M7: =Assumptions!D12/Assumptions!D15 -> 733.33333 | N7: =Assumptions!D13/Assumptions!D16 -> 1555.5556 | O7: =Assumptions!D13/Assumptions!D16 -> 1555.5556 | P7: =Assumptions!D13/Assumptions!D16 -> 1555.5556 | Q7: =Assumptions!D13/Assumptions!D16 -> 1555.5556 | R7: =Assumptions!D13/Assumptions!D16 -> 1555.5556 | S7: =Assumptions!D13/Assumptions!D16 -> 1555.5556 | T7: =Assumptions!D13/Assumptions!D16 -> 1555.5556 | U7: =Assumptions!D13/Assumptions!D16 -> 1555.5556 | V7: =Assumptions!D13/Assumptions!D16 -> 1555.5556 | W7: =Assumptions!D13/Assumptions!D16 -> 1555.5556 | X7: =Assumptions!D13/Assumptions!D16 -> 1555.5556 | Y7: =Assumptions!D13/Assumptions!D16 -> 1555.5556 | Z7: =Assumptions!D14/Assumptions!D16 -> 1166.6667 | AA7: =Assumptions!D14/Assumptions!D16 -> 1166.6667 | AB7: =Assumptions!D14/Assumptions!D16 -> 1166.6667 | AC7: =Assumptions!D14/Assumptions!D16 -> 1166.6667 | AD7: =Assumptions!D14/Assumptions!D16 -> 1166.6667 | AE7: =Assumptions!D14/Assumptions!D16 -> 1166.6667 | AF7: =Assumptions!D14/Assumptions!D16 -> 1166.6667 | AG7: =Assumptions!D14/Assumptions!D16 -> 1166.6667 | AH7: =Assumptions!D14/Assumptions!D16 -> 1166.6667 | AI7: =Assumptions!D14/Assumptions!D16 -> 1166.6667 | AJ7: =Assumptions!D14/Assumptions!D16 -> 1166.6667 | AK7: =Assumptions!D14/Assumptions!D16 -> 1166.6667 | AL7: =SUM(B7:M7) -> 6600 | AM7: =SUM(N7:Y7) -> 18666.667 | AN7: =SUM(Z7:AK7) -> 14000 | AO7: Budget / CAC. CAC corrected: €20 Y1 conservative (not €6–8; install alone $3.70–4.70).
A8: % of paid users with wearable connected | B8: =0 -> 0 | C8: =0 -> 0 | D8: =0 -> 0 | E8: =MIN(Assumptions!D22,1*Assumptions!D21) -> 0.02 | F8: =MIN(Assumptions!D22,2*Assumptions!D21) -> 0.04 | G8: =MIN(Assumptions!D22,3*Assumptions!D21) -> 0.06 | H8: =MIN(Assumptions!D22,4*Assumptions!D21) -> 0.08 | I8: =MIN(Assumptions!D22,5*Assumptions!D21) -> 0.1 | J8: =MIN(Assumptions!D22,6*Assumptions!D21) -> 0.12 | K8: =MIN(Assumptions!D22,7*Assumptions!D21) -> 0.14 | L8: =MIN(Assumptions!D22,8*Assumptions!D21) -> 0.16 | M8: =MIN(Assumptions!D22,9*Assumptions!D21) -> 0.18 | N8: =MIN(Assumptions!D22,10*Assumptions!D21) -> 0.2 | O8: =MIN(Assumptions!D22,11*Assumptions!D21) -> 0.22 | P8: =MIN(Assumptions!D22,12*Assumptions!D21) -> 0.24 | Q8: =MIN(Assumptions!D22,13*Assumptions!D21) -> 0.26 | R8: =MIN(Assumptions!D22,14*Assumptions!D21) -> 0.28 | S8: =MIN(Assumptions!D22,15*Assumptions!D21) -> 0.3 | T8: =MIN(Assumptions!D22,16*Assumptions!D21) -> 0.32 | U8: =MIN(Assumptions!D22,17*Assumptions!D21) -> 0.34 | V8: =MIN(Assumptions!D22,18*Assumptions!D21) -> 0.36 | W8: =MIN(Assumptions!D22,19*Assumptions!D21) -> 0.38 | X8: =MIN(Assumptions!D22,20*Assumptions!D21) -> 0.4 | Y8: =MIN(Assumptions!D22,21*Assumptions!D21) -> 0.4 | Z8: =MIN(Assumptions!D22,22*Assumptions!D21) -> 0.4 | AA8: =MIN(Assumptions!D22,23*Assumptions!D21) -> 0.4 | AB8: =MIN(Assumptions!D22,24*Assumptions!D21) -> 0.4 | AC8: =MIN(Assumptions!D22,25*Assumptions!D21) -> 0.4 | AD8: =MIN(Assumptions!D22,26*Assumptions!D21) -> 0.4 | AE8: =MIN(Assumptions!D22,27*Assumptions!D21) -> 0.4 | AF8: =MIN(Assumptions!D22,28*Assumptions!D21) -> 0.4 | AG8: =MIN(Assumptions!D22,29*Assumptions!D21) -> 0.4 | AH8: =MIN(Assumptions!D22,30*Assumptions!D21) -> 0.4 | AI8: =MIN(Assumptions!D22,31*Assumptions!D21) -> 0.4 | AJ8: =MIN(Assumptions!D22,32*Assumptions!D21) -> 0.4 | AK8: =MIN(Assumptions!D22,33*Assumptions!D21) -> 0.4 | AL8: =M8 -> 0.18 | AM8: =Y8 -> 0.4 | AN8: =AK8 -> 0.4 | AO8: Ramps +1.5–2.5%pts/mo from M4; capped at adoption ceiling.
A9: Blended monthly churn (wearable-adjusted) | B9: =Assumptions!D18*(1-B8*Assumptions!D23) -> 0.08 | C9: =Assumptions!D18*(1-C8*Assumptions!D23) -> 0.08 | D9: =Assumptions!D18*(1-D8*Assumptions!D23) -> 0.08 | E9: =Assumptions!D18*(1-E8*Assumptions!D23) -> 0.07944 | F9: =Assumptions!D18*(1-F8*Assumptions!D23) -> 0.07888 | G9: =Assumptions!D18*(1-G8*Assumptions!D23) -> 0.07832 | H9: =Assumptions!D18*(1-H8*Assumptions!D23) -> 0.07776 | I9: =Assumptions!D18*(1-I8*Assumptions!D23) -> 0.0772 | J9: =Assumptions!D18*(1-J8*Assumptions!D23) -> 0.07664 | K9: =Assumptions!D18*(1-K8*Assumptions!D23) -> 0.07608 | L9: =Assumptions!D18*(1-L8*Assumptions!D23) -> 0.07552 | M9: =Assumptions!D18*(1-M8*Assumptions!D23) -> 0.07496 | N9: =Assumptions!D19*(1-N8*Assumptions!D23) -> 0.0651 | O9: =Assumptions!D19*(1-O8*Assumptions!D23) -> 0.06461 | P9: =Assumptions!D19*(1-P8*Assumptions!D23) -> 0.06412 | Q9: =Assumptions!D19*(1-Q8*Assumptions!D23) -> 0.06363 | R9: =Assumptions!D19*(1-R8*Assumptions!D23) -> 0.06314 | S9: =Assumptions!D19*(1-S8*Assumptions!D23) -> 0.06265 | T9: =Assumptions!D19*(1-T8*Assumptions!D23) -> 0.06216 | U9: =Assumptions!D19*(1-U8*Assumptions!D23) -> 0.06167 | V9: =Assumptions!D19*(1-V8*Assumptions!D23) -> 0.06118 | W9: =Assumptions!D19*(1-W8*Assumptions!D23) -> 0.06069 | X9: =Assumptions!D19*(1-X8*Assumptions!D23) -> 0.0602 | Y9: =Assumptions!D19*(1-Y8*Assumptions!D23) -> 0.0602 | Z9: =Assumptions!D20*(1-Z8*Assumptions!D23) -> 0.0473 | AA9: =Assumptions!D20*(1-AA8*Assumptions!D23) -> 0.0473 | AB9: =Assumptions!D20*(1-AB8*Assumptions!D23) -> 0.0473 | AC9: =Assumptions!D20*(1-AC8*Assumptions!D23) -> 0.0473 | AD9: =Assumptions!D20*(1-AD8*Assumptions!D23) -> 0.0473 | AE9: =Assumptions!D20*(1-AE8*Assumptions!D23) -> 0.0473 | AF9: =Assumptions!D20*(1-AF8*Assumptions!D23) -> 0.0473 | AG9: =Assumptions!D20*(1-AG8*Assumptions!D23) -> 0.0473 | AH9: =Assumptions!D20*(1-AH8*Assumptions!D23) -> 0.0473 | AI9: =Assumptions!D20*(1-AI8*Assumptions!D23) -> 0.0473 | AJ9: =Assumptions!D20*(1-AJ8*Assumptions!D23) -> 0.0473 | AK9: =Assumptions!D20*(1-AK8*Assumptions!D23) -> 0.0473 | AL9: =AVERAGE(B9:M9) -> 0.0779 | AM9: =AVERAGE(N9:Y9) -> 0.062445833 | AN9: =AVERAGE(Z9:AK9) -> 0.0473 | AO9: base × (1 − wearable% × reduction_factor).
A10: Premium upgrades from basic (M13+) | B10: =0 -> 0 | C10: =0 -> 0 | D10: =0 -> 0 | E10: =0 -> 0 | F10: =0 -> 0 | G10: =0 -> 0 | H10: =0 -> 0 | I10: =0 -> 0 | ... M10: =0 -> 0 | N10: =M11*Assumptions!D26 -> 63.215806 | O10: =N11*Assumptions!D26 -> 77.975333 | P10: =O11*Assumptions!D26 -> 92.415408 | Q10: =P11*Assumptions!D26 -> 106.71682 | R10: =Q11*Assumptions!D26 -> 121.07369 | S10: =R11*Assumptions!D26 -> 135.69797 | T10: =S11*Assumptions!D26 -> 150.82469 | U10: =T11*Assumptions!D26 -> 166.71799 | V10: =U11*Assumptions!D26 -> 183.67816 | W10: =V11*Assumptions!D26 -> 202.04992 | X10: =W11*Assumptions!D26 -> 222.23217 | Y10: =X11*Assumptions!D26 -> 244.68944 | Z10: =Y11*Assumptions!D26 -> 269.84568 | AA10: =Z11*Assumptions!D26 -> 297.91587 | AB10: =AA11*Assumptions!D26 -> 330.43211 | AC10: =AB11*Assumptions!D26 -> 368.29 | AD10: =AC11*Assumptions!D26 -> 412.55238 | AE10: =AD11*Assumptions!D26 -> 464.48129 | AF10: =AE11*Assumptions!D26 -> 525.57596 | AG10: =AF11*Assumptions!D26 -> 597.61802 | AH10: =AG11*Assumptions!D26 -> 682.72535 | AI10: =AH11*Assumptions!D26 -> 783.41602 | AJ10: =AI11*Assumptions!D26 -> 902.68451 | AK10: =AJ11*Assumptions!D26 -> 1044.0923 | AL10: =SUM(B10:M10) -> 0 | AM10: =SUM(N10:Y10) -> 1767.2874 | AN10: =SUM(Z10:AK10) -> 6679.6295 | AO10: 0.75–1.5%/mo of basic base (corrected from 4–8%/mo compounding).
A11: B2C basic subscribers (EoM) | B11: =B6+B7 -> 49 | C11: =B11*(1-C9)-C10+C6+C7 -> 103.39 | D11: =C11*(1-D9)-D10+D6+D7 -> 164.5077 | E11: =D11*(1-E9)-E10+E6+E7 -> 967.34533 | F11: =E11*(1-F9)-F10+F6+F7 -> 1722.6361 | G11: =F11*(1-G9)-G10+G6+G7 -> 2437.9839 | H11: =G11*(1-H9)-H10+H6+H7 -> 3120.8879 | I11: =H11*(1-I9)-I10+I6+I7 -> 3778.8751 | J11: =I11*(1-J9)-J10+J6+J7 -> 4419.6433 | ... AK11: =AJ11*(1-AK9)-AK10+AK6+AK7 -> 121187.58 | AL11: =M11 -> 6321.5806 | AM11: =Y11 -> 26984.568 | AN11: =AK11 -> 121187.58 | AO11: Prior × (1-churn) - upgrades + new converts.
A12: B2C premium subscribers (EoM — upgrade from basic, not added on top) | B12: =0 -> 0 | C12: =0 -> 0 | D12: =0 -> 0 | E12: =0 -> 0 | F12: =0 -> 0 | G12: =0 -> 0 | H12: =0 -> 0 | I12: =0 -> 0 | ... M12: =0 -> 0 | N12: =N10 -> 63.215806 | O12: =N12*(1-Assumptions!D27)+O10 -> 138.97859 | P12: =O12*(1-Assumptions!D27)+P10 -> 226.52974 | Q12: =P12*(1-Assumptions!D27)+Q10 -> 325.31802 | R12: =Q12*(1-Assumptions!D27)+R10 -> 435.00558 | S12: =R12*(1-Assumptions!D27)+S10 -> 555.47835 | T12: =S12*(1-Assumptions!D27)+T10 -> 686.8613 | U12: =T12*(1-Assumptions!D27)+U10 -> 829.53915 | V12: =U12*(1-Assumptions!D27)+V10 -> 984.18344 | W12: =V12*(1-Assumptions!D27)+W10 -> 1151.7869 | X12: =W12*(1-Assumptions!D27)+X10 -> 1333.7066 | Y12: =X12*(1-Assumptions!D27)+Y10 -> 1531.7163 | Z12: =Y12*(1-Assumptions!D27)+Z10 -> 1747.9519 | AA12: =Z12*(1-Assumptions!D27)+AA10 -> 1984.6894 | AB12: =AA12*(1-Assumptions!D27)+AB10 -> 2245.6574 | AC12: =AB12*(1-Assumptions!D27)+AC10 -> 2535.3494 | AD12: =AC12*(1-Assumptions!D27)+AD10 -> 2859.1646 | AE12: =AD12*(1-Assumptions!D27)+AE10 -> 3223.5751 | AF12: =AE12*(1-Assumptions!D27)+AF10 -> 3636.3259 | AG12: =AF12*(1-Assumptions!D27)+AG10 -> 4106.6725 | AH12: =AG12*(1-Assumptions!D27)+AH10 -> 4645.6644 | AI12: =AH12*(1-Assumptions!D27)+AI10 -> 5266.4821 | AJ12: =AI12*(1-Assumptions!D27)+AJ10 -> 5984.8398 | AK12: =AJ12*(1-Assumptions!D27)+AK10 -> 6819.4627 | AL12: =M12 -> 0 | AM12: =Y12 -> 1531.7163 | AN12: =AK12 -> 6819.4627 | AO12: Premium users MOVE from basic — no double-counting.
A13: B2B contracts signed (cumulative) | B13: =0 -> 0 | C13: =0 -> 0 | D13: =0 -> 0 | E13: =0 -> 0 | F13: =0 -> 0 | G13: =Assumptions!D29 -> 1.7 | H13: =G13+Assumptions!D29 -> 3.4 | I13: =H13+Assumptions!D29 -> 5.1 | J13: =I13+Assumptions!D29 -> 6.8 | K13: =J13+Assumptions!D29 -> 8.5 | L13: =K13+Assumptions!D29 -> 10.2 | M13: =L13+Assumptions!D29 -> 11.9 | N13: =M13+Assumptions!D30 -> 13.6 | O13: =N13+Assumptions!D30 -> 15.3 | P13: =O13+Assumptions!D30 -> 17 | Q13: =P13+Assumptions!D30 -> 18.7 | R13: =Q13+Assumptions!D30 -> 20.4 | S13: =R13+Assumptions!D30 -> 22.1 | T13: =S13+Assumptions!D30 -> 23.8 | U13: =T13+Assumptions!D30 -> 25.5 | V13: =U13+Assumptions!D30 -> 27.2 | W13: =V13+Assumptions!D30 -> 28.9 | X13: =W13+Assumptions!D30 -> 30.6 | Y13: =X13+Assumptions!D30 -> 32.3 | Z13: =Y13+Assumptions!D31 -> 35.9 | AA13: =Z13+Assumptions!D31 -> 39.5 | AB13: =AA13+Assumptions!D31 -> 43.1 | AC13: =AB13+Assumptions!D31 -> 46.7 | AD13: =AC13+Assumptions!D31 -> 50.3 | AE13: =AD13+Assumptions!D31 -> 53.9 | AF13: =AE13+Assumptions!D31 -> 57.5 | AG13: =AF13+Assumptions!D31 -> 61.1 | AH13: =AG13+Assumptions!D31 -> 64.7 | AI13: =AH13+Assumptions!D31 -> 68.3 | AJ13: =AI13+Assumptions!D31 -> 71.9 | AK13: =AJ13+Assumptions!D31 -> 75.5 | AL13: =M13 -> 11.9 | AM13: =Y13 -> 32.3 | AN13: =AK13 -> 75.5
A14: B2B employees active (EoM) | B14: =0 -> 0 | C14: =0 -> 0 | D14: =0 -> 0 | E14: =0 -> 0 | F14: =0 -> 0 | G14: =Assumptions!D29*Assumptions!D32 -> 255 | H14: =G14*(1-(1-(1-Assumptions!D33)^(1/12)))+Assumptions!D29*Assumptions!D32 -> 505.8176 | I14: =H14*(1-(1-(1-Assumptions!D33)^(1/12)))+Assumptions!D29*Assumptions!D32 -> 752.52139 | J14: =I14*(1-(1-(1-Assumptions!D33)^(1/12)))+Assumptions!D29*Assumptions!D32 -> 995.17884 | K14: =J14*(1-(1-(1-Assumptions!D33)^(1/12)))+Assumptions!D29*Assumptions!D32 -> 1233.8563 | L14: =K14*(1-(1-(1-Assumptions!D33)^(1/12)))+Assumptions!D29*Assumptions!D32 -> 1468.6191 | M14: =L14*(1-(1-(1-Assumptions!D33)^(1/12)))+Assumptions!D29*Assumptions!D32 -> 1699.5315 | N14: =M14*(1-(1-(1-Assumptions!D33)^(1/12)))+Assumptions!D30*Assumptions!D32 -> 1926.6565 | O14: =N14*(1-(1-(1-Assumptions!D33)^(1/12)))+Assumptions!D30*Assumptions!D32 -> 2150.0562 | P14: =O14*(1-(1-(1-Assumptions!D33)^(1/12)))+Assumptions!D30*Assumptions!D32 -> 2369.7919 | Q14: =P14*(1-(1-(1-Assumptions!D33)^(1/12)))+Assumptions!D30*Assumptions!D32 -> 2585.9236 | R14: =Q14*(1-(1-(1-Assumptions!D33)^(1/12)))+Assumptions!D30*Assumptions!D32 -> 2798.5103 | S14: =R14*(1-(1-(1-Assumptions!D33)^(1/12)))+Assumptions!D30*Assumptions!D32 -> 3007.6103 | T14: =S14*(1-(1-(1-Assumptions!D33)^(1/12)))+Assumptions!D30*Assumptions!D32 -> 3213.2808 | U14: =T14*(1-(1-(1-Assumptions!D33)^(1/12)))+Assumptions!D30*Assumptions!D32 -> 3415.5779 | V14: =U14*(1-(1-(1-Assumptions!D33)^(1/12)))+Assumptions!D30*Assumptions!D32 -> 3614.557 | W14: =V14*(1-(1-(1-Assumptions!D33)^(1/12)))+Assumptions!D30*Assumptions!D32 -> 3810.2725 | X14: =W14*(1-(1-(1-Assumptions!D33)^(1/12)))+Assumptions!D30*Assumptions!D32 -> 4002.778 | Y14: =X14*(1-(1-(1-Assumptions!D33)^(1/12)))+Assumptions!D30*Assumptions!D32 -> 4192.1261 | Z14: =Y14*(1-(1-(1-Assumptions!D33)^(1/12)))+Assumptions!D31*Assumptions!D32 -> 4663.3686 | AA14: =Z14*(1-(1-(1-Assumptions!D33)^(1/12)))+Assumptions!D31*Assumptions!D32 -> 5126.882 | AB14: =AA14*(1-(1-(1-Assumptions!D33)^(1/12)))+Assumptions!D31*Assumptions!D32 -> 5582.793 | AC14: =AB14*(1-(1-(1-Assumptions!D33)^(1/12)))+Assumptions!D31*Assumptions!D32 -> 6031.2264 | AD14: =AC14*(1-(1-(1-Assumptions!D33)^(1/12)))+Assumptions!D31*Assumptions!D32 -> 6472.3047 | AE14: =AD14*(1-(1-(1-Assumptions!D33)^(1/12)))+Assumptions!D31*Assumptions!D32 -> 6906.1487 | AF14: =AE14*(1-(1-(1-Assumptions!D33)^(1/12)))+Assumptions!D31*Assumptions!D32 -> 7332.8769 | AG14: =AF14*(1-(1-(1-Assumptions!D33)^(1/12)))+Assumptions!D31*Assumptions!D32 -> 7752.6061 | AH14: =AG14*(1-(1-(1-Assumptions!D33)^(1/12)))+Assumptions!D31*Assumptions!D32 -> 8165.4511 | AI14: =AH14*(1-(1-(1-Assumptions!D33)^(1/12)))+Assumptions!D31*Assumptions!D32 -> 8571.5248 | AJ14: =AI14*(1-(1-(1-Assumptions!D33)^(1/12)))+Assumptions!D31*Assumptions!D32 -> 8970.9382 | AK14: =AJ14*(1-(1-(1-Assumptions!D33)^(1/12)))+Assumptions!D31*Assumptions!D32 -> 9363.8006 | AL14: =M14 -> 1699.5315 | AM14: =Y14 -> 4192.1261 | AN14: =AK14 -> 9363.8006 | AO14: Prior × (1-monthly logo churn) + new seats.
A15: TOTAL PAYING USERS (EoM) | B15: =B11+B12+B14 -> 49 | C15: =C11+C12+C14 -> 103.39 | D15: =D11+D12+D14 -> 164.5077 | E15: =E11+E12+E14 -> 967.34533 | F15: =F11+F12+F14 -> 1722.6361 | G15: =G11+G12+G14 -> 2692.9839 | H15: =H11+H12+H14 -> 3626.7055 | I15: =I11+I12+I14 -> 4531.3965 | ... AK15: =AK11+AK12+AK14 -> 137370.84 | AL15: =M15 -> 8021.112 | AM15: =Y15 -> 32708.41 | AN15: =AK15 -> 137370.84 | AO15: Basic + premium + B2B. Premium NOT double-counted.
A17: SECTION 2 — REVENUE
A18: B2C basic subscriptions | B18: =B11*Assumptions!D4 -> 244.51 | C18: =(B11+C11)/2*Assumptions!D4 -> 380.21305 | D18: =(C11+D11)/2*Assumptions!D4 -> 668.40476 | E18: =(D11+E11)/2*Assumptions!D4 -> 2823.9733 | F18: =(E11+F11)/2*Assumptions!D4 -> 6711.5036 | G18: =(F11+G11)/2*Assumptions!D4 -> 10380.747 | H18: =(G11+H11)/2*Assumptions!D4 -> 13869.385 | I18: =(H11+I11)/2*Assumptions!D4 -> 17214.909 | J18: =(I11+J11)/2*Assumptions!D4 -> 20455.304 | K18: =(J11+K11)/2*Assumptions!D4 -> 23629.797 | L18: =(K11+L11)/2*Assumptions!D4 -> 26779.682 | M18: =(L11+M11)/2*Assumptions!D4 -> 29949.238 | N18: =(M11+N11)/2*Assumptions!D4 -> 35227.189 | O18: =(N11+O11)/2*Assumptions!D4 -> 42512.49 | P18: =(O11+P11)/2*Assumptions!D4 -> 49683.491 | Q18: =(P11+Q11)/2*Assumptions!D4 -> 56833.732 | R18: =(Q11+R11)/2*Assumptions!D4 -> 64064.528 | S18: =(R11+S11)/2*Assumptions!D4 -> 71487.404 | T18: =(S11+T11)/2*Assumptions!D4 -> 79226.899 | U18: =(T11+U11)/2*Assumptions!D4 -> 87423.84 | V18: =(U11+V11)/2*Assumptions!D4 -> 96239.157 | W18: =(V11+W11)/2*Assumptions!D4 -> 105858.38 | X18: =(W11+X11)/2*Assumptions!D4 -> 116496.94 | Y18: =(X11+Y11)/2*Assumptions!D4 -> 128376.51 | Z18: =(Y11+Z11)/2*Assumptions!D4 -> 141656.51 | AA18: =(Z11+AA11)/2*Assumptions!D4 -> 156772.82 | AB18: =(AA11+AB11)/2*Assumptions!D4 -> 174331.17 | AC18: =(AB11+AC11)/2*Assumptions!D4 -> 194820.18 | AD18: =(AC11+AD11)/2*Assumptions!D4 -> 218819.9 | AE18: =(AD11+AE11)/2*Assumptions!D4 -> 247019.28 | AF18: =(AE11+AF11)/2*Assumptions!D4 -> 280236.9 | AG18: =(AF11+AG11)/2*Assumptions!D4 -> 319445.67 | AH18: =(AG11+AH11)/2*Assumptions!D4 -> 365802.27 | AI18: =(AH11+AI11)/2*Assumptions!D4 -> 420682.08 | AJ18: =(AI11+AJ11)/2*Assumptions!D4 -> 485720.82 | AK18: =(AJ11+AK11)/2*Assumptions!D4 -> 562864.04 | AL18: =SUM(B18:M18) -> 153107.67 | AM18: =SUM(N18:Y18) -> 933430.57 | AN18: =SUM(Z18:AK18) -> 3568171.6
A19: B2C premium subscriptions (from M13) | B19: =0 -> 0 | C19: =0 -> 0 | D19: =0 -> 0 | E19: =0 -> 0 | F19: =0 -> 0 | G19: =0 -> 0 | H19: =0 -> 0 | I19: =0 -> 0 | ... M19: =0 -> 0 | N19: =N12*Assumptions!D5 -> 821.17332 | O19: =(N12+O12)/2*Assumptions!D5 -> 1313.2526 | P19: =(O12+P12)/2*Assumptions!D5 -> 2373.9766 | Q19: =(P12+Q12)/2*Assumptions!D5 -> 3584.2512 | R19: =(Q12+R12)/2*Assumptions!D5 -> 4938.3018 | S19: =(R12+S12)/2*Assumptions!D5 -> 6433.1932 | T19: =(S12+T12)/2*Assumptions!D5 -> 8068.9961 | U19: =(T12+U12)/2*Assumptions!D5 -> 9849.0209 | V19: =(U12+V12)/2*Assumptions!D5 -> 11780.128 | W19: =(V12+W12)/2*Assumptions!D5 -> 13873.128 | X19: =(W12+X12)/2*Assumptions!D5 -> 16143.28 | Y19: =(X12+Y12)/2*Assumptions!D5 -> 18610.921 | Z19: =(Y12+Z12)/2*Assumptions!D5 -> 21301.445 | AA19: =(Z12+AA12)/2*Assumptions!D5 -> 24243.505 | AB19: =(AA12+AB12)/2*Assumptions!D5 -> 27476.103 | AC19: =(AB12+AC12)/2*Assumptions!D5 -> 31052.639 | AD19: =(AC12+AD12)/2*Assumptions!D5 -> 35037.368 | AE19: =(AD12+AE12)/2*Assumptions!D5 -> 39507.394 | AF19: =(AE12+AF12)/2*Assumptions!D5 -> 44555.057 | AG19: =(AF12+AG12)/2*Assumptions!D5 -> 50290.775 | AH19: =(AG12+AH12)/2*Assumptions!D5 -> 56846.428 | AI19: =(AH12+AI12)/2*Assumptions!D5 -> 64379.391 | AJ19: =(AI12+AJ12)/2*Assumptions!D5 -> 73077.336 | AK19: =(AJ12+AK12)/2*Assumptions!D5 -> 83163.944 | AL19: =SUM(B19:M19) -> 0 | AM19: =SUM(N19:Y19) -> 97789.623 | AN19: =SUM(Z19:AK19) -> 550931.39
A20: B2B corporate wellbeing | B20: =0 -> 0 | C20: =0 -> 0 | D20: =0 -> 0 | E20: =0 -> 0 | F20: =0 -> 0 | G20: =G14*Assumptions!D6 -> 1017.45 | H20: =H14*Assumptions!D6 -> 2018.2122 | I20: =I14*Assumptions!D6 -> 3002.5603 | J20: =J14*Assumptions!D6 -> 3970.7636 | K20: =K14*Assumptions!D6 -> 4923.0868 | L20: =L14*Assumptions!D6 -> 5859.7904 | M20: =M14*Assumptions!D6 -> 6781.1305 | N20: =N14*Assumptions!D7 -> 11540.672 | O20: =O14*Assumptions!D7 -> 12878.837 | P20: =P14*Assumptions!D7 -> 14195.054 | Q20: =Q14*Assumptions!D7 -> 15489.682 | R20: =R14*Assumptions!D7 -> 16763.077 | S20: =S14*Assumptions!D7 -> 18015.586 | T20: =T14*Assumptions!D7 -> 19247.552 | U20: =U14*Assumptions!D7 -> 20459.311 | V20: =V14*Assumptions!D7 -> 21651.196 | W20: =W14*Assumptions!D7 -> 22823.532 | X20: =X14*Assumptions!D7 -> 23976.64 | Y20: =Y14*Assumptions!D7 -> 25110.836 | Z20: =Z14*Assumptions!D7 -> 27933.578 | AA20: =AA14*Assumptions!D7 -> 30710.023 | AB20: =AB14*Assumptions!D7 -> 33440.93 | AC20: =AC14*Assumptions!D7 -> 36127.046 | AD20: =AD14*Assumptions!D7 -> 38769.105 | AE20: =AE14*Assumptions!D7 -> 41367.83 | AF20: =AF14*Assumptions!D7 -> 43923.933 | AG20: =AG14*Assumptions!D7 -> 46438.111 | AH20: =AH14*Assumptions!D7 -> 48911.052 | AI20: =AI14*Assumptions!D7 -> 51343.433 | AJ20: =AJ14*Assumptions!D7 -> 53735.92 | AK20: =AK14*Assumptions!D7 -> 56089.166 | AL20: =SUM(B20:M20) -> 27572.994 | AM20: =SUM(N20:Y20) -> 222151.98 | AN20: =SUM(Z20:AK20) -> 508790.13
A21: Events & workshops (net) | B21: =0 -> 0 | C21: =0 -> 0 | D21: =Assumptions!D35 -> 750 | E21: =Assumptions!D35 -> 750 | F21: =Assumptions!D35 -> 750 | G21: =Assumptions!D35 -> 750 | H21: =Assumptions!D35 -> 750 | I21: =Assumptions!D35 -> 750 | J21: =Assumptions!D35 -> 750 | K21: =Assumptions!D35 -> 750 | L21: =Assumptions!D35 -> 750 | M21: =Assumptions!D35 -> 750 | N21: =Assumptions!D36 -> 1500 | O21: =Assumptions!D36 -> 1500 | P21: =Assumptions!D36 -> 1500 | Q21: =Assumptions!D36 -> 1500 | R21: =Assumptions!D36 -> 1500 | S21: =Assumptions!D36 -> 1500 | T21: =Assumptions!D36 -> 1500 | U21: =Assumptions!D36 -> 1500 | V21: =Assumptions!D36 -> 1500 | W21: =Assumptions!D36 -> 1500 | X21: =Assumptions!D36 -> 1500 | Y21: =Assumptions!D36 -> 1500 | Z21: =Assumptions!D37 -> 2000 | AA21: =Assumptions!D37 -> 2000 | AB21: =Assumptions!D37 -> 2000 | AC21: =Assumptions!D37 -> 2000 | AD21: =Assumptions!D37 -> 2000 | AE21: =Assumptions!D37 -> 2000 | AF21: =Assumptions!D37 -> 2000 | AG21: =Assumptions!D37 -> 2000 | AH21: =Assumptions!D37 -> 2000 | AI21: =Assumptions!D37 -> 2000 | AJ21: =Assumptions!D37 -> 2000 | AK21: =Assumptions!D37 -> 2000 | AL21: =SUM(B21:M21) -> 7500 | AM21: =SUM(N21:Y21) -> 18000 | AN21: =SUM(Z21:AK21) -> 24000 | AO21: €420 earned to date → €500 conservative. NOT in MRR.
A22: Clinical B2B referral fees (€/contract/mo, from M6) | B22: =0 -> 0 | C22: =0 -> 0 | D22: =0 -> 0 | E22: =0 -> 0 | F22: =0 -> 0 | G22: =G13*Assumptions!D39 -> 680 | H22: =H13*Assumptions!D39 -> 1360 | I22: =I13*Assumptions!D39 -> 2040 | J22: =J13*Assumptions!D39 -> 2720 | K22: =K13*Assumptions!D39 -> 3400 | L22: =L13*Assumptions!D39 -> 4080 | M22: =M13*Assumptions!D39 -> 4760 | N22: =N13*Assumptions!D39 -> 5440 | O22: =O13*Assumptions!D39 -> 6120 | P22: =P13*Assumptions!D39 -> 6800 | Q22: =Q13*Assumptions!D39 -> 7480 | R22: =R13*Assumptions!D39 -> 8160 | S22: =S13*Assumptions!D39 -> 8840 | T22: =T13*Assumptions!D39 -> 9520 | U22: =U13*Assumptions!D39 -> 10200 | V22: =V13*Assumptions!D39 -> 10880 | W22: =W13*Assumptions!D39 -> 11560 | X22: =X13*Assumptions!D39 -> 12240 | Y22: =Y13*Assumptions!D39 -> 12920 | Z22: =Z13*Assumptions!D39 -> 14360 | AA22: =AA13*Assumptions!D39 -> 15800 | AB22: =AB13*Assumptions!D39 -> 17240 | AC22: =AC13*Assumptions!D39 -> 18680 | AD22: =AD13*Assumptions!D39 -> 20120 | AE22: =AE13*Assumptions!D39 -> 21560 | AF22: =AF13*Assumptions!D39 -> 23000 | AG22: =AG13*Assumptions!D39 -> 24440 | AH22: =AH13*Assumptions!D39 -> 25880 | AI22: =AI13*Assumptions!D39 -> 27320 | AJ22: =AJ13*Assumptions!D39 -> 28760 | AK22: =AK13*Assumptions!D39 -> 30200 | AL22: =SUM(B22:M22) -> 19040 | AM22: =SUM(N22:Y22) -> 110160 | AN22: =SUM(Z22:AK22) -> 267360
A23: Brand partnerships (0 in conservative; upside only) | B23: =0 -> 0 | C23: =0 -> 0 | D23: =0 -> 0 | E23: =0 -> 0 | F23: =0 -> 0 | G23: =0 -> 0 | H23: =0 -> 0 | I23: =0 -> 0 | ... Y23: =0 -> 0 | Z23: =Assumptions!D38 -> 2000 | AA23: =Assumptions!D38 -> 2000 | AB23: =Assumptions!D38 -> 2000 | AC23: =Assumptions!D38 -> 2000 | AD23: =Assumptions!D38 -> 2000 | AE23: =Assumptions!D38 -> 2000 | AF23: =Assumptions!D38 -> 2000 | AG23: =Assumptions!D38 -> 2000 | AH23: =Assumptions!D38 -> 2000 | AI23: =Assumptions!D38 -> 2000 | AJ23: =Assumptions!D38 -> 2000 | AK23: =Assumptions!D38 -> 2000 | AL23: =SUM(B23:M23) -> 0 | AM23: =SUM(N23:Y23) -> 0 | AN23: =SUM(Z23:AK23) -> 24000
A24: TOTAL REVENUE | B24: =B18+B19+B20+B21+B22+B23 -> 244.51 | C24: =C18+C19+C20+C21+C22+C23 -> 380.21305 | D24: =D18+D19+D20+D21+D22+D23 -> 1418.4048 | E24: =E18+E19+E20+E21+E22+E23 -> 3573.9733 | F24: =F18+F19+F20+F21+F22+F23 -> 7461.5036 | G24: =G18+G19+G20+G21+G22+G23 -> 12828.197 | H24: =H18+H19+H20+H21+H22+H23 -> 17997.597 | I24: =I18+I19+I20+I21+I22+I23 -> 23007.469 | ... AK24: =AK18+AK19+AK20+AK21+AK22+AK23 -> 736317.15 | AL24: =SUM(B24:M24) -> 207220.66 | AM24: =SUM(N24:Y24) -> 1381532.2 | AN24: =SUM(Z24:AK24) -> 4943253.2
A25: MRR — recurring only (basic + premium + B2B) | B25: =B18+B19+B20 -> 244.51 | C25: =C18+C19+C20 -> 380.21305 | D25: =D18+D19+D20 -> 668.40476 | E25: =E18+E19+E20 -> 2823.9733 | F25: =F18+F19+F20 -> 6711.5036 | G25: =G18+G19+G20 -> 11398.197 | H25: =H18+H19+H20 -> 15887.597 | I25: =I18+I19+I20 -> 20217.469 | ... AK25: =AK18+AK19+AK20 -> 702117.15 | AL25: =M25 -> 36730.369 | AM25: =Y25 -> 172098.27 | AN25: =AK25 -> 702117.15 | AO25: Events and clinical fees excluded — VCs strip them.
A26: ARR (MRR × 12) | B26: =B25*12 -> 2934.12 | C26: =C25*12 -> 4562.5566 | D26: =D25*12 -> 8020.8571 | E26: =E25*12 -> 33887.68 | F26: =F25*12 -> 80538.044 | G26: =G25*12 -> 136778.36 | H26: =H25*12 -> 190651.17 | I26: =I25*12 -> 242609.63 | ... AK26: =AK25*12 -> 8425405.8 | AL26: =M26 -> 440764.43 | AM26: =Y26 -> 2065179.2 | AN26: =AK26 -> 8425405.8
A28: SECTION 3 — COSTS
A29: [helper] Trailing-12-month B2C gross revenue (fee-tier test) | B29: =SUM(B18:B18)+SUM(B19:B19) -> 244.51 | C29: =SUM(B18:C18)+SUM(B19:C19) -> 624.72305 | D29: =SUM(B18:D18)+SUM(B19:D19) -> 1293.1278 | E29: =SUM(B18:E18)+SUM(B19:E19) -> 4117.1011 | F29: =SUM(B18:F18)+SUM(B19:F19) -> 10828.605 | G29: =SUM(B18:G18)+SUM(B19:G19) -> 21209.352 | H29: =SUM(B18:H18)+SUM(B19:H19) -> 35078.737 | I29: =SUM(B18:I18)+SUM(B19:I19) -> 52293.645 | J29: =SUM(B18:J18)+SUM(B19:J19) -> 72748.949 | K29: =SUM(B18:K18)+SUM(B19:K19) -> 96378.746 | L29: =SUM(B18:L18)+SUM(B19:L19) -> 123158.43 | M29: =SUM(B18:M18)+SUM(B19:M19) -> 153107.67 | N29: =SUM(C18:N18)+SUM(C19:N19) -> 188911.52 | O29: =SUM(D18:O18)+SUM(D19:O19) -> 232357.05 | P29: =SUM(E18:P18)+SUM(E19:P19) -> 283746.11 | Q29: =SUM(F18:Q18)+SUM(F19:Q19) -> 341340.12 | R29: =SUM(G18:R18)+SUM(G19:R19) -> 403631.45 | S29: =SUM(H18:S18)+SUM(H19:S19) -> 471171.3 | T29: =SUM(I18:T18)+SUM(I19:T19) -> 544597.81 | ... AK29: =SUM(Z18:AK18)+SUM(Z19:AK19) -> 4119103
A30: App store fees — CORRECTED (15% under $1M; 30% above) | B30: =IF(B29<Assumptions!D43,(B18+B19)*Assumptions!D41,(B18+B19)*Assumptions!D42) -> 36.6765 | C30: =IF(C29<Assumptions!D43,(C18+C19)*Assumptions!D41,(C18+C19)*Assumptions!D42) -> 57.031958 | D30: =IF(D29<Assumptions!D43,(D18+D19)*Assumptions!D41,(D18+D19)*Assumptions!D42) -> 100.26071 | E30: =IF(E29<Assumptions!D43,(E18+E19)*Assumptions!D41,(E18+E19)*Assumptions!D42) -> 423.596 | F30: =IF(F29<Assumptions!D43,(F18+F19)*Assumptions!D41,(F18+F19)*Assumptions!D42) -> 1006.7255 | G30: =IF(G29<Assumptions!D43,(G18+G19)*Assumptions!D41,(G18+G19)*Assumptions!D42) -> 1557.112 | H30: =IF(H29<Assumptions!D43,(H18+H19)*Assumptions!D41,(H18+H19)*Assumptions!D42) -> 2080.4078 | I30: =IF(I29<Assumptions!D43,(I18+I19)*Assumptions!D41,(I18+I19)*Assumptions!D42) -> 2582.2363 | J30: =IF(J29<Assumptions!D43,(J18+J19)*Assumptions!D41,(J18+J19)*Assumptions!D42) -> 3068.2955 | K30: =IF(K29<Assumptions!D43,(K18+K19)*Assumptions!D41,(K18+K19)*Assumptions!D42) -> 3544.4696 | L30: =IF(L29<Assumptions!D43,(L18+L19)*Assumptions!D41,(L18+L19)*Assumptions!D42) -> 4016.9522 | M30: =IF(M29<Assumptions!D43,(M18+M19)*Assumptions!D41,(M18+M19)*Assumptions!D42) -> 4492.3857 | N30: =IF(N29<Assumptions!D43,(N18+N19)*Assumptions!D41,(N18+N19)*Assumptions!D42) -> 5407.2544 | O30: =IF(O29<Assumptions!D43,(O18+O19)*Assumptions!D41,(O18+O19)*Assumptions!D42) -> 6573.8614 | P30: =IF(P29<Assumptions!D43,(P18+P19)*Assumptions!D41,(P18+P19)*Assumptions!D42) -> 7808.6202 | Q30: =IF(Q29<Assumptions!D43,(Q18+Q19)*Assumptions!D41,(Q18+Q19)*Assumptions!D42) -> 9062.6975 | R30: =IF(R29<Assumptions!D43,(R18+R19)*Assumptions!D41,(R18+R19)*Assumptions!D42) -> 10350.424 | S30: =IF(S29<Assumptions!D43,(S18+S19)*Assumptions!D41,(S18+S19)*Assumptions!D42) -> 11688.09 | T30: =IF(T29<Assumptions!D43,(T18+T19)*Assumptions!D41,(T18+T19)*Assumptions!D42) -> 13094.384 | U30: =IF(U29<Assumptions!D43,(U18+U19)*Assumptions!D41,(U18+U19)*Assumptions!D42) -> 14590.929 | V30: =IF(V29<Assumptions!D43,(V18+V19)*Assumptions!D41,(V18+V19)*Assumptions!D42) -> 16202.893 | W30: =IF(W29<Assumptions!D43,(W18+W19)*Assumptions!D41,(W18+W19)*Assumptions!D42) -> 17959.726 | X30: =IF(X29<Assumptions!D43,(X18+X19)*Assumptions!D41,(X18+X19)*Assumptions!D42) -> 39792.066 | Y30: =IF(Y29<Assumptions!D43,(Y18+Y19)*Assumptions!D41,(Y18+Y19)*Assumptions!D42) -> 44096.23 | Z30: =IF(Z29<Assumptions!D43,(Z18+Z19)*Assumptions!D41,(Z18+Z19)*Assumptions!D42) -> 48887.385 | AA30: =IF(AA29<Assumptions!D43,(AA18+AA19)*Assumptions!D41,(AA18+AA19)*Assumptions!D42) -> 54304.898 | AB30: =IF(AB29<Assumptions!D43,(AB18+AB19)*Assumptions!D41,(AB18+AB19)*Assumptions!D42) -> 60542.181 | AC30: =IF(AC29<Assumptions!D43,(AC18+AC19)*Assumptions!D41,(AC18+AC19)*Assumptions!D42) -> 67761.844 | AD30: =IF(AD29<Assumptions!D43,(AD18+AD19)*Assumptions!D41,(AD18+AD19)*Assumptions!D42) -> 76157.181 | AE30: =IF(AE29<Assumptions!D43,(AE18+AE19)*Assumptions!D41,(AE18+AE19)*Assumptions!D42) -> 85958.003 | AF30: =IF(AF29<Assumptions!D43,(AF18+AF19)*Assumptions!D41,(AF18+AF19)*Assumptions!D42) -> 97437.586 | AG30: =IF(AG29<Assumptions!D43,(AG18+AG19)*Assumptions!D41,(AG18+AG19)*Assumptions!D42) -> 110920.93 | AH30: =IF(AH29<Assumptions!D43,(AH18+AH19)*Assumptions!D41,(AH18+AH19)*Assumptions!D42) -> 126794.61 | AI30: =IF(AI29<Assumptions!D43,(AI18+AI19)*Assumptions!D41,(AI18+AI19)*Assumptions!D42) -> 145518.44 | AJ30: =IF(AJ29<Assumptions!D43,(AJ18+AJ19)*Assumptions!D41,(AJ18+AJ19)*Assumptions!D42) -> 167639.45 | AK30: =IF(AK29<Assumptions!D43,(AK18+AK19)*Assumptions!D41,(AK18+AK19)*Assumptions!D42) -> 193808.4 | AL30: =SUM(B30:M30) -> 22966.15 | AM30: =SUM(N30:Y30) -> 196627.18 | AN30: =SUM(Z30:AK30) -> 1235730.9 | AO30: CORRECTED: 15% until trailing-12mo B2C > ~$1M; 30% after. Original was backwards.
A31: Payment processing (Stripe 1.4% on B2B) | B31: =B20*Assumptions!D44 -> 0 | C31: =C20*Assumptions!D44 -> 0 | D31: =D20*Assumptions!D44 -> 0 | E31: =E20*Assumptions!D44 -> 0 | F31: =F20*Assumptions!D44 -> 0 | G31: =G20*Assumptions!D44 -> 14.2443 | H31: =H20*Assumptions!D44 -> 28.254971 | I31: =I20*Assumptions!D44 -> 42.035845 | J31: =J20*Assumptions!D44 -> 55.59069 | K31: =K20*Assumptions!D44 -> 68.923215 | L31: =L20*Assumptions!D44 -> 82.037065 | M31: =M20*Assumptions!D44 -> 94.935827 | N31: =N20*Assumptions!D44 -> 161.56941 | O31: =O20*Assumptions!D44 -> 180.30372 | P31: =P20*Assumptions!D44 -> 198.73075 | Q31: =Q20*Assumptions!D44 -> 216.85555 | R31: =R20*Assumptions!D44 -> 234.68308 | S31: =S20*Assumptions!D44 -> 252.2182 | T31: =T20*Assumptions!D44 -> 269.46572 | U31: =U20*Assumptions!D44 -> 286.43036 | V31: =V20*Assumptions!D44 -> 303.11675 | W31: =W20*Assumptions!D44 -> 319.52945 | X31: =X20*Assumptions!D44 -> 335.67297 | Y31: =Y20*Assumptions!D44 -> 351.5517 | Z31: =Z20*Assumptions!D44 -> 391.07009 | AA31: =AA20*Assumptions!D44 -> 429.94032 | AB31: =AB20*Assumptions!D44 -> 468.17302 | AC31: =AC20*Assumptions!D44 -> 505.77864 | AD31: =AD20*Assumptions!D44 -> 542.76747 | AE31: =AE20*Assumptions!D44 -> 579.14963 | AF31: =AF20*Assumptions!D44 -> 614.93506 | AG31: =AG20*Assumptions!D44 -> 650.13355 | AH31: =AH20*Assumptions!D44 -> 684.75473 | AI31: =AI20*Assumptions!D44 -> 718.80807 | AJ31: =AJ20*Assumptions!D44 -> 752.30288 | AK31: =AK20*Assumptions!D44 -> 785.24832 | AL31: =SUM(B31:M31) -> 386.02191 | AM31: =SUM(N31:Y31) -> 3110.1277 | AN31: =SUM(Z31:AK31) -> 7123.0618
A32: AI API costs (from M6, scales with users, capped) | B32: =0 -> 0 | C32: =0 -> 0 | D32: =0 -> 0 | E32: =0 -> 0 | F32: =0 -> 0 | G32: =MIN(Assumptions!D48,Assumptions!D46+(G15/500)*Assumptions!D47) -> 669.29839 | H32: =MIN(Assumptions!D48,Assumptions!D46+(H15/500)*Assumptions!D47) -> 762.67055 | I32: =MIN(Assumptions!D48,Assumptions!D46+(I15/500)*Assumptions!D47) -> 853.13965 | J32: =MIN(Assumptions!D48,Assumptions!D46+(J15/500)*Assumptions!D47) -> 941.48222 | K32: =MIN(Assumptions!D48,Assumptions!D46+(K15/500)*Assumptions!D47) -> 1028.5074 | L32: =MIN(Assumptions!D48,Assumptions!D46+(L15/500)*Assumptions!D47) -> 1115.0741 | M32: =MIN(Assumptions!D48,Assumptions!D46+(M15/500)*Assumptions!D47) -> 1202.1112 | N32: =MIN(Assumptions!D48,Assumptions!D46+(N15/500)*Assumptions!D47) -> 1378.7406 | O32: =MIN(Assumptions!D48,Assumptions!D46+(O15/500)*Assumptions!D47) -> 1553.0576 | P32: =MIN(Assumptions!D48,Assumptions!D46+(P15/500)*Assumptions!D47) -> 1726.8004 | Q32: =MIN(Assumptions!D48,Assumptions!D46+(Q15/500)*Assumptions!D47) -> 1901.861 | R32: =MIN(Assumptions!D48,Assumptions!D46+(R15/500)*Assumptions!D47) -> 2080.3313 | S32: =MIN(Assumptions!D48,Assumptions!D46+(S15/500)*Assumptions!D47) -> 2264.5558 | T32: =MIN(Assumptions!D48,Assumptions!D46+(T15/500)*Assumptions!D47) -> 2457.1941 | U32: =MIN(Assumptions!D48,Assumptions!D46+(U15/500)*Assumptions!D47) -> 2661.2933 | V32: =MIN(Assumptions!D48,Assumptions!D46+(V15/500)*Assumptions!D47) -> 2880.3733 | W32: =MIN(Assumptions!D48,Assumptions!D46+(W15/500)*Assumptions!D47) -> 3118.5276 | X32: =MIN(Assumptions!D48,Assumptions!D46+(X15/500)*Assumptions!D47) -> 3380.5429 | Y32: =MIN(Assumptions!D48,Assumptions!D46+(Y15/500)*Assumptions!D47) -> 3500 | Z32: =MIN(Assumptions!D48,Assumptions!D46+(Z15/500)*Assumptions!D47) -> 3500 | AA32: =MIN(Assumptions!D48,Assumptions!D46+(AA15/500)*Assumptions!D47) -> 3500 | AB32: =MIN(Assumptions!D48,Assumptions!D46+(AB15/500)*Assumptions!D47) -> 3500 | AC32: =MIN(Assumptions!D48,Assumptions!D46+(AC15/500)*Assumptions!D47) -> 3500 | AD32: =MIN(Assumptions!D48,Assumptions!D46+(AD15/500)*Assumptions!D47) -> 3500 | AE32: =MIN(Assumptions!D48,Assumptions!D46+(AE15/500)*Assumptions!D47) -> 3500 | AF32: =MIN(Assumptions!D48,Assumptions!D46+(AF15/500)*Assumptions!D47) -> 3500 | AG32: =MIN(Assumptions!D48,Assumptions!D46+(AG15/500)*Assumptions!D47) -> 3500 | AH32: =MIN(Assumptions!D48,Assumptions!D46+(AH15/500)*Assumptions!D47) -> 3500 | AI32: =MIN(Assumptions!D48,Assumptions!D46+(AI15/500)*Assumptions!D47) -> 3500 | AJ32: =MIN(Assumptions!D48,Assumptions!D46+(AJ15/500)*Assumptions!D47) -> 3500 | AK32: =MIN(Assumptions!D48,Assumptions!D46+(AK15/500)*Assumptions!D47) -> 3500 | AL32: =SUM(B32:M32) -> 6572.2835 | AM32: =SUM(N32:Y32) -> 28903.278 | AN32: =SUM(Z32:AK32) -> 42000
A33: Infrastructure & hosting (base + variable, capped) | B33: =80 -> 80 | C33: =80 -> 80 | D33: =MIN(Assumptions!D71,Assumptions!D69+(D15/400)*Assumptions!D70) -> 661.69039 | E33: =MIN(Assumptions!D71,Assumptions!D69+(E15/400)*Assumptions!D70) -> 962.7545 | F33: =MIN(Assumptions!D71,Assumptions!D69+(F15/400)*Assumptions!D70) -> 1245.9885 | G33: =MIN(Assumptions!D71,Assumptions!D69+(G15/400)*Assumptions!D70) -> 1609.869 | H33: =MIN(Assumptions!D71,Assumptions!D69+(H15/400)*Assumptions!D70) -> 1960.0146 | I33: =MIN(Assumptions!D71,Assumptions!D69+(I15/400)*Assumptions!D70) -> 2299.2737 | J33: =MIN(Assumptions!D71,Assumptions!D69+(J15/400)*Assumptions!D70) -> 2630.5583 | K33: =MIN(Assumptions!D71,Assumptions!D69+(K15/400)*Assumptions!D70) -> 2956.9026 | L33: =MIN(Assumptions!D71,Assumptions!D69+(L15/400)*Assumptions!D70) -> 3281.528 | M33: =MIN(Assumptions!D71,Assumptions!D69+(M15/400)*Assumptions!D70) -> 3607.917 | N33: =MIN(Assumptions!D71,Assumptions!D69+(N15/400)*Assumptions!D70) -> 4270.2771 | O33: =MIN(Assumptions!D71,Assumptions!D69+(O15/400)*Assumptions!D70) -> 4923.9659 | P33: =MIN(Assumptions!D71,Assumptions!D69+(P15/400)*Assumptions!D70) -> 5575.5015 | Q33: =MIN(Assumptions!D71,Assumptions!D69+(Q15/400)*Assumptions!D70) -> 6231.9789 | R33: =MIN(Assumptions!D71,Assumptions!D69+(R15/400)*Assumptions!D70) -> 6901.2423 | S33: =MIN(Assumptions!D71,Assumptions!D69+(S15/400)*Assumptions!D70) -> 7592.0842 | T33: =MIN(Assumptions!D71,Assumptions!D69+(T15/400)*Assumptions!D70) -> 8314.4779 | U33: =MIN(Assumptions!D71,Assumptions!D69+(U15/400)*Assumptions!D70) -> 9079.8499 | V33: =MIN(Assumptions!D71,Assumptions!D69+(V15/400)*Assumptions!D70) -> 9901.3997 | W33: =MIN(Assumptions!D71,Assumptions!D69+(W15/400)*Assumptions!D70) -> 10794.478 | X33: =MIN(Assumptions!D71,Assumptions!D69+(X15/400)*Assumptions!D70) -> 11777.036 | Y33: =MIN(Assumptions!D71,Assumptions!D69+(Y15/400)*Assumptions!D70) -> 12865.654 | Z33: =MIN(Assumptions!D71,Assumptions!D69+(Z15/400)*Assumptions!D70) -> 14176.09 | AA33: =MIN(Assumptions!D71,Assumptions!D69+(AA15/400)*Assumptions!D70) -> 15658.043 | AB33: =MIN(Assumptions!D71,Assumptions!D69+(AB15/400)*Assumptions!D70) -> 17346.544 | AC33: =MIN(Assumptions!D71,Assumptions!D69+(AC15/400)*Assumptions!D70) -> 18000 | AD33: =MIN(Assumptions!D71,Assumptions!D69+(AD15/400)*Assumptions!D70) -> 18000 | AE33: =MIN(Assumptions!D71,Assumptions!D69+(AE15/400)*Assumptions!D70) -> 18000 | AF33: =MIN(Assumptions!D71,Assumptions!D69+(AF15/400)*Assumptions!D70) -> 18000 | AG33: =MIN(Assumptions!D71,Assumptions!D69+(AG15/400)*Assumptions!D70) -> 18000 | AH33: =MIN(Assumptions!D71,Assumptions!D69+(AH15/400)*Assumptions!D70) -> 18000 | AI33: =MIN(Assumptions!D71,Assumptions!D69+(AI15/400)*Assumptions!D70) -> 18000 | AJ33: =MIN(Assumptions!D71,Assumptions!D69+(AJ15/400)*Assumptions!D70) -> 18000 | AK33: =MIN(Assumptions!D71,Assumptions!D69+(AK15/400)*Assumptions!D70) -> 18000 | AL33: =SUM(B33:M33) -> 21376.497 | AM33: =SUM(N33:Y33) -> 98227.946 | AN33: =SUM(Z33:AK33) -> 209180.68
A34: Founder stipends ×3 | B34: =Assumptions!D54 -> 900 | C34: =Assumptions!D54 -> 900 | D34: =Assumptions!D54 -> 900 | E34: =Assumptions!D54 -> 900 | F34: =Assumptions!D54 -> 900 | G34: =Assumptions!D54 -> 900 | H34: =Assumptions!D54 -> 900 | I34: =Assumptions!D54 -> 900 | J34: =Assumptions!D54 -> 900 | K34: =Assumptions!D54 -> 900 | L34: =Assumptions!D54 -> 900 | M34: =Assumptions!D54 -> 900 | N34: =Assumptions!D55 -> 9000 | O34: =Assumptions!D55 -> 9000 | P34: =Assumptions!D55 -> 9000 | Q34: =Assumptions!D55 -> 9000 | R34: =Assumptions!D55 -> 9000 | S34: =Assumptions!D55 -> 9000 | T34: =Assumptions!D55 -> 9000 | U34: =Assumptions!D55 -> 9000 | V34: =Assumptions!D55 -> 9000 | W34: =Assumptions!D55 -> 9000 | X34: =Assumptions!D55 -> 9000 | Y34: =Assumptions!D55 -> 9000 | Z34: =Assumptions!D76 -> 12000 | AA34: =Assumptions!D76 -> 12000 | AB34: =Assumptions!D76 -> 12000 | AC34: =Assumptions!D76 -> 12000 | AD34: =Assumptions!D76 -> 12000 | AE34: =Assumptions!D76 -> 12000 | AF34: =Assumptions!D76 -> 12000 | AG34: =Assumptions!D76 -> 12000 | AH34: =Assumptions!D76 -> 12000 | AI34: =Assumptions!D76 -> 12000 | AJ34: =Assumptions!D76 -> 12000 | AK34: =Assumptions!D76 -> 12000 | AL34: =SUM(B34:M34) -> 10800 | AM34: =SUM(N34:Y34) -> 108000 | AN34: =SUM(Z34:AK34) -> 144000
A35: Team salaries & contractors | B35: =0 -> 0 | C35: =0 -> 0 | D35: =Assumptions!D56 -> 6000 | E35: =Assumptions!D56 -> 6000 | F35: =Assumptions!D56 -> 6000 | G35: =Assumptions!D56 -> 6000 | H35: =Assumptions!D57 -> 11000 | I35: =Assumptions!D57 -> 11000 | J35: =Assumptions!D57 -> 11000 | K35: =Assumptions!D57 -> 11000 | L35: =Assumptions!D57 -> 11000 | M35: =Assumptions!D57 -> 11000 | N35: =Assumptions!D58 -> 38000 | O35: =Assumptions!D58 -> 38000 | P35: =Assumptions!D58 -> 38000 | Q35: =Assumptions!D58 -> 38000 | R35: =Assumptions!D58 -> 38000 | S35: =Assumptions!D58 -> 38000 | T35: =Assumptions!D58 -> 38000 | U35: =Assumptions!D58 -> 38000 | V35: =Assumptions!D58 -> 38000 | W35: =Assumptions!D58 -> 38000 | X35: =Assumptions!D58 -> 38000 | Y35: =Assumptions!D58 -> 38000 | Z35: =Assumptions!D59 -> 85000 | AA35: =Assumptions!D59 -> 85000 | AB35: =Assumptions!D59 -> 85000 | AC35: =Assumptions!D59 -> 85000 | AD35: =Assumptions!D59 -> 85000 | AE35: =Assumptions!D59 -> 85000 | AF35: =Assumptions!D59 -> 85000 | AG35: =Assumptions!D59 -> 85000 | AH35: =Assumptions!D59 -> 85000 | AI35: =Assumptions!D59 -> 85000 | AJ35: =Assumptions!D59 -> 85000 | AK35: =Assumptions!D59 -> 85000 | AL35: =SUM(B35:M35) -> 90000 | AM35: =SUM(N35:Y35) -> 456000 | AN35: =SUM(Z35:AK35) -> 1020000
A36: Marketing (content/tools base + paid social) | B36: =Assumptions!D60 -> 1500 | C36: =Assumptions!D60 -> 1500 | D36: =Assumptions!D60 -> 1500 | E36: =Assumptions!D60+Assumptions!D12 -> 12500 | F36: =Assumptions!D60+Assumptions!D12 -> 12500 | G36: =Assumptions!D60+Assumptions!D12 -> 12500 | H36: =Assumptions!D60+Assumptions!D12 -> 12500 | I36: =Assumptions!D60+Assumptions!D12 -> 12500 | J36: =Assumptions!D60+Assumptions!D12 -> 12500 | K36: =Assumptions!D60+Assumptions!D12 -> 12500 | L36: =Assumptions!D60+Assumptions!D12 -> 12500 | M36: =Assumptions!D60+Assumptions!D12 -> 12500 | N36: =Assumptions!D61+Assumptions!D13 -> 30500 | O36: =Assumptions!D61+Assumptions!D13 -> 30500 | P36: =Assumptions!D61+Assumptions!D13 -> 30500 | Q36: =Assumptions!D61+Assumptions!D13 -> 30500 | R36: =Assumptions!D61+Assumptions!D13 -> 30500 | S36: =Assumptions!D61+Assumptions!D13 -> 30500 | T36: =Assumptions!D61+Assumptions!D13 -> 30500 | U36: =Assumptions!D61+Assumptions!D13 -> 30500 | V36: =Assumptions!D61+Assumptions!D13 -> 30500 | W36: =Assumptions!D61+Assumptions!D13 -> 30500 | X36: =Assumptions!D61+Assumptions!D13 -> 30500 | Y36: =Assumptions!D61+Assumptions!D13 -> 30500 | Z36: =Assumptions!D62+Assumptions!D14 -> 24500 | AA36: =Assumptions!D62+Assumptions!D14 -> 24500 | AB36: =Assumptions!D62+Assumptions!D14 -> 24500 | AC36: =Assumptions!D62+Assumptions!D14 -> 24500 | AD36: =Assumptions!D62+Assumptions!D14 -> 24500 | AE36: =Assumptions!D62+Assumptions!D14 -> 24500 | AF36: =Assumptions!D62+Assumptions!D14 -> 24500 | AG36: =Assumptions!D62+Assumptions!D14 -> 24500 | AH36: =Assumptions!D62+Assumptions!D14 -> 24500 | AI36: =Assumptions!D62+Assumptions!D14 -> 24500 | AJ36: =Assumptions!D62+Assumptions!D14 -> 24500 | AK36: =Assumptions!D62+Assumptions!D14 -> 24500 | AL36: =SUM(B36:M36) -> 117000 | AM36: =SUM(N36:Y36) -> 366000 | AN36: =SUM(Z36:AK36) -> 294000
A37: Clinical partnerships (cost) | B37: =0 -> 0 | C37: =0 -> 0 | D37: =Assumptions!D63 -> 900 | E37: =Assumptions!D63 -> 900 | F37: =Assumptions!D63 -> 900 | G37: =Assumptions!D63 -> 900 | H37: =Assumptions!D63 -> 900 | I37: =Assumptions!D63 -> 900 | J37: =Assumptions!D63 -> 900 | K37: =Assumptions!D63 -> 900 | L37: =Assumptions!D63 -> 900 | M37: =Assumptions!D63 -> 900 | N37: =Assumptions!D64 -> 1500 | O37: =Assumptions!D64 -> 1500 | P37: =Assumptions!D64 -> 1500 | Q37: =Assumptions!D64 -> 1500 | R37: =Assumptions!D64 -> 1500 | S37: =Assumptions!D64 -> 1500 | T37: =Assumptions!D64 -> 1500 | U37: =Assumptions!D64 -> 1500 | V37: =Assumptions!D64 -> 1500 | W37: =Assumptions!D64 -> 1500 | X37: =Assumptions!D64 -> 1500 | Y37: =Assumptions!D64 -> 1500 | Z37: =Assumptions!D65 -> 2200 | AA37: =Assumptions!D65 -> 2200 | AB37: =Assumptions!D65 -> 2200 | AC37: =Assumptions!D65 -> 2200 | AD37: =Assumptions!D65 -> 2200 | AE37: =Assumptions!D65 -> 2200 | AF37: =Assumptions!D65 -> 2200 | AG37: =Assumptions!D65 -> 2200 | AH37: =Assumptions!D65 -> 2200 | AI37: =Assumptions!D65 -> 2200 | AJ37: =Assumptions!D65 -> 2200 | AK37: =Assumptions!D65 -> 2200 | AL37: =SUM(B37:M37) -> 9000 | AM37: =SUM(N37:Y37) -> 18000 | AN37: =SUM(Z37:AK37) -> 26400
A38: Legal & admin | B38: =Assumptions!D66 -> 800 | C38: =Assumptions!D66 -> 800 | D38: =Assumptions!D66 -> 800 | E38: =Assumptions!D67 -> 350 | F38: =Assumptions!D67 -> 350 | G38: =Assumptions!D67 -> 350 | H38: =Assumptions!D67 -> 350 | I38: =Assumptions!D67 -> 350 | J38: =Assumptions!D67 -> 350 | K38: =Assumptions!D67 -> 350 | L38: =Assumptions!D67 -> 350 | M38: =Assumptions!D67 -> 350 | N38: =Assumptions!D67 -> 350 | O38: =Assumptions!D67 -> 350 | P38: =Assumptions!D67 -> 350 | Q38: =Assumptions!D67 -> 350 | R38: =Assumptions!D67 -> 350 | S38: =Assumptions!D67 -> 350 | T38: =Assumptions!D67 -> 350 | U38: =Assumptions!D67 -> 350 | V38: =Assumptions!D67 -> 350 | W38: =Assumptions!D67 -> 350 | X38: =Assumptions!D67 -> 350 | Y38: =Assumptions!D67 -> 350 | Z38: =Assumptions!D67 -> 350 | AA38: =Assumptions!D67 -> 350 | AB38: =Assumptions!D67 -> 350 | AC38: =Assumptions!D67 -> 350 | AD38: =Assumptions!D67 -> 350 | AE38: =Assumptions!D67 -> 350 | AF38: =Assumptions!D67 -> 350 | AG38: =Assumptions!D67 -> 350 | AH38: =Assumptions!D67 -> 350 | AI38: =Assumptions!D67 -> 350 | AJ38: =Assumptions!D67 -> 350 | AK38: =Assumptions!D67 -> 350 | AL38: =SUM(B38:M38) -> 5550 | AM38: =SUM(N38:Y38) -> 4200 | AN38: =SUM(Z38:AK38) -> 4200
A39: HealthKit + Health Connect build (M4–6, one-off) | B39: =0 -> 0 | C39: =0 -> 0 | D39: =0 -> 0 | E39: =Assumptions!D50/3 -> 2666.6667 | F39: =Assumptions!D50/3 -> 2666.6667 | G39: =Assumptions!D50/3 -> 2666.6667 | H39: =0 -> 0 | I39: =0 -> 0 | J39: =0 -> 0 | K39: =0 -> 0 | L39: =0 -> 0 | M39: =0 -> 0 | N39: =0 -> 0 | O39: =0 -> 0 | ... AK39: =0 -> 0 | AL39: =SUM(B39:M39) -> 8000 | AM39: =SUM(N39:Y39) -> 0 | AN39: =SUM(Z39:AK39) -> 0
A40: Oura Ring integration (M15, one-off) | B40: =0 -> 0 | C40: =0 -> 0 | D40: =0 -> 0 | E40: =0 -> 0 | F40: =0 -> 0 | G40: =0 -> 0 | H40: =0 -> 0 | I40: =0 -> 0 | ... O40: =0 -> 0 | P40: =Assumptions!D51 -> 5000 | Q40: =0 -> 0 | R40: =0 -> 0 | S40: =0 -> 0 | T40: =0 -> 0 | U40: =0 -> 0 | V40: =0 -> 0 | W40: =0 -> 0 | X40: =0 -> 0 | ... AK40: =0 -> 0 | AL40: =SUM(B40:M40) -> 0 | AM40: =SUM(N40:Y40) -> 5000 | AN40: =SUM(Z40:AK40) -> 0
A41: Predictive AI dev (M20–M23, €3K/mo) | B41: =0 -> 0 | C41: =0 -> 0 | D41: =0 -> 0 | E41: =0 -> 0 | F41: =0 -> 0 | G41: =0 -> 0 | H41: =0 -> 0 | I41: =0 -> 0 | ... T41: =0 -> 0 | U41: =Assumptions!D52 -> 3000 | V41: =Assumptions!D52 -> 3000 | W41: =Assumptions!D52 -> 3000 | X41: =Assumptions!D52 -> 3000 | Y41: =0 -> 0 | Z41: =0 -> 0 | AA41: =0 -> 0 | AB41: =0 -> 0 | AC41: =0 -> 0 | AD41: =0 -> 0 | AE41: =0 -> 0 | AF41: =0 -> 0 | ... AK41: =0 -> 0 | AL41: =SUM(B41:M41) -> 0 | AM41: =SUM(N41:Y41) -> 12000 | AN41: =SUM(Z41:AK41) -> 0
A42: TOTAL COSTS | B42: =B30+B31+B32+B33+B34+B35+B36+B37+B38+B39+B40+B41 -> 3316.6765 | C42: =C30+C31+C32+C33+C34+C35+C36+C37+C38+C39+C40+C41 -> 3337.032 | D42: =D30+D31+D32+D33+D34+D35+D36+D37+D38+D39+D40+D41 -> 10861.951 | E42: =E30+E31+E32+E33+E34+E35+E36+E37+E38+E39+E40+E41 -> 24703.017 | F42: =F30+F31+F32+F33+F34+F35+F36+F37+F38+F39+F40+F41 -> 25569.381 | G42: =G30+G31+G32+G33+G34+G35+G36+G37+G38+G39+G40+G41 -> 27167.19 | H42: =H30+H31+H32+H33+H34+H35+H36+H37+H38+H39+H40+H41 -> 30481.348 | I42: =I30+I31+I32+I33+I34+I35+I36+I37+I38+I39+I40+I41 -> 31426.685 | ... AK42: =AK30+AK31+AK32+AK33+AK34+AK35+AK36+AK37+AK38+AK39+AK40+AK41 -> 340143.64 | AL42: =SUM(B42:M42) -> 291650.95 | AM42: =SUM(N42:Y42) -> 1296068.5 | AN42: =SUM(Z42:AK42) -> 2982634.6
A44: SECTION 4 — PROFIT & LOSS & CASH
A45: Gross margin % — FIXED (from annual revenue/COGS sums, not monthly average) | B45: =IF(B24=0,0,(B24-(B30+B31+B32))/B24) -> 0.85 | C45: =IF(C24=0,0,(C24-(C30+C31+C32))/C24) -> 0.85 | D45: =IF(D24=0,0,(D24-(D30+D31+D32))/D24) -> 0.92931445 | E45: =IF(E24=0,0,(E24-(E30+E31+E32))/E24) -> 0.88147757 | F45: =IF(F24=0,0,(F24-(F30+F31+F32))/F24) -> 0.86507739 | G45: =IF(G24=0,0,(G24-(G30+G31+G32))/G24) -> 0.82533362 | H45: =IF(H24=0,0,(H24-(H30+H31+H32))/H24) -> 0.84046019 | I45: =IF(I24=0,0,(I24-(I30+I31+I32))/I24) -> 0.84885726 | ... AK45: =IF(AK24=0,0,(AK24-(AK30+AK31+AK32))/AK24) -> 0.73096696 | AL45: =IF(SUM(B24:M24)=0,0,(SUM(B24:M24)-(SUM(B30:M30)+SUM(B31:M31)+SUM(B32:M32)))/SUM(B24:M24)) -> 0.85559135 | AM45: =IF(SUM(N24:Y24)=0,0,(SUM(N24:Y24)-(SUM(N30:Y30)+SUM(N31:Y31)+SUM(N32:Y32)))/SUM(N24:Y24)) -> 0.83450216 | AN45: =IF(SUM(Z24:AK24)=0,0,(SUM(Z24:AK24)-(SUM(Z30:AK30)+SUM(Z31:AK31)+SUM(Z32:AK32)))/SUM(Z24:AK24)) -> 0.74007927 | AO45: CORRECTED: annual cell = (annual revenue - annual COGS) / annual revenue. Old formula averaged monthly %s → ~6% nonsense.
A46: Net burn / profit (negative = burning) | B46: =B24-B42 -> -3072.1665 | C46: =C24-C42 -> -2956.8189 | D46: =D24-D42 -> -9443.5463 | E46: =E24-E42 -> -21129.044 | F46: =F24-F42 -> -18107.877 | G46: =G24-G42 -> -14338.993 | H46: =H24-H42 -> -12483.751 | I46: =I24-I42 -> -8419.2165 | ... AK46: =AK24-AK42 -> 396173.51 | AL46: =SUM(B46:M46) -> -84430.292 | AM46: =SUM(N46:Y46) -> 85463.636 | AN46: =SUM(Z46:AK46) -> 1960618.5
A47: Financing inflows (pre-seed M1; seed explicit, not in revenue) | B47: =Assumptions!D73 -> 350000 | C47: =IF(2=Assumptions!D74,Assumptions!D75,0) -> 0 | D47: =IF(3=Assumptions!D74,Assumptions!D75,0) -> 0 | E47: =IF(4=Assumptions!D74,Assumptions!D75,0) -> 0 | F47: =IF(5=Assumptions!D74,Assumptions!D75,0) -> 0 | G47: =IF(6=Assumptions!D74,Assumptions!D75,0) -> 0 | H47: =IF(7=Assumptions!D74,Assumptions!D75,0) -> 0 | I47: =IF(8=Assumptions!D74,Assumptions!D75,0) -> 0 | J47: =IF(9=Assumptions!D74,Assumptions!D75,0) -> 0 | K47: =IF(10=Assumptions!D74,Assumptions!D75,0) -> 0 | L47: =IF(11=Assumptions!D74,Assumptions!D75,0) -> 0 | M47: =IF(12=Assumptions!D74,Assumptions!D75,0) -> 0 | N47: =IF(13=Assumptions!D74,Assumptions!D75,0) -> 3000000 | O47: =IF(14=Assumptions!D74,Assumptions!D75,0) -> 0 | P47: =IF(15=Assumptions!D74,Assumptions!D75,0) -> 0 | Q47: =IF(16=Assumptions!D74,Assumptions!D75,0) -> 0 | R47: =IF(17=Assumptions!D74,Assumptions!D75,0) -> 0 | S47: =IF(18=Assumptions!D74,Assumptions!D75,0) -> 0 | T47: =IF(19=Assumptions!D74,Assumptions!D75,0) -> 0 | U47: =IF(20=Assumptions!D74,Assumptions!D75,0) -> 0 | V47: =IF(21=Assumptions!D74,Assumptions!D75,0) -> 0 | W47: =IF(22=Assumptions!D74,Assumptions!D75,0) -> 0 | X47: =IF(23=Assumptions!D74,Assumptions!D75,0) -> 0 | Y47: =IF(24=Assumptions!D74,Assumptions!D75,0) -> 0 | Z47: =IF(25=Assumptions!D74,Assumptions!D75,0) -> 0 | AA47: =IF(26=Assumptions!D74,Assumptions!D75,0) -> 0 | AB47: =IF(27=Assumptions!D74,Assumptions!D75,0) -> 0 | AC47: =IF(28=Assumptions!D74,Assumptions!D75,0) -> 0 | AD47: =IF(29=Assumptions!D74,Assumptions!D75,0) -> 0 | AE47: =IF(30=Assumptions!D74,Assumptions!D75,0) -> 0 | AF47: =IF(31=Assumptions!D74,Assumptions!D75,0) -> 0 | AG47: =IF(32=Assumptions!D74,Assumptions!D75,0) -> 0 | AH47: =IF(33=Assumptions!D74,Assumptions!D75,0) -> 0 | AI47: =IF(34=Assumptions!D74,Assumptions!D75,0) -> 0 | AJ47: =IF(35=Assumptions!D74,Assumptions!D75,0) -> 0 | AK47: =IF(36=Assumptions!D74,Assumptions!D75,0) -> 0 | AL47: =SUM(B47:M47) -> 350000 | AM47: =SUM(N47:Y47) -> 3000000 | AN47: =SUM(Z47:AK47) -> 0 | AO47: Seed shown as explicit injection so runway dependence is honest. NOT revenue.
A48: Ending cash (cumulative) | B48: =B46+B47 -> 346927.83 | C48: =B48+C46+C47 -> 343971.01 | D48: =C48+D46+D47 -> 334527.47 | E48: =D48+E46+E47 -> 313398.42 | F48: =E48+F46+F47 -> 295290.55 | G48: =F48+G46+G47 -> 280951.55 | H48: =G48+H46+H47 -> 268467.8 | I48: =H48+I46+I47 -> 260048.59 | J48: =I48+J46+J47 -> 255598.73 | ... AK48: =AJ48+AK46+AK47 -> 5311651.8 | AL48: =M48 -> 265569.71 | AM48: =Y48 -> 3351033.3 | AN48: =AK48 -> 5311651.8
A50: SECTION 5 — UNIT ECONOMICS (single consistent method; all linked to assumptions)
A51: LTV — B2C basic (price × (1-app_fee) ÷ Y2 avg churn) | B51: =Assumptions!D4*(1-Assumptions!D41)/AVERAGE(N9:Y9) -> 67.922866 | AO51: ONE consistent formula. Original mixed €42.42 / €40.92 / €34.93 across three lines.
A52: LTV — B2C premium (price × (1-app_fee) ÷ prem churn) | B52: =Assumptions!D5*(1-Assumptions!D41)/Assumptions!D27 -> 315.47143
A53: CAC — paid social Y1 (€) | B53: =Assumptions!D15 -> 15
A54: LTV:CAC — B2C basic paid channel (VC floor: 3×) | B54: =IF(B53=0,0,B51/B53) -> 4.5281911 | AO54: VC floor 3×. Corrected LTV and CAC feed this — one consistent calculation.
A55: Payback period — paid social (months) | B55: =IF(B53=0,0,B53/(Assumptions!D4*(1-Assumptions!D41))) -> 3.5364847
A56: CAC — organic Y1 (€4.20 — events €500 + tools €200 ÷ ~167 users) | B56: 4.2
A57: LTV:CAC — organic | B57: =IF(B56=0,0,B51/B56) -> 16.172111

Sheet Ambitious
A1: NutriSync — Ambitious Scenario | All inputs from Assumptions sheet | Blue = inputs, Black = formulas
A2: METRIC | B2: M1 | C2: M2 | D2: M3 | E2: M4 | F2: M5 | G2: M6 | H2: M7 | I2: M8 | J2: M9 | K2: M10 | L2: M11 | M2: M12 | N2: M13 | O2: M14 | P2: M15 | Q2: M16 | R2: M17 | S2: M18 | T2: M19 | U2: M20 | V2: M21 | W2: M22 | X2: M23 | Y2: M24 | Z2: M25 | AA2: M26 | AB2: M27 | AC2: M28 | AD2: M29 | AE2: M30 | AF2: M31 | AG2: M32 | AH2: M33 | AI2: M34 | AJ2: M35 | AK2: M36 | AL2: Y1 Total | AM2: Y2 Total | AN2: Y3 Total | AO2: Notes / Formula
A3: Year | B3: 1 | C3: 1 | D3: 1 | E3: 1 | F3: 1 | G3: 1 | H3: 1 | I3: 1 | J3: 1 | K3: 1 | L3: 1 | M3: 1 | N3: 2 | O3: 2 | P3: 2 | Q3: 2 | R3: 2 | S3: 2 | T3: 2 | U3: 2 | V3: 2 | W3: 2 | X3: 2 | Y3: 2 | Z3: 3 | AA3: 3 | AB3: 3 | AC3: 3 | AD3: 3 | AE3: 3 | AF3: 3 | AG3: 3 | AH3: 3 | AI3: 3 | AJ3: 3 | AK3: 3
A4: SECTION 1 — USER PROJECTIONS
A5: New organic free users/mo | B5: =Assumptions!E9 -> 420 | C5: =B5*(1+Assumptions!E10) -> 504 | D5: =C5*(1+Assumptions!E10) -> 604.8 | E5: =D5*(1+Assumptions!E10) -> 725.76 | F5: =E5*(1+Assumptions!E10) -> 870.912 | G5: =F5*(1+Assumptions!E10) -> 1045.0944 | H5: =G5*(1+Assumptions!E10) -> 1254.1133 | I5: =H5*(1+Assumptions!E10) -> 1504.9359 | J5: =I5*(1+Assumptions!E10) -> 1805.9231 | K5: =J5*(1+Assumptions!E10) -> 2167.1077 | L5: =K5*(1+Assumptions!E10) -> 2600.5293 | M5: =L5*(1+Assumptions!E10) -> 3120.6352 | N5: =M5*(1+Assumptions!E10) -> 3744.7622 | O5: =N5*(1+Assumptions!E10) -> 4493.7146 | P5: =O5*(1+Assumptions!E10) -> 5392.4576 | Q5: =P5*(1+Assumptions!E10) -> 6470.9491 | R5: =Q5*(1+Assumptions!E10) -> 7765.1389 | S5: =R5*(1+Assumptions!E10) -> 9318.1666 | T5: =S5*(1+Assumptions!E10) -> 11181.8 | U5: =T5*(1+Assumptions!E10) -> 13418.16 | V5: =U5*(1+Assumptions!E10) -> 16101.792 | W5: =V5*(1+Assumptions!E10) -> 19322.15 | X5: =W5*(1+Assumptions!E10) -> 23186.58 | Y5: =X5*(1+Assumptions!E10) -> 27823.897 | Z5: =Y5*(1+Assumptions!E10) -> 33388.676 | AA5: =Z5*(1+Assumptions!E10) -> 40066.411 | AB5: =AA5*(1+Assumptions!E10) -> 48079.693 | AC5: =AB5*(1+Assumptions!E10) -> 57695.632 | AD5: =AC5*(1+Assumptions!E10) -> 69234.758 | AE5: =AD5*(1+Assumptions!E10) -> 83081.71 | AF5: =AE5*(1+Assumptions!E10) -> 99698.052 | AG5: =AF5*(1+Assumptions!E10) -> 119637.66 | AH5: =AG5*(1+Assumptions!E10) -> 143565.19 | AI5: =AH5*(1+Assumptions!E10) -> 172278.23 | AJ5: =AI5*(1+Assumptions!E10) -> 206733.88 | AK5: =AJ5*(1+Assumptions!E10) -> 248080.66 | AL5: =SUM(B5:M5) -> 16623.811 | AM5: =SUM(N5:Y5) -> 148219.57 | AN5: =SUM(Z5:AK5) -> 1321540.6 | AO5: Compounds from M1 at organic growth rate.
A6: → New paid: organic conversion (one-off per month's new free users) | B6: =B5*Assumptions!E11 -> 54.6 | C6: =C5*Assumptions!E11 -> 65.52 | D6: =D5*Assumptions!E11 -> 78.624 | E6: =E5*Assumptions!E11 -> 94.3488 | F6: =F5*Assumptions!E11 -> 113.21856 | G6: =G5*Assumptions!E11 -> 135.86227 | H6: =H5*Assumptions!E11 -> 163.03473 | I6: =I5*Assumptions!E11 -> 195.64167 | J6: =J5*Assumptions!E11 -> 234.77001 | K6: =K5*Assumptions!E11 -> 281.72401 | L6: =L5*Assumptions!E11 -> 338.06881 | M6: =M5*Assumptions!E11 -> 405.68257 | N6: =N5*Assumptions!E11 -> 486.81908 | O6: =O5*Assumptions!E11 -> 584.1829 | P6: =P5*Assumptions!E11 -> 701.01948 | Q6: =Q5*Assumptions!E11 -> 841.22338 | R6: =R5*Assumptions!E11 -> 1009.4681 | S6: =S5*Assumptions!E11 -> 1211.3617 | T6: =T5*Assumptions!E11 -> 1453.634 | U6: =U5*Assumptions!E11 -> 1744.3608 | V6: =V5*Assumptions!E11 -> 2093.233 | W6: =W5*Assumptions!E11 -> 2511.8795 | X6: =X5*Assumptions!E11 -> 3014.2555 | Y6: =Y5*Assumptions!E11 -> 3617.1065 | Z6: =Z5*Assumptions!E11 -> 4340.5279 | AA6: =AA5*Assumptions!E11 -> 5208.6334 | AB6: =AB5*Assumptions!E11 -> 6250.3601 | AC6: =AC5*Assumptions!E11 -> 7500.4321 | AD6: =AD5*Assumptions!E11 -> 9000.5186 | AE6: =AE5*Assumptions!E11 -> 10800.622 | AF6: =AF5*Assumptions!E11 -> 12960.747 | AG6: =AG5*Assumptions!E11 -> 15552.896 | AH6: =AH5*Assumptions!E11 -> 18663.475 | AI6: =AI5*Assumptions!E11 -> 22396.17 | AJ6: =AJ5*Assumptions!E11 -> 26875.404 | AK6: =AK5*Assumptions!E11 -> 32250.485 | AL6: =SUM(B6:M6) -> 2161.0954 | AM6: =SUM(N6:Y6) -> 19268.544 | AN6: =SUM(Z6:AK6) -> 171800.27 | AO6: 5–8% one-off per month (NOT monthly to pool). Benchmark: RevenueCat H&F median 6.9%.
A7: → New paid: paid social (budget ÷ CAC) | B7: =0 -> 0 | C7: =0 -> 0 | D7: =0 -> 0 | E7: =Assumptions!E12/Assumptions!E15 -> 1166.6667 | F7: =Assumptions!E12/Assumptions!E15 -> 1166.6667 | G7: =Assumptions!E12/Assumptions!E15 -> 1166.6667 | H7: =Assumptions!E12/Assumptions!E15 -> 1166.6667 | I7: =Assumptions!E12/Assumptions!E15 -> 1166.6667 | J7: =Assumptions!E12/Assumptions!E15 -> 1166.6667 | K7: =Assumptions!E12/Assumptions!E15 -> 1166.6667 | L7: =Assumptions!E12/Assumptions!E15 -> 1166.6667 | M7: =Assumptions!E12/Assumptions!E15 -> 1166.6667 | N7: =Assumptions!E13/Assumptions!E16 -> 1785.7143 | O7: =Assumptions!E13/Assumptions!E16 -> 1785.7143 | P7: =Assumptions!E13/Assumptions!E16 -> 1785.7143 | Q7: =Assumptions!E13/Assumptions!E16 -> 1785.7143 | R7: =Assumptions!E13/Assumptions!E16 -> 1785.7143 | S7: =Assumptions!E13/Assumptions!E16 -> 1785.7143 | T7: =Assumptions!E13/Assumptions!E16 -> 1785.7143 | U7: =Assumptions!E13/Assumptions!E16 -> 1785.7143 | V7: =Assumptions!E13/Assumptions!E16 -> 1785.7143 | W7: =Assumptions!E13/Assumptions!E16 -> 1785.7143 | X7: =Assumptions!E13/Assumptions!E16 -> 1785.7143 | Y7: =Assumptions!E13/Assumptions!E16 -> 1785.7143 | Z7: =Assumptions!E14/Assumptions!E16 -> 2714.2857 | AA7: =Assumptions!E14/Assumptions!E16 -> 2714.2857 | AB7: =Assumptions!E14/Assumptions!E16 -> 2714.2857 | AC7: =Assumptions!E14/Assumptions!E16 -> 2714.2857 | AD7: =Assumptions!E14/Assumptions!E16 -> 2714.2857 | AE7: =Assumptions!E14/Assumptions!E16 -> 2714.2857 | AF7: =Assumptions!E14/Assumptions!E16 -> 2714.2857 | AG7: =Assumptions!E14/Assumptions!E16 -> 2714.2857 | AH7: =Assumptions!E14/Assumptions!E16 -> 2714.2857 | AI7: =Assumptions!E14/Assumptions!E16 -> 2714.2857 | AJ7: =Assumptions!E14/Assumptions!E16 -> 2714.2857 | AK7: =Assumptions!E14/Assumptions!E16 -> 2714.2857 | AL7: =SUM(B7:M7) -> 10500 | AM7: =SUM(N7:Y7) -> 21428.571 | AN7: =SUM(Z7:AK7) -> 32571.429 | AO7: Budget / CAC. CAC corrected: €20 Y1 conservative (not €6–8; install alone $3.70–4.70).
A8: % of paid users with wearable connected | B8: =0 -> 0 | C8: =0 -> 0 | D8: =0 -> 0 | E8: =MIN(Assumptions!E22,1*Assumptions!E21) -> 0.025 | F8: =MIN(Assumptions!E22,2*Assumptions!E21) -> 0.05 | G8: =MIN(Assumptions!E22,3*Assumptions!E21) -> 0.075 | H8: =MIN(Assumptions!E22,4*Assumptions!E21) -> 0.1 | I8: =MIN(Assumptions!E22,5*Assumptions!E21) -> 0.125 | J8: =MIN(Assumptions!E22,6*Assumptions!E21) -> 0.15 | K8: =MIN(Assumptions!E22,7*Assumptions!E21) -> 0.175 | L8: =MIN(Assumptions!E22,8*Assumptions!E21) -> 0.2 | M8: =MIN(Assumptions!E22,9*Assumptions!E21) -> 0.225 | N8: =MIN(Assumptions!E22,10*Assumptions!E21) -> 0.25 | O8: =MIN(Assumptions!E22,11*Assumptions!E21) -> 0.275 | P8: =MIN(Assumptions!E22,12*Assumptions!E21) -> 0.3 | Q8: =MIN(Assumptions!E22,13*Assumptions!E21) -> 0.325 | R8: =MIN(Assumptions!E22,14*Assumptions!E21) -> 0.35 | S8: =MIN(Assumptions!E22,15*Assumptions!E21) -> 0.375 | T8: =MIN(Assumptions!E22,16*Assumptions!E21) -> 0.4 | U8: =MIN(Assumptions!E22,17*Assumptions!E21) -> 0.425 | V8: =MIN(Assumptions!E22,18*Assumptions!E21) -> 0.45 | W8: =MIN(Assumptions!E22,19*Assumptions!E21) -> 0.475 | X8: =MIN(Assumptions!E22,20*Assumptions!E21) -> 0.5 | Y8: =MIN(Assumptions!E22,21*Assumptions!E21) -> 0.5 | Z8: =MIN(Assumptions!E22,22*Assumptions!E21) -> 0.5 | AA8: =MIN(Assumptions!E22,23*Assumptions!E21) -> 0.5 | AB8: =MIN(Assumptions!E22,24*Assumptions!E21) -> 0.5 | AC8: =MIN(Assumptions!E22,25*Assumptions!E21) -> 0.5 | AD8: =MIN(Assumptions!E22,26*Assumptions!E21) -> 0.5 | AE8: =MIN(Assumptions!E22,27*Assumptions!E21) -> 0.5 | AF8: =MIN(Assumptions!E22,28*Assumptions!E21) -> 0.5 | AG8: =MIN(Assumptions!E22,29*Assumptions!E21) -> 0.5 | AH8: =MIN(Assumptions!E22,30*Assumptions!E21) -> 0.5 | AI8: =MIN(Assumptions!E22,31*Assumptions!E21) -> 0.5 | AJ8: =MIN(Assumptions!E22,32*Assumptions!E21) -> 0.5 | AK8: =MIN(Assumptions!E22,33*Assumptions!E21) -> 0.5 | AL8: =M8 -> 0.225 | AM8: =Y8 -> 0.5 | AN8: =AK8 -> 0.5 | AO8: Ramps +1.5–2.5%pts/mo from M4; capped at adoption ceiling.
A9: Blended monthly churn (wearable-adjusted) | B9: =Assumptions!E18*(1-B8*Assumptions!E23) -> 0.07 | C9: =Assumptions!E18*(1-C8*Assumptions!E23) -> 0.07 | D9: =Assumptions!E18*(1-D8*Assumptions!E23) -> 0.07 | E9: =Assumptions!E18*(1-E8*Assumptions!E23) -> 0.0693 | F9: =Assumptions!E18*(1-F8*Assumptions!E23) -> 0.0686 | G9: =Assumptions!E18*(1-G8*Assumptions!E23) -> 0.0679 | H9: =Assumptions!E18*(1-H8*Assumptions!E23) -> 0.0672 | I9: =Assumptions!E18*(1-I8*Assumptions!E23) -> 0.0665 | J9: =Assumptions!E18*(1-J8*Assumptions!E23) -> 0.0658 | K9: =Assumptions!E18*(1-K8*Assumptions!E23) -> 0.0651 | L9: =Assumptions!E18*(1-L8*Assumptions!E23) -> 0.0644 | M9: =Assumptions!E18*(1-M8*Assumptions!E23) -> 0.0637 | N9: =Assumptions!E19*(1-N8*Assumptions!E23) -> 0.054 | O9: =Assumptions!E19*(1-O8*Assumptions!E23) -> 0.0534 | P9: =Assumptions!E19*(1-P8*Assumptions!E23) -> 0.0528 | Q9: =Assumptions!E19*(1-Q8*Assumptions!E23) -> 0.0522 | R9: =Assumptions!E19*(1-R8*Assumptions!E23) -> 0.0516 | S9: =Assumptions!E19*(1-S8*Assumptions!E23) -> 0.051 | T9: =Assumptions!E19*(1-T8*Assumptions!E23) -> 0.0504 | U9: =Assumptions!E19*(1-U8*Assumptions!E23) -> 0.0498 | V9: =Assumptions!E19*(1-V8*Assumptions!E23) -> 0.0492 | W9: =Assumptions!E19*(1-W8*Assumptions!E23) -> 0.0486 | X9: =Assumptions!E19*(1-X8*Assumptions!E23) -> 0.048 | Y9: =Assumptions!E19*(1-Y8*Assumptions!E23) -> 0.048 | Z9: =Assumptions!E20*(1-Z8*Assumptions!E23) -> 0.04 | AA9: =Assumptions!E20*(1-AA8*Assumptions!E23) -> 0.04 | AB9: =Assumptions!E20*(1-AB8*Assumptions!E23) -> 0.04 | AC9: =Assumptions!E20*(1-AC8*Assumptions!E23) -> 0.04 | AD9: =Assumptions!E20*(1-AD8*Assumptions!E23) -> 0.04 | AE9: =Assumptions!E20*(1-AE8*Assumptions!E23) -> 0.04 | AF9: =Assumptions!E20*(1-AF8*Assumptions!E23) -> 0.04 | AG9: =Assumptions!E20*(1-AG8*Assumptions!E23) -> 0.04 | AH9: =Assumptions!E20*(1-AH8*Assumptions!E23) -> 0.04 | AI9: =Assumptions!E20*(1-AI8*Assumptions!E23) -> 0.04 | AJ9: =Assumptions!E20*(1-AJ8*Assumptions!E23) -> 0.04 | AK9: =Assumptions!E20*(1-AK8*Assumptions!E23) -> 0.04 | AL9: =AVERAGE(B9:M9) -> 0.067375 | AM9: =AVERAGE(N9:Y9) -> 0.05075 | AN9: =AVERAGE(Z9:AK9) -> 0.04 | AO9: base × (1 − wearable% × reduction_factor).
A10: Premium upgrades from basic (M13+) | B10: =0 -> 0 | C10: =0 -> 0 | D10: =0 -> 0 | E10: =0 -> 0 | F10: =0 -> 0 | G10: =0 -> 0 | H10: =0 -> 0 | I10: =0 -> 0 | ... L10: =0 -> 0 | M10: =L11*Assumptions!E26 -> 133.12741 | N10: =M11*Assumptions!E26 -> 146.23552 | O10: =N11*Assumptions!E26 -> 170.23327 | P10: =O11*Assumptions!E26 -> 194.13777 | Q10: =P11*Assumptions!E26 -> 218.27624 | R10: =Q11*Assumptions!E26 -> 243.01214 | S10: =R11*Assumptions!E26 -> 268.75527 | T10: =S11*Assumptions!E26 -> 295.97356 | U10: =T11*Assumptions!E26 -> 325.20711 | V10: =U11*Assumptions!E26 -> 357.08482 | W10: =V11*Assumptions!E26 -> 392.34418 | X10: =W11*Assumptions!E26 -> 431.855 | Y10: =X11*Assumptions!E26 -> 476.64768 | Z10: =Y11*Assumptions!E26 -> 527.66119 | AA10: =Z11*Assumptions!E26 -> 604.46203 | AB10: =AA11*Assumptions!E26 -> 690.0604 | AC10: =AB11*Assumptions!E26 -> 786.57677 | AD10: =AC11*Assumptions!E26 -> 896.53581 | AE10: =AD11*Assumptions!E26 -> 1022.9484 | AF10: =AE11*Assumptions!E26 -> 1169.4099 | AG10: =AF11*Assumptions!E26 -> 1340.2178 | AH10: =AG11*Assumptions!E26 -> 1540.5136 | AI10: =AH11*Assumptions!E26 -> 1776.4517 | AJ10: =AI11*Assumptions!E26 -> 2055.4037 | AK10: =AJ11*Assumptions!E26 -> 2386.2019 | AL10: =SUM(B10:M10) -> 133.12741 | AM10: =SUM(N10:Y10) -> 3519.7626 | AN10: =SUM(Z10:AK10) -> 14796.443 | AO10: 0.75–1.5%/mo of basic base (corrected from 4–8%/mo compounding).
A11: B2C basic subscribers (EoM) | B11: =B6+B7 -> 54.6 | C11: =B11*(1-C9)-C10+C6+C7 -> 116.298 | D11: =C11*(1-D9)-D10+D6+D7 -> 186.78114 | E11: =D11*(1-E9)-E10+E6+E7 -> 1434.8527 | F11: =E11*(1-F9)-F10+F6+F7 -> 2616.307 | G11: =F11*(1-G9)-G10+G6+G7 -> 3741.1887 | H11: =G11*(1-H9)-H10+H6+H7 -> 4819.4822 | I11: =H11*(1-I9)-I10+I6+I7 -> 5861.295 | J11: =I11*(1-J9)-J10+J6+J7 -> 6877.0584 | ... AK11: =AJ11*(1-AK9)-AK10+AK6+AK7 -> 185295.49 | AL11: =M11 -> 9749.0349 | AM11: =Y11 -> 35177.413 | AN11: =AK11 -> 185295.49 | AO11: Prior × (1-churn) - upgrades + new converts.
A12: B2C premium subscribers (EoM — upgrade from basic, not added on top) | B12: =0 -> 0 | C12: =0 -> 0 | D12: =0 -> 0 | E12: =0 -> 0 | F12: =0 -> 0 | G12: =0 -> 0 | H12: =0 -> 0 | I12: =0 -> 0 | ... L12: =0 -> 0 | M12: =M10 -> 133.12741 | N12: =M12*(1-Assumptions!E27)+N10 -> 275.36911 | O12: =N12*(1-Assumptions!E27)+O10 -> 437.34131 | P12: =O12*(1-Assumptions!E27)+P10 -> 618.35885 | Q12: =P12*(1-Assumptions!E27)+Q10 -> 818.08432 | R12: =Q12*(1-Assumptions!E27)+R10 -> 1036.5539 | S12: =R12*(1-Assumptions!E27)+S10 -> 1274.2126 | T12: =S12*(1-Assumptions!E27)+T10 -> 1531.9598 | U12: =T12*(1-Assumptions!E27)+U10 -> 1811.2081 | V12: =U12*(1-Assumptions!E27)+V10 -> 2113.9567 | W12: =V12*(1-Assumptions!E27)+W10 -> 2442.8821 | X12: =W12*(1-Assumptions!E27)+X10 -> 2801.4507 | Y12: =X12*(1-Assumptions!E27)+Y10 -> 3194.0548 | Z12: =Y12*(1-Assumptions!E27)+Z10 -> 3625.8944 | AA12: =Z12*(1-Assumptions!E27)+AA10 -> 4121.5796 | AB12: =AA12*(1-Assumptions!E27)+AB10 -> 4687.9926 | AC12: =AB12*(1-Assumptions!E27)+AC10 -> 5333.9296 | AD12: =AC12*(1-Assumptions!E27)+AD10 -> 6070.4475 | AE12: =AD12*(1-Assumptions!E27)+AE10 -> 6911.2825 | AF12: =AE12*(1-Assumptions!E27)+AF10 -> 7873.3539 | AG12: =AF12*(1-Assumptions!E27)+AG10 -> 8977.3711 | AH12: =AG12*(1-Assumptions!E27)+AH10 -> 10248.564 | AI12: =AH12*(1-Assumptions!E27)+AI10 -> 11717.558 | AJ12: =AI12*(1-Assumptions!E27)+AJ10 -> 13421.435 | AK12: =AJ12*(1-Assumptions!E27)+AK10 -> 15404.994 | AL12: =M12 -> 133.12741 | AM12: =Y12 -> 3194.0548 | AN12: =AK12 -> 15404.994 | AO12: Premium users MOVE from basic — no double-counting.
A13: B2B contracts signed (cumulative) | B13: =0 -> 0 | C13: =0 -> 0 | D13: =0 -> 0 | E13: =0 -> 0 | F13: =0 -> 0 | G13: =Assumptions!E29 -> 2 | H13: =G13+Assumptions!E29 -> 4 | I13: =H13+Assumptions!E29 -> 6 | J13: =I13+Assumptions!E29 -> 8 | K13: =J13+Assumptions!E29 -> 10 | L13: =K13+Assumptions!E29 -> 12 | M13: =L13+Assumptions!E29 -> 14 | N13: =M13+Assumptions!E30 -> 19.3 | O13: =N13+Assumptions!E30 -> 24.6 | P13: =O13+Assumptions!E30 -> 29.9 | Q13: =P13+Assumptions!E30 -> 35.2 | R13: =Q13+Assumptions!E30 -> 40.5 | S13: =R13+Assumptions!E30 -> 45.8 | T13: =S13+Assumptions!E30 -> 51.1 | U13: =T13+Assumptions!E30 -> 56.4 | V13: =U13+Assumptions!E30 -> 61.7 | W13: =V13+Assumptions!E30 -> 67 | X13: =W13+Assumptions!E30 -> 72.3 | Y13: =X13+Assumptions!E30 -> 77.6 | Z13: =Y13+Assumptions!E31 -> 81.2 | AA13: =Z13+Assumptions!E31 -> 84.8 | AB13: =AA13+Assumptions!E31 -> 88.4 | AC13: =AB13+Assumptions!E31 -> 92 | AD13: =AC13+Assumptions!E31 -> 95.6 | AE13: =AD13+Assumptions!E31 -> 99.2 | AF13: =AE13+Assumptions!E31 -> 102.8 | AG13: =AF13+Assumptions!E31 -> 106.4 | AH13: =AG13+Assumptions!E31 -> 110 | AI13: =AH13+Assumptions!E31 -> 113.6 | AJ13: =AI13+Assumptions!E31 -> 117.2 | AK13: =AJ13+Assumptions!E31 -> 120.8 | AL13: =M13 -> 14 | AM13: =Y13 -> 77.6 | AN13: =AK13 -> 120.8
A14: B2B employees active (EoM) | B14: =0 -> 0 | C14: =0 -> 0 | D14: =0 -> 0 | E14: =0 -> 0 | F14: =0 -> 0 | G14: =Assumptions!E29*Assumptions!E32 -> 350 | H14: =G14*(1-(1-(1-Assumptions!E33)^(1/12)))+Assumptions!E29*Assumptions!E32 -> 695.29182 | I14: =H14*(1-(1-(1-Assumptions!E33)^(1/12)))+Assumptions!E29*Assumptions!E32 -> 1035.9388 | J14: =I14*(1-(1-(1-Assumptions!E33)^(1/12)))+Assumptions!E29*Assumptions!E32 -> 1372.0034 | K14: =J14*(1-(1-(1-Assumptions!E33)^(1/12)))+Assumptions!E29*Assumptions!E32 -> 1703.5473 | L14: =K14*(1-(1-(1-Assumptions!E33)^(1/12)))+Assumptions!E29*Assumptions!E32 -> 2030.6313 | M14: =L14*(1-(1-(1-Assumptions!E33)^(1/12)))+Assumptions!E29*Assumptions!E32 -> 2353.3153 | N14: =M14*(1-(1-(1-Assumptions!E33)^(1/12)))+Assumptions!E30*Assumptions!E32 -> 3249.1586 | O14: =N14*(1-(1-(1-Assumptions!E33)^(1/12)))+Assumptions!E30*Assumptions!E32 -> 4132.9511 | P14: =O14*(1-(1-(1-Assumptions!E33)^(1/12)))+Assumptions!E30*Assumptions!E32 -> 5004.8549 | Q14: =P14*(1-(1-(1-Assumptions!E33)^(1/12)))+Assumptions!E30*Assumptions!E32 -> 5865.0298 | R14: =Q14*(1-(1-(1-Assumptions!E33)^(1/12)))+Assumptions!E30*Assumptions!E32 -> 6713.6338 | S14: =R14*(1-(1-(1-Assumptions!E33)^(1/12)))+Assumptions!E30*Assumptions!E32 -> 7550.8223 | T14: =S14*(1-(1-(1-Assumptions!E33)^(1/12)))+Assumptions!E30*Assumptions!E32 -> 8376.7491 | U14: =T14*(1-(1-(1-Assumptions!E33)^(1/12)))+Assumptions!E30*Assumptions!E32 -> 9191.5655 | V14: =U14*(1-(1-(1-Assumptions!E33)^(1/12)))+Assumptions!E30*Assumptions!E32 -> 9995.421 | W14: =V14*(1-(1-(1-Assumptions!E33)^(1/12)))+Assumptions!E30*Assumptions!E32 -> 10788.463 | X14: =W14*(1-(1-(1-Assumptions!E33)^(1/12)))+Assumptions!E30*Assumptions!E32 -> 11570.837 | Y14: =X14*(1-(1-(1-Assumptions!E33)^(1/12)))+Assumptions!E30*Assumptions!E32 -> 12342.687 | Z14: =Y14*(1-(1-(1-Assumptions!E33)^(1/12)))+Assumptions!E31*Assumptions!E32 -> 12806.654 | AA14: =Z14*(1-(1-(1-Assumptions!E33)^(1/12)))+Assumptions!E31*Assumptions!E32 -> 13264.379 | AB14: =AA14*(1-(1-(1-Assumptions!E33)^(1/12)))+Assumptions!E31*Assumptions!E32 -> 13715.948 | AC14: =AB14*(1-(1-(1-Assumptions!E33)^(1/12)))+Assumptions!E31*Assumptions!E32 -> 14161.441 | AD14: =AC14*(1-(1-(1-Assumptions!E33)^(1/12)))+Assumptions!E31*Assumptions!E32 -> 14600.943 | AE14: =AD14*(1-(1-(1-Assumptions!E33)^(1/12)))+Assumptions!E31*Assumptions!E32 -> 15034.531 | AF14: =AE14*(1-(1-(1-Assumptions!E33)^(1/12)))+Assumptions!E31*Assumptions!E32 -> 15462.288 | AG14: =AF14*(1-(1-(1-Assumptions!E33)^(1/12)))+Assumptions!E31*Assumptions!E32 -> 15884.29 | AH14: =AG14*(1-(1-(1-Assumptions!E33)^(1/12)))+Assumptions!E31*Assumptions!E32 -> 16300.615 | AI14: =AH14*(1-(1-(1-Assumptions!E33)^(1/12)))+Assumptions!E31*Assumptions!E32 -> 16711.34 | AJ14: =AI14*(1-(1-(1-Assumptions!E33)^(1/12)))+Assumptions!E31*Assumptions!E32 -> 17116.54 | AK14: =AJ14*(1-(1-(1-Assumptions!E33)^(1/12)))+Assumptions!E31*Assumptions!E32 -> 17516.289 | AL14: =M14 -> 2353.3153 | AM14: =Y14 -> 12342.687 | AN14: =AK14 -> 17516.289 | AO14: Prior × (1-monthly logo churn) + new seats.
A15: TOTAL PAYING USERS (EoM) | B15: =B11+B12+B14 -> 54.6 | C15: =C11+C12+C14 -> 116.298 | D15: =D11+D12+D14 -> 186.78114 | E15: =E11+E12+E14 -> 1434.8527 | F15: =F11+F12+F14 -> 2616.307 | G15: =G11+G12+G14 -> 4091.1887 | H15: =H11+H12+H14 -> 5514.774 | I15: =I11+I12+I14 -> 6897.2338 | ... AK15: =AK11+AK12+AK14 -> 218216.77 | AL15: =M15 -> 12235.478 | AM15: =Y15 -> 50714.154 | AN15: =AK15 -> 218216.77 | AO15: Basic + premium + B2B. Premium NOT double-counted.
A17: SECTION 2 — REVENUE
A18: B2C basic subscriptions | B18: =B11*Assumptions!E4 -> 272.454 | C18: =(B11+C11)/2*Assumptions!E4 -> 426.39051 | D18: =(C11+D11)/2*Assumptions!E4 -> 756.18245 | E18: =(D11+E11)/2*Assumptions!E4 -> 4045.9764 | F18: =(E11+F11)/2*Assumptions!E4 -> 10107.643 | G18: =(F11+G11)/2*Assumptions!E4 -> 15861.952 | H18: =(G11+H11)/2*Assumptions!E4 -> 21358.874 | I18: =(H11+I11)/2*Assumptions!E4 -> 26648.539 | J18: =(I11+J11)/2*Assumptions!E4 -> 31782.192 | K18: =(J11+K11)/2*Assumptions!E4 -> 36813.254 | L18: =(K11+L11)/2*Assumptions!E4 -> 41798.519 | M18: =(L11+M11)/2*Assumptions!E4 -> 46467.368 | N18: =(M11+N11)/2*Assumptions!E4 -> 52639.31 | O18: =(N11+O11)/2*Assumptions!E4 -> 60607.051 | P18: =(O11+P11)/2*Assumptions!E4 -> 68598.198 | Q18: =(P11+Q11)/2*Assumptions!E4 -> 76727.634 | R18: =(Q11+R11)/2*Assumptions!E4 -> 85123.979 | S18: =(R11+S11)/2*Assumptions!E4 -> 93933.228 | T18: =(S11+T11)/2*Assumptions!E4 -> 103323.05 | U18: =(T11+U11)/2*Assumptions!E4 -> 113487.89 | V18: =(U11+V11)/2*Assumptions!E4 -> 124655.02 | W18: =(V11+W11)/2*Assumptions!E4 -> 137091.8 | X18: =(W11+X11)/2*Assumptions!E4 -> 151114.28 | Y18: =(X11+Y11)/2*Assumptions!E4 -> 167050.04 | Z18: =(Y11+Z11)/2*Assumptions!E4 -> 188309.83 | AA18: =(Z11+AA11)/2*Assumptions!E4 -> 215322.23 | AB18: =(AA11+AB11)/2*Assumptions!E4 -> 245613.98 | AC18: =(AB11+AC11)/2*Assumptions!E4 -> 279957.73 | AD18: =(AC11+AD11)/2*Assumptions!E4 -> 319274.21 | AE18: =(AD11+AE11)/2*Assumptions!E4 -> 364662.26 | AF18: =(AE11+AF11)/2*Assumptions!E4 -> 417434.74 | AG18: =(AF11+AG11)/2*Assumptions!E4 -> 479161.65 | AH18: =(AG11+AH11)/2*Assumptions!E4 -> 551721.89 | AI18: =(AH11+AI11)/2*Assumptions!E4 -> 637365.29 | AJ18: =(AI11+AJ11)/2*Assumptions!E4 -> 738787.06 | AK18: =(AJ11+AK11)/2*Assumptions!E4 -> 859217.16 | AL18: =SUM(B18:M18) -> 236339.34 | AM18: =SUM(N18:Y18) -> 1234351.5 | AN18: =SUM(Z18:AK18) -> 5296828
A19: B2C premium subscriptions (from M13) | B19: =0 -> 0 | C19: =0 -> 0 | D19: =0 -> 0 | E19: =0 -> 0 | F19: =0 -> 0 | G19: =0 -> 0 | H19: =0 -> 0 | I19: =0 -> 0 | ... L19: =0 -> 0 | M19: =M12*Assumptions!E5 -> 1729.3251 | N19: =(M12+N12)/2*Assumptions!E5 -> 2653.1849 | O19: =(N12+O12)/2*Assumptions!E5 -> 4629.0542 | P19: =(O12+P12)/2*Assumptions!E5 -> 6856.7725 | Q19: =(P12+Q12)/2*Assumptions!E5 -> 9329.6984 | R19: =(Q12+R12)/2*Assumptions!E5 -> 12045.875 | S19: =(R12+S12)/2*Assumptions!E5 -> 15008.429 | T19: =(S12+T12)/2*Assumptions!E5 -> 18226.089 | U19: =(T12+U12)/2*Assumptions!E5 -> 21713.875 | V19: =(U12+V12)/2*Assumptions!E5 -> 25493.945 | W19: =(V12+W12)/2*Assumptions!E5 -> 29596.668 | X19: =(W12+X12)/2*Assumptions!E5 -> 34061.942 | Y19: =(X12+Y12)/2*Assumptions!E5 -> 38940.808 | Z19: =(Y12+Z12)/2*Assumptions!E5 -> 44295.57 | AA19: =(Z12+AA12)/2*Assumptions!E5 -> 50319.843 | AB19: =(AA12+AB12)/2*Assumptions!E5 -> 57218.171 | AC19: =(AB12+AC12)/2*Assumptions!E5 -> 65092.385 | AD19: =(AC12+AD12)/2*Assumptions!E5 -> 74071.429 | AE19: =(AD12+AE12)/2*Assumptions!E5 -> 84316.336 | AF19: =(AE12+AF12)/2*Assumptions!E5 -> 96026.213 | AG19: =(AF12+AG12)/2*Assumptions!E5 -> 109445.46 | AH19: =(AG12+AH12)/2*Assumptions!E5 -> 124872.45 | AI19: =(AH12+AI12)/2*Assumptions!E5 -> 142669.96 | AJ19: =(AI12+AJ12)/2*Assumptions!E5 -> 163277.76 | AK19: =(AJ12+AK12)/2*Assumptions!E5 -> 187227.66 | AL19: =SUM(B19:M19) -> 1729.3251 | AM19: =SUM(N19:Y19) -> 218556.34 | AN19: =SUM(Z19:AK19) -> 1198833.2
A20: B2B corporate wellbeing | B20: =0 -> 0 | C20: =0 -> 0 | D20: =0 -> 0 | E20: =0 -> 0 | F20: =0 -> 0 | G20: =G14*Assumptions!E6 -> 1396.5 | H20: =H14*Assumptions!E6 -> 2774.2144 | I20: =I14*Assumptions!E6 -> 4133.3958 | J20: =J14*Assumptions!E6 -> 5474.2936 | K20: =K14*Assumptions!E6 -> 6797.1536 | L20: =L14*Assumptions!E6 -> 8102.2187 | M20: =M14*Assumptions!E6 -> 9389.7281 | N20: =N14*Assumptions!E7 -> 19462.46 | O20: =O14*Assumptions!E7 -> 24756.377 | P20: =P14*Assumptions!E7 -> 29979.081 | Q20: =Q14*Assumptions!E7 -> 35131.529 | R20: =R14*Assumptions!E7 -> 40214.666 | S20: =S14*Assumptions!E7 -> 45229.426 | T20: =T14*Assumptions!E7 -> 50176.727 | U20: =U14*Assumptions!E7 -> 55057.477 | V20: =V14*Assumptions!E7 -> 59872.572 | W20: =W14*Assumptions!E7 -> 64622.894 | X20: =X14*Assumptions!E7 -> 69309.316 | Y20: =Y14*Assumptions!E7 -> 73932.695 | Z20: =Z14*Assumptions!E7 -> 76711.857 | AA20: =AA14*Assumptions!E7 -> 79453.633 | AB20: =AB14*Assumptions!E7 -> 82158.527 | AC20: =AC14*Assumptions!E7 -> 84827.035 | AD20: =AD14*Assumptions!E7 -> 87459.646 | AE20: =AE14*Assumptions!E7 -> 90056.843 | AF20: =AF14*Assumptions!E7 -> 92619.103 | AG20: =AG14*Assumptions!E7 -> 95146.896 | AH20: =AH14*Assumptions!E7 -> 97640.685 | AI20: =AI14*Assumptions!E7 -> 100100.93 | AJ20: =AJ14*Assumptions!E7 -> 102528.08 | AK20: =AK14*Assumptions!E7 -> 104922.57 | AL20: =SUM(B20:M20) -> 38067.504 | AM20: =SUM(N20:Y20) -> 567745.22 | AN20: =SUM(Z20:AK20) -> 1093625.8
A21: Events & workshops (net) | B21: =0 -> 0 | C21: =0 -> 0 | D21: =Assumptions!E35 -> 1000 | E21: =Assumptions!E35 -> 1000 | F21: =Assumptions!E35 -> 1000 | G21: =Assumptions!E35 -> 1000 | H21: =Assumptions!E35 -> 1000 | I21: =Assumptions!E35 -> 1000 | J21: =Assumptions!E35 -> 1000 | K21: =Assumptions!E35 -> 1000 | L21: =Assumptions!E35 -> 1000 | M21: =Assumptions!E35 -> 1000 | N21: =Assumptions!E36 -> 2000 | O21: =Assumptions!E36 -> 2000 | P21: =Assumptions!E36 -> 2000 | Q21: =Assumptions!E36 -> 2000 | R21: =Assumptions!E36 -> 2000 | S21: =Assumptions!E36 -> 2000 | T21: =Assumptions!E36 -> 2000 | U21: =Assumptions!E36 -> 2000 | V21: =Assumptions!E36 -> 2000 | W21: =Assumptions!E36 -> 2000 | X21: =Assumptions!E36 -> 2000 | Y21: =Assumptions!E36 -> 2000 | Z21: =Assumptions!E37 -> 3000 | AA21: =Assumptions!E37 -> 3000 | AB21: =Assumptions!E37 -> 3000 | AC21: =Assumptions!E37 -> 3000 | AD21: =Assumptions!E37 -> 3000 | AE21: =Assumptions!E37 -> 3000 | AF21: =Assumptions!E37 -> 3000 | AG21: =Assumptions!E37 -> 3000 | AH21: =Assumptions!E37 -> 3000 | AI21: =Assumptions!E37 -> 3000 | AJ21: =Assumptions!E37 -> 3000 | AK21: =Assumptions!E37 -> 3000 | AL21: =SUM(B21:M21) -> 10000 | AM21: =SUM(N21:Y21) -> 24000 | AN21: =SUM(Z21:AK21) -> 36000 | AO21: €420 earned to date → €500 conservative. NOT in MRR.
A22: Clinical B2B referral fees (€/contract/mo, from M6) | B22: =0 -> 0 | C22: =0 -> 0 | D22: =0 -> 0 | E22: =0 -> 0 | F22: =0 -> 0 | G22: =G13*Assumptions!E39 -> 1000 | H22: =H13*Assumptions!E39 -> 2000 | I22: =I13*Assumptions!E39 -> 3000 | J22: =J13*Assumptions!E39 -> 4000 | K22: =K13*Assumptions!E39 -> 5000 | L22: =L13*Assumptions!E39 -> 6000 | M22: =M13*Assumptions!E39 -> 7000 | N22: =N13*Assumptions!E39 -> 9650 | O22: =O13*Assumptions!E39 -> 12300 | P22: =P13*Assumptions!E39 -> 14950 | Q22: =Q13*Assumptions!E39 -> 17600 | R22: =R13*Assumptions!E39 -> 20250 | S22: =S13*Assumptions!E39 -> 22900 | T22: =T13*Assumptions!E39 -> 25550 | U22: =U13*Assumptions!E39 -> 28200 | V22: =V13*Assumptions!E39 -> 30850 | W22: =W13*Assumptions!E39 -> 33500 | X22: =X13*Assumptions!E39 -> 36150 | Y22: =Y13*Assumptions!E39 -> 38800 | Z22: =Z13*Assumptions!E39 -> 40600 | AA22: =AA13*Assumptions!E39 -> 42400 | AB22: =AB13*Assumptions!E39 -> 44200 | AC22: =AC13*Assumptions!E39 -> 46000 | AD22: =AD13*Assumptions!E39 -> 47800 | AE22: =AE13*Assumptions!E39 -> 49600 | AF22: =AF13*Assumptions!E39 -> 51400 | AG22: =AG13*Assumptions!E39 -> 53200 | AH22: =AH13*Assumptions!E39 -> 55000 | AI22: =AI13*Assumptions!E39 -> 56800 | AJ22: =AJ13*Assumptions!E39 -> 58600 | AK22: =AK13*Assumptions!E39 -> 60400 | AL22: =SUM(B22:M22) -> 28000 | AM22: =SUM(N22:Y22) -> 290700 | AN22: =SUM(Z22:AK22) -> 606000
A23: Brand partnerships (0 in conservative; upside only) | B23: =0 -> 0 | C23: =0 -> 0 | D23: =0 -> 0 | E23: =0 -> 0 | F23: =0 -> 0 | G23: =0 -> 0 | H23: =0 -> 0 | I23: =0 -> 0 | ... Y23: =0 -> 0 | Z23: =Assumptions!E38 -> 3500 | AA23: =Assumptions!E38 -> 3500 | AB23: =Assumptions!E38 -> 3500 | AC23: =Assumptions!E38 -> 3500 | AD23: =Assumptions!E38 -> 3500 | AE23: =Assumptions!E38 -> 3500 | AF23: =Assumptions!E38 -> 3500 | AG23: =Assumptions!E38 -> 3500 | AH23: =Assumptions!E38 -> 3500 | AI23: =Assumptions!E38 -> 3500 | AJ23: =Assumptions!E38 -> 3500 | AK23: =Assumptions!E38 -> 3500 | AL23: =SUM(B23:M23) -> 0 | AM23: =SUM(N23:Y23) -> 0 | AN23: =SUM(Z23:AK23) -> 42000
A24: TOTAL REVENUE | B24: =B18+B19+B20+B21+B22+B23 -> 272.454 | C24: =C18+C19+C20+C21+C22+C23 -> 426.39051 | D24: =D18+D19+D20+D21+D22+D23 -> 1756.1825 | E24: =E18+E19+E20+E21+E22+E23 -> 5045.9764 | F24: =F18+F19+F20+F21+F22+F23 -> 11107.643 | G24: =G18+G19+G20+G21+G22+G23 -> 19258.452 | H24: =H18+H19+H20+H21+H22+H23 -> 27133.088 | I24: =I18+I19+I20+I21+I22+I23 -> 34781.935 | ... AK24: =AK18+AK19+AK20+AK21+AK22+AK23 -> 1218267.4 | AL24: =SUM(B24:M24) -> 314136.17 | AM24: =SUM(N24:Y24) -> 2335353 | AN24: =SUM(Z24:AK24) -> 8273287.1
A25: MRR — recurring only (basic + premium + B2B) | B25: =B18+B19+B20 -> 272.454 | C25: =C18+C19+C20 -> 426.39051 | D25: =D18+D19+D20 -> 756.18245 | E25: =E18+E19+E20 -> 4045.9764 | F25: =F18+F19+F20 -> 10107.643 | G25: =G18+G19+G20 -> 17258.452 | H25: =H18+H19+H20 -> 24133.088 | I25: =I18+I19+I20 -> 30781.935 | ... AK25: =AK18+AK19+AK20 -> 1151367.4 | AL25: =M25 -> 57586.421 | AM25: =Y25 -> 279923.55 | AN25: =AK25 -> 1151367.4 | AO25: Events and clinical fees excluded — VCs strip them.
A26: ARR (MRR × 12) | B26: =B25*12 -> 3269.448 | C26: =C25*12 -> 5116.6861 | D26: =D25*12 -> 9074.1895 | E26: =E25*12 -> 48551.716 | F26: =F25*12 -> 121291.72 | G26: =G25*12 -> 207101.42 | H26: =H25*12 -> 289597.06 | I26: =I25*12 -> 369383.22 | ... AK26: =AK25*12 -> 13816409 | AL26: =M26 -> 691037.06 | AM26: =Y26 -> 3359082.5 | AN26: =AK26 -> 13816409
A28: SECTION 3 — COSTS
A29: [helper] Trailing-12-month B2C gross revenue (fee-tier test) | B29: =SUM(B18:B18)+SUM(B19:B19) -> 272.454 | C29: =SUM(B18:C18)+SUM(B19:C19) -> 698.84451 | D29: =SUM(B18:D18)+SUM(B19:D19) -> 1455.027 | E29: =SUM(B18:E18)+SUM(B19:E19) -> 5501.0033 | F29: =SUM(B18:F18)+SUM(B19:F19) -> 15608.647 | G29: =SUM(B18:G18)+SUM(B19:G19) -> 31470.599 | H29: =SUM(B18:H18)+SUM(B19:H19) -> 52829.472 | I29: =SUM(B18:I18)+SUM(B19:I19) -> 79478.012 | J29: =SUM(B18:J18)+SUM(B19:J19) -> 111260.2 | K29: =SUM(B18:K18)+SUM(B19:K19) -> 148073.46 | L29: =SUM(B18:L18)+SUM(B19:L19) -> 189871.98 | M29: =SUM(B18:M18)+SUM(B19:M19) -> 238068.67 | N29: =SUM(C18:N18)+SUM(C19:N19) -> 293088.71 | O29: =SUM(D18:O18)+SUM(D19:O19) -> 357898.42 | P29: =SUM(E18:P18)+SUM(E19:P19) -> 432597.21 | Q29: =SUM(F18:Q18)+SUM(F19:Q19) -> 514608.57 | R29: =SUM(G18:R18)+SUM(G19:R19) -> 601670.78 | S29: =SUM(H18:S18)+SUM(H19:S19) -> 694750.49 | T29: =SUM(I18:T18)+SUM(I19:T19) -> 794940.75 | ... AK29: =SUM(Z18:AK18)+SUM(Z19:AK19) -> 6495661.3
A30: App store fees — CORRECTED (15% under $1M; 30% above) | B30: =IF(B29<Assumptions!E43,(B18+B19)*Assumptions!E41,(B18+B19)*Assumptions!E42) -> 40.8681 | C30: =IF(C29<Assumptions!E43,(C18+C19)*Assumptions!E41,(C18+C19)*Assumptions!E42) -> 63.958576 | D30: =IF(D29<Assumptions!E43,(D18+D19)*Assumptions!E41,(D18+D19)*Assumptions!E42) -> 113.42737 | E30: =IF(E29<Assumptions!E43,(E18+E19)*Assumptions!E41,(E18+E19)*Assumptions!E42) -> 606.89645 | F30: =IF(F29<Assumptions!E43,(F18+F19)*Assumptions!E41,(F18+F19)*Assumptions!E42) -> 1516.1465 | G30: =IF(G29<Assumptions!E43,(G18+G19)*Assumptions!E41,(G18+G19)*Assumptions!E42) -> 2379.2928 | H30: =IF(H29<Assumptions!E43,(H18+H19)*Assumptions!E41,(H18+H19)*Assumptions!E42) -> 3203.8311 | I30: =IF(I29<Assumptions!E43,(I18+I19)*Assumptions!E41,(I18+I19)*Assumptions!E42) -> 3997.2809 | J30: =IF(J29<Assumptions!E43,(J18+J19)*Assumptions!E41,(J18+J19)*Assumptions!E42) -> 4767.3288 | K30: =IF(K29<Assumptions!E43,(K18+K19)*Assumptions!E41,(K18+K19)*Assumptions!E42) -> 5521.988 | L30: =IF(L29<Assumptions!E43,(L18+L19)*Assumptions!E41,(L18+L19)*Assumptions!E42) -> 6269.7779 | M30: =IF(M29<Assumptions!E43,(M18+M19)*Assumptions!E41,(M18+M19)*Assumptions!E42) -> 7229.504 | N30: =IF(N29<Assumptions!E43,(N18+N19)*Assumptions!E41,(N18+N19)*Assumptions!E42) -> 8293.8742 | O30: =IF(O29<Assumptions!E43,(O18+O19)*Assumptions!E41,(O18+O19)*Assumptions!E42) -> 9785.4158 | P30: =IF(P29<Assumptions!E43,(P18+P19)*Assumptions!E41,(P18+P19)*Assumptions!E42) -> 11318.246 | Q30: =IF(Q29<Assumptions!E43,(Q18+Q19)*Assumptions!E41,(Q18+Q19)*Assumptions!E42) -> 12908.6 | R30: =IF(R29<Assumptions!E43,(R18+R19)*Assumptions!E41,(R18+R19)*Assumptions!E42) -> 14575.478 | S30: =IF(S29<Assumptions!E43,(S18+S19)*Assumptions!E41,(S18+S19)*Assumptions!E42) -> 16341.249 | T30: =IF(T29<Assumptions!E43,(T18+T19)*Assumptions!E41,(T18+T19)*Assumptions!E42) -> 18232.371 | U30: =IF(U29<Assumptions!E43,(U18+U19)*Assumptions!E41,(U18+U19)*Assumptions!E42) -> 40560.53 | V30: =IF(V29<Assumptions!E43,(V18+V19)*Assumptions!E41,(V18+V19)*Assumptions!E42) -> 45044.691 | W30: =IF(W29<Assumptions!E43,(W18+W19)*Assumptions!E41,(W18+W19)*Assumptions!E42) -> 50006.54 | X30: =IF(X29<Assumptions!E43,(X18+X19)*Assumptions!E41,(X18+X19)*Assumptions!E42) -> 55552.866 | Y30: =IF(Y29<Assumptions!E43,(Y18+Y19)*Assumptions!E41,(Y18+Y19)*Assumptions!E42) -> 61797.255 | Z30: =IF(Z29<Assumptions!E43,(Z18+Z19)*Assumptions!E41,(Z18+Z19)*Assumptions!E42) -> 69781.62 | AA30: =IF(AA29<Assumptions!E43,(AA18+AA19)*Assumptions!E41,(AA18+AA19)*Assumptions!E42) -> 79692.622 | AB30: =IF(AB29<Assumptions!E43,(AB18+AB19)*Assumptions!E41,(AB18+AB19)*Assumptions!E42) -> 90849.646 | AC30: =IF(AC29<Assumptions!E43,(AC18+AC19)*Assumptions!E41,(AC18+AC19)*Assumptions!E42) -> 103515.03 | AD30: =IF(AD29<Assumptions!E43,(AD18+AD19)*Assumptions!E41,(AD18+AD19)*Assumptions!E42) -> 118003.69 | AE30: =IF(AE29<Assumptions!E43,(AE18+AE19)*Assumptions!E41,(AE18+AE19)*Assumptions!E42) -> 134693.58 | AF30: =IF(AF29<Assumptions!E43,(AF18+AF19)*Assumptions!E41,(AF18+AF19)*Assumptions!E42) -> 154038.28 | AG30: =IF(AG29<Assumptions!E43,(AG18+AG19)*Assumptions!E41,(AG18+AG19)*Assumptions!E42) -> 176582.13 | AH30: =IF(AH29<Assumptions!E43,(AH18+AH19)*Assumptions!E41,(AH18+AH19)*Assumptions!E42) -> 202978.3 | AI30: =IF(AI29<Assumptions!E43,(AI18+AI19)*Assumptions!E41,(AI18+AI19)*Assumptions!E42) -> 234010.58 | AJ30: =IF(AJ29<Assumptions!E43,(AJ18+AJ19)*Assumptions!E41,(AJ18+AJ19)*Assumptions!E42) -> 270619.45 | AK30: =IF(AK29<Assumptions!E43,(AK18+AK19)*Assumptions!E41,(AK18+AK19)*Assumptions!E42) -> 313933.44 | AL30: =SUM(B30:M30) -> 35710.3 | AM30: =SUM(N30:Y30) -> 344417.11 | AN30: =SUM(Z30:AK30) -> 1948698.4 | AO30: CORRECTED: 15% until trailing-12mo B2C > ~$1M; 30% after. Original was backwards.
A31: Payment processing (Stripe 1.4% on B2B) | B31: =B20*Assumptions!E44 -> 0 | C31: =C20*Assumptions!E44 -> 0 | D31: =D20*Assumptions!E44 -> 0 | E31: =E20*Assumptions!E44 -> 0 | F31: =F20*Assumptions!E44 -> 0 | G31: =G20*Assumptions!E44 -> 19.551 | H31: =H20*Assumptions!E44 -> 38.839001 | I31: =I20*Assumptions!E44 -> 57.867541 | J31: =J20*Assumptions!E44 -> 76.64011 | K31: =K20*Assumptions!E44 -> 95.160151 | L31: =L20*Assumptions!E44 -> 113.43106 | M31: =M20*Assumptions!E44 -> 131.45619 | N31: =N20*Assumptions!E44 -> 272.47444 | O31: =O20*Assumptions!E44 -> 346.58928 | P31: =P20*Assumptions!E44 -> 419.70713 | Q31: =Q20*Assumptions!E44 -> 491.8414 | R31: =R20*Assumptions!E44 -> 563.00533 | S31: =S20*Assumptions!E44 -> 633.21196 | T31: =T20*Assumptions!E44 -> 702.47418 | U31: =U20*Assumptions!E44 -> 770.80468 | V31: =V20*Assumptions!E44 -> 838.21601 | W31: =W20*Assumptions!E44 -> 904.72052 | X31: =X20*Assumptions!E44 -> 970.33042 | Y31: =Y20*Assumptions!E44 -> 1035.0577 | Z31: =Z20*Assumptions!E44 -> 1073.966 | AA31: =AA20*Assumptions!E44 -> 1112.3509 | AB31: =AB20*Assumptions!E44 -> 1150.2194 | AC31: =AC20*Assumptions!E44 -> 1187.5785 | AD31: =AD20*Assumptions!E44 -> 1224.435 | AE31: =AE20*Assumptions!E44 -> 1260.7958 | AF31: =AF20*Assumptions!E44 -> 1296.6674 | AG31: =AG20*Assumptions!E44 -> 1332.0565 | AH31: =AH20*Assumptions!E44 -> 1366.9696 | AI31: =AI20*Assumptions!E44 -> 1401.413 | AJ31: =AJ20*Assumptions!E44 -> 1435.3931 | AK31: =AK20*Assumptions!E44 -> 1468.916 | AL31: =SUM(B31:M31) -> 532.94506 | AM31: =SUM(N31:Y31) -> 7948.4331 | AN31: =SUM(Z31:AK31) -> 15310.761
A32: AI API costs (from M6, scales with users, capped) | B32: =0 -> 0 | C32: =0 -> 0 | D32: =0 -> 0 | E32: =0 -> 0 | F32: =0 -> 0 | G32: =MIN(Assumptions!E48,Assumptions!E46+(G15/500)*Assumptions!E47) -> 809.11887 | H32: =MIN(Assumptions!E48,Assumptions!E46+(H15/500)*Assumptions!E47) -> 951.4774 | I32: =MIN(Assumptions!E48,Assumptions!E46+(I15/500)*Assumptions!E47) -> 1089.7234 | J32: =MIN(Assumptions!E48,Assumptions!E46+(J15/500)*Assumptions!E47) -> 1224.9062 | K32: =MIN(Assumptions!E48,Assumptions!E46+(K15/500)*Assumptions!E47) -> 1358.13 | L32: =MIN(Assumptions!E48,Assumptions!E46+(L15/500)*Assumptions!E47) -> 1490.5792 | M32: =MIN(Assumptions!E48,Assumptions!E46+(M15/500)*Assumptions!E47) -> 1623.5478 | N32: =MIN(Assumptions!E48,Assumptions!E46+(N15/500)*Assumptions!E47) -> 1887.3413 | O32: =MIN(Assumptions!E48,Assumptions!E46+(O15/500)*Assumptions!E47) -> 2151.2811 | P32: =MIN(Assumptions!E48,Assumptions!E46+(P15/500)*Assumptions!E47) -> 2417.4963 | Q32: =MIN(Assumptions!E48,Assumptions!E46+(Q15/500)*Assumptions!E47) -> 2688.3924 | R32: =MIN(Assumptions!E48,Assumptions!E46+(R15/500)*Assumptions!E47) -> 2966.7206 | S32: =MIN(Assumptions!E48,Assumptions!E46+(S15/500)*Assumptions!E47) -> 3255.6606 | T32: =MIN(Assumptions!E48,Assumptions!E46+(T15/500)*Assumptions!E47) -> 3500 | U32: =MIN(Assumptions!E48,Assumptions!E46+(U15/500)*Assumptions!E47) -> 3500 | V32: =MIN(Assumptions!E48,Assumptions!E46+(V15/500)*Assumptions!E47) -> 3500 | W32: =MIN(Assumptions!E48,Assumptions!E46+(W15/500)*Assumptions!E47) -> 3500 | X32: =MIN(Assumptions!E48,Assumptions!E46+(X15/500)*Assumptions!E47) -> 3500 | Y32: =MIN(Assumptions!E48,Assumptions!E46+(Y15/500)*Assumptions!E47) -> 3500 | Z32: =MIN(Assumptions!E48,Assumptions!E46+(Z15/500)*Assumptions!E47) -> 3500 | AA32: =MIN(Assumptions!E48,Assumptions!E46+(AA15/500)*Assumptions!E47) -> 3500 | AB32: =MIN(Assumptions!E48,Assumptions!E46+(AB15/500)*Assumptions!E47) -> 3500 | AC32: =MIN(Assumptions!E48,Assumptions!E46+(AC15/500)*Assumptions!E47) -> 3500 | AD32: =MIN(Assumptions!E48,Assumptions!E46+(AD15/500)*Assumptions!E47) -> 3500 | AE32: =MIN(Assumptions!E48,Assumptions!E46+(AE15/500)*Assumptions!E47) -> 3500 | AF32: =MIN(Assumptions!E48,Assumptions!E46+(AF15/500)*Assumptions!E47) -> 3500 | AG32: =MIN(Assumptions!E48,Assumptions!E46+(AG15/500)*Assumptions!E47) -> 3500 | AH32: =MIN(Assumptions!E48,Assumptions!E46+(AH15/500)*Assumptions!E47) -> 3500 | AI32: =MIN(Assumptions!E48,Assumptions!E46+(AI15/500)*Assumptions!E47) -> 3500 | AJ32: =MIN(Assumptions!E48,Assumptions!E46+(AJ15/500)*Assumptions!E47) -> 3500 | AK32: =MIN(Assumptions!E48,Assumptions!E46+(AK15/500)*Assumptions!E47) -> 3500 | AL32: =SUM(B32:M32) -> 8547.4828 | AM32: =SUM(N32:Y32) -> 36366.892 | AN32: =SUM(Z32:AK32) -> 42000
A33: Infrastructure & hosting (base + variable, capped) | B33: =80 -> 80 | C33: =80 -> 80 | D33: =MIN(Assumptions!E71,Assumptions!E69+(D15/400)*Assumptions!E70) -> 770.04293 | E33: =MIN(Assumptions!E71,Assumptions!E69+(E15/400)*Assumptions!E70) -> 1238.0698 | F33: =MIN(Assumptions!E71,Assumptions!E69+(F15/400)*Assumptions!E70) -> 1681.1151 | G33: =MIN(Assumptions!E71,Assumptions!E69+(G15/400)*Assumptions!E70) -> 2234.1958 | H33: =MIN(Assumptions!E71,Assumptions!E69+(H15/400)*Assumptions!E70) -> 2768.0403 | I33: =MIN(Assumptions!E71,Assumptions!E69+(I15/400)*Assumptions!E70) -> 3286.4627 | J33: =MIN(Assumptions!E71,Assumptions!E69+(J15/400)*Assumptions!E70) -> 3793.3982 | K33: =MIN(Assumptions!E71,Assumptions!E69+(K15/400)*Assumptions!E70) -> 4292.9875 | L33: =MIN(Assumptions!E71,Assumptions!E69+(L15/400)*Assumptions!E70) -> 4789.672 | M33: =MIN(Assumptions!E71,Assumptions!E69+(M15/400)*Assumptions!E70) -> 5288.3041 | N33: =MIN(Assumptions!E71,Assumptions!E69+(N15/400)*Assumptions!E70) -> 6277.5297 | O33: =MIN(Assumptions!E71,Assumptions!E69+(O15/400)*Assumptions!E70) -> 7267.304 | P33: =MIN(Assumptions!E71,Assumptions!E69+(P15/400)*Assumptions!E70) -> 8265.6112 | Q33: =MIN(Assumptions!E71,Assumptions!E69+(Q15/400)*Assumptions!E70) -> 9281.4714 | R33: =MIN(Assumptions!E71,Assumptions!E69+(R15/400)*Assumptions!E70) -> 10325.202 | S33: =MIN(Assumptions!E71,Assumptions!E69+(S15/400)*Assumptions!E70) -> 11408.727 | T33: =MIN(Assumptions!E71,Assumptions!E69+(T15/400)*Assumptions!E70) -> 12545.944 | U33: =MIN(Assumptions!E71,Assumptions!E69+(U15/400)*Assumptions!E70) -> 13753.161 | V33: =MIN(Assumptions!E71,Assumptions!E69+(V15/400)*Assumptions!E70) -> 15049.621 | W33: =MIN(Assumptions!E71,Assumptions!E69+(W15/400)*Assumptions!E70) -> 16458.129 | X33: =MIN(Assumptions!E71,Assumptions!E69+(X15/400)*Assumptions!E70) -> 18000 | Y33: =MIN(Assumptions!E71,Assumptions!E69+(Y15/400)*Assumptions!E70) -> 18000 | Z33: =MIN(Assumptions!E71,Assumptions!E69+(Z15/400)*Assumptions!E70) -> 18000 | AA33: =MIN(Assumptions!E71,Assumptions!E69+(AA15/400)*Assumptions!E70) -> 18000 | AB33: =MIN(Assumptions!E71,Assumptions!E69+(AB15/400)*Assumptions!E70) -> 18000 | AC33: =MIN(Assumptions!E71,Assumptions!E69+(AC15/400)*Assumptions!E70) -> 18000 | AD33: =MIN(Assumptions!E71,Assumptions!E69+(AD15/400)*Assumptions!E70) -> 18000 | AE33: =MIN(Assumptions!E71,Assumptions!E69+(AE15/400)*Assumptions!E70) -> 18000 | AF33: =MIN(Assumptions!E71,Assumptions!E69+(AF15/400)*Assumptions!E70) -> 18000 | AG33: =MIN(Assumptions!E71,Assumptions!E69+(AG15/400)*Assumptions!E70) -> 18000 | AH33: =MIN(Assumptions!E71,Assumptions!E69+(AH15/400)*Assumptions!E70) -> 18000 | AI33: =MIN(Assumptions!E71,Assumptions!E69+(AI15/400)*Assumptions!E70) -> 18000 | AJ33: =MIN(Assumptions!E71,Assumptions!E69+(AJ15/400)*Assumptions!E70) -> 18000 | AK33: =MIN(Assumptions!E71,Assumptions!E69+(AK15/400)*Assumptions!E70) -> 18000 | AL33: =SUM(B33:M33) -> 30302.288 | AM33: =SUM(N33:Y33) -> 146632.7 | AN33: =SUM(Z33:AK33) -> 216000
A34: Founder stipends ×3 | B34: =Assumptions!E54 -> 900 | C34: =Assumptions!E54 -> 900 | D34: =Assumptions!E54 -> 900 | E34: =Assumptions!E54 -> 900 | F34: =Assumptions!E54 -> 900 | G34: =Assumptions!E54 -> 900 | H34: =Assumptions!E54 -> 900 | I34: =Assumptions!E54 -> 900 | J34: =Assumptions!E54 -> 900 | K34: =Assumptions!E54 -> 900 | L34: =Assumptions!E54 -> 900 | M34: =Assumptions!E54 -> 900 | N34: =Assumptions!E55 -> 9000 | O34: =Assumptions!E55 -> 9000 | P34: =Assumptions!E55 -> 9000 | Q34: =Assumptions!E55 -> 9000 | R34: =Assumptions!E55 -> 9000 | S34: =Assumptions!E55 -> 9000 | T34: =Assumptions!E55 -> 9000 | U34: =Assumptions!E55 -> 9000 | V34: =Assumptions!E55 -> 9000 | W34: =Assumptions!E55 -> 9000 | X34: =Assumptions!E55 -> 9000 | Y34: =Assumptions!E55 -> 9000 | Z34: =Assumptions!E76 -> 12000 | AA34: =Assumptions!E76 -> 12000 | AB34: =Assumptions!E76 -> 12000 | AC34: =Assumptions!E76 -> 12000 | AD34: =Assumptions!E76 -> 12000 | AE34: =Assumptions!E76 -> 12000 | AF34: =Assumptions!E76 -> 12000 | AG34: =Assumptions!E76 -> 12000 | AH34: =Assumptions!E76 -> 12000 | AI34: =Assumptions!E76 -> 12000 | AJ34: =Assumptions!E76 -> 12000 | AK34: =Assumptions!E76 -> 12000 | AL34: =SUM(B34:M34) -> 10800 | AM34: =SUM(N34:Y34) -> 108000 | AN34: =SUM(Z34:AK34) -> 144000
A35: Team salaries & contractors | B35: =0 -> 0 | C35: =0 -> 0 | D35: =Assumptions!E56 -> 7000 | E35: =Assumptions!E56 -> 7000 | F35: =Assumptions!E56 -> 7000 | G35: =Assumptions!E56 -> 7000 | H35: =Assumptions!E57 -> 13000 | I35: =Assumptions!E57 -> 13000 | J35: =Assumptions!E57 -> 13000 | K35: =Assumptions!E57 -> 13000 | L35: =Assumptions!E57 -> 13000 | M35: =Assumptions!E57 -> 13000 | N35: =Assumptions!E58 -> 46000 | O35: =Assumptions!E58 -> 46000 | P35: =Assumptions!E58 -> 46000 | Q35: =Assumptions!E58 -> 46000 | R35: =Assumptions!E58 -> 46000 | S35: =Assumptions!E58 -> 46000 | T35: =Assumptions!E58 -> 46000 | U35: =Assumptions!E58 -> 46000 | V35: =Assumptions!E58 -> 46000 | W35: =Assumptions!E58 -> 46000 | X35: =Assumptions!E58 -> 46000 | Y35: =Assumptions!E58 -> 46000 | Z35: =Assumptions!E59 -> 105000 | AA35: =Assumptions!E59 -> 105000 | AB35: =Assumptions!E59 -> 105000 | AC35: =Assumptions!E59 -> 105000 | AD35: =Assumptions!E59 -> 105000 | AE35: =Assumptions!E59 -> 105000 | AF35: =Assumptions!E59 -> 105000 | AG35: =Assumptions!E59 -> 105000 | AH35: =Assumptions!E59 -> 105000 | AI35: =Assumptions!E59 -> 105000 | AJ35: =Assumptions!E59 -> 105000 | AK35: =Assumptions!E59 -> 105000 | AL35: =SUM(B35:M35) -> 106000 | AM35: =SUM(N35:Y35) -> 552000 | AN35: =SUM(Z35:AK35) -> 1260000
A36: Marketing (content/tools base + paid social) | B36: =Assumptions!E60 -> 2000 | C36: =Assumptions!E60 -> 2000 | D36: =Assumptions!E60 -> 2000 | E36: =Assumptions!E60+Assumptions!E12 -> 16000 | F36: =Assumptions!E60+Assumptions!E12 -> 16000 | G36: =Assumptions!E60+Assumptions!E12 -> 16000 | H36: =Assumptions!E60+Assumptions!E12 -> 16000 | I36: =Assumptions!E60+Assumptions!E12 -> 16000 | J36: =Assumptions!E60+Assumptions!E12 -> 16000 | K36: =Assumptions!E60+Assumptions!E12 -> 16000 | L36: =Assumptions!E60+Assumptions!E12 -> 16000 | M36: =Assumptions!E60+Assumptions!E12 -> 16000 | N36: =Assumptions!E61+Assumptions!E13 -> 28000 | O36: =Assumptions!E61+Assumptions!E13 -> 28000 | P36: =Assumptions!E61+Assumptions!E13 -> 28000 | Q36: =Assumptions!E61+Assumptions!E13 -> 28000 | R36: =Assumptions!E61+Assumptions!E13 -> 28000 | S36: =Assumptions!E61+Assumptions!E13 -> 28000 | T36: =Assumptions!E61+Assumptions!E13 -> 28000 | U36: =Assumptions!E61+Assumptions!E13 -> 28000 | V36: =Assumptions!E61+Assumptions!E13 -> 28000 | W36: =Assumptions!E61+Assumptions!E13 -> 28000 | X36: =Assumptions!E61+Assumptions!E13 -> 28000 | Y36: =Assumptions!E61+Assumptions!E13 -> 28000 | Z36: =Assumptions!E62+Assumptions!E14 -> 42000 | AA36: =Assumptions!E62+Assumptions!E14 -> 42000 | AB36: =Assumptions!E62+Assumptions!E14 -> 42000 | AC36: =Assumptions!E62+Assumptions!E14 -> 42000 | AD36: =Assumptions!E62+Assumptions!E14 -> 42000 | AE36: =Assumptions!E62+Assumptions!E14 -> 42000 | AF36: =Assumptions!E62+Assumptions!E14 -> 42000 | AG36: =Assumptions!E62+Assumptions!E14 -> 42000 | AH36: =Assumptions!E62+Assumptions!E14 -> 42000 | AI36: =Assumptions!E62+Assumptions!E14 -> 42000 | AJ36: =Assumptions!E62+Assumptions!E14 -> 42000 | AK36: =Assumptions!E62+Assumptions!E14 -> 42000 | AL36: =SUM(B36:M36) -> 150000 | AM36: =SUM(N36:Y36) -> 336000 | AN36: =SUM(Z36:AK36) -> 504000
A37: Clinical partnerships (cost) | B37: =0 -> 0 | C37: =0 -> 0 | D37: =Assumptions!E63 -> 900 | E37: =Assumptions!E63 -> 900 | F37: =Assumptions!E63 -> 900 | G37: =Assumptions!E63 -> 900 | H37: =Assumptions!E63 -> 900 | I37: =Assumptions!E63 -> 900 | J37: =Assumptions!E63 -> 900 | K37: =Assumptions!E63 -> 900 | L37: =Assumptions!E63 -> 900 | M37: =Assumptions!E63 -> 900 | N37: =Assumptions!E64 -> 1500 | O37: =Assumptions!E64 -> 1500 | P37: =Assumptions!E64 -> 1500 | Q37: =Assumptions!E64 -> 1500 | R37: =Assumptions!E64 -> 1500 | S37: =Assumptions!E64 -> 1500 | T37: =Assumptions!E64 -> 1500 | U37: =Assumptions!E64 -> 1500 | V37: =Assumptions!E64 -> 1500 | W37: =Assumptions!E64 -> 1500 | X37: =Assumptions!E64 -> 1500 | Y37: =Assumptions!E64 -> 1500 | Z37: =Assumptions!E65 -> 2200 | AA37: =Assumptions!E65 -> 2200 | AB37: =Assumptions!E65 -> 2200 | AC37: =Assumptions!E65 -> 2200 | AD37: =Assumptions!E65 -> 2200 | AE37: =Assumptions!E65 -> 2200 | AF37: =Assumptions!E65 -> 2200 | AG37: =Assumptions!E65 -> 2200 | AH37: =Assumptions!E65 -> 2200 | AI37: =Assumptions!E65 -> 2200 | AJ37: =Assumptions!E65 -> 2200 | AK37: =Assumptions!E65 -> 2200 | AL37: =SUM(B37:M37) -> 9000 | AM37: =SUM(N37:Y37) -> 18000 | AN37: =SUM(Z37:AK37) -> 26400
A38: Legal & admin | B38: =Assumptions!E66 -> 800 | C38: =Assumptions!E66 -> 800 | D38: =Assumptions!E66 -> 800 | E38: =Assumptions!E67 -> 350 | F38: =Assumptions!E67 -> 350 | G38: =Assumptions!E67 -> 350 | H38: =Assumptions!E67 -> 350 | I38: =Assumptions!E67 -> 350 | J38: =Assumptions!E67 -> 350 | K38: =Assumptions!E67 -> 350 | L38: =Assumptions!E67 -> 350 | M38: =Assumptions!E67 -> 350 | N38: =Assumptions!E67 -> 350 | O38: =Assumptions!E67 -> 350 | P38: =Assumptions!E67 -> 350 | Q38: =Assumptions!E67 -> 350 | R38: =Assumptions!E67 -> 350 | S38: =Assumptions!E67 -> 350 | T38: =Assumptions!E67 -> 350 | U38: =Assumptions!E67 -> 350 | V38: =Assumptions!E67 -> 350 | W38: =Assumptions!E67 -> 350 | X38: =Assumptions!E67 -> 350 | Y38: =Assumptions!E67 -> 350 | Z38: =Assumptions!E67 -> 350 | AA38: =Assumptions!E67 -> 350 | AB38: =Assumptions!E67 -> 350 | AC38: =Assumptions!E67 -> 350 | AD38: =Assumptions!E67 -> 350 | AE38: =Assumptions!E67 -> 350 | AF38: =Assumptions!E67 -> 350 | AG38: =Assumptions!E67 -> 350 | AH38: =Assumptions!E67 -> 350 | AI38: =Assumptions!E67 -> 350 | AJ38: =Assumptions!E67 -> 350 | AK38: =Assumptions!E67 -> 350 | AL38: =SUM(B38:M38) -> 5550 | AM38: =SUM(N38:Y38) -> 4200 | AN38: =SUM(Z38:AK38) -> 4200
A39: HealthKit + Health Connect build (M4–6, one-off) | B39: =0 -> 0 | C39: =0 -> 0 | D39: =0 -> 0 | E39: =Assumptions!E50/3 -> 2666.6667 | F39: =Assumptions!E50/3 -> 2666.6667 | G39: =Assumptions!E50/3 -> 2666.6667 | H39: =0 -> 0 | I39: =0 -> 0 | J39: =0 -> 0 | K39: =0 -> 0 | L39: =0 -> 0 | M39: =0 -> 0 | N39: =0 -> 0 | O39: =0 -> 0 | ... AK39: =0 -> 0 | AL39: =SUM(B39:M39) -> 8000 | AM39: =SUM(N39:Y39) -> 0 | AN39: =SUM(Z39:AK39) -> 0
A40: Oura Ring integration (M15, one-off) | B40: =0 -> 0 | C40: =0 -> 0 | D40: =0 -> 0 | E40: =0 -> 0 | F40: =0 -> 0 | G40: =0 -> 0 | H40: =0 -> 0 | I40: =0 -> 0 | ... O40: =0 -> 0 | P40: =Assumptions!E51 -> 5000 | Q40: =0 -> 0 | R40: =0 -> 0 | S40: =0 -> 0 | T40: =0 -> 0 | U40: =0 -> 0 | V40: =0 -> 0 | W40: =0 -> 0 | X40: =0 -> 0 | ... AK40: =0 -> 0 | AL40: =SUM(B40:M40) -> 0 | AM40: =SUM(N40:Y40) -> 5000 | AN40: =SUM(Z40:AK40) -> 0
A41: Predictive AI dev (M20–M23, €3K/mo) | B41: =0 -> 0 | C41: =0 -> 0 | D41: =0 -> 0 | E41: =0 -> 0 | F41: =0 -> 0 | G41: =0 -> 0 | H41: =0 -> 0 | I41: =0 -> 0 | ... T41: =0 -> 0 | U41: =Assumptions!E52 -> 3000 | V41: =Assumptions!E52 -> 3000 | W41: =Assumptions!E52 -> 3000 | X41: =Assumptions!E52 -> 3000 | Y41: =0 -> 0 | Z41: =0 -> 0 | AA41: =0 -> 0 | AB41: =0 -> 0 | AC41: =0 -> 0 | AD41: =0 -> 0 | AE41: =0 -> 0 | AF41: =0 -> 0 | ... AK41: =0 -> 0 | AL41: =SUM(B41:M41) -> 0 | AM41: =SUM(N41:Y41) -> 12000 | AN41: =SUM(Z41:AK41) -> 0
A42: TOTAL COSTS | B42: =B30+B31+B32+B33+B34+B35+B36+B37+B38+B39+B40+B41 -> 3820.8681 | C42: =C30+C31+C32+C33+C34+C35+C36+C37+C38+C39+C40+C41 -> 3843.9586 | D42: =D30+D31+D32+D33+D34+D35+D36+D37+D38+D39+D40+D41 -> 12483.47 | E42: =E30+E31+E32+E33+E34+E35+E36+E37+E38+E39+E40+E41 -> 29661.633 | F42: =F30+F31+F32+F33+F34+F35+F36+F37+F38+F39+F40+F41 -> 31013.928 | G42: =G30+G31+G32+G33+G34+G35+G36+G37+G38+G39+G40+G41 -> 33258.825 | H42: =H30+H31+H32+H33+H34+H35+H36+H37+H38+H39+H40+H41 -> 38112.188 | I42: =I30+I31+I32+I33+I34+I35+I36+I37+I38+I39+I40+I41 -> 39581.334 | ... AK42: =AK30+AK31+AK32+AK33+AK34+AK35+AK36+AK37+AK38+AK39+AK40+AK41 -> 498452.36 | AL42: =SUM(B42:M42) -> 364443.02 | AM42: =SUM(N42:Y42) -> 1570565.1 | AN42: =SUM(Z42:AK42) -> 4160609.1
A44: SECTION 4 — PROFIT & LOSS & CASH
A45: Gross margin % — FIXED (from annual revenue/COGS sums, not monthly average) | B45: =IF(B24=0,0,(B24-(B30+B31+B32))/B24) -> 0.85 | C45: =IF(C24=0,0,(C24-(C30+C31+C32))/C24) -> 0.85 | D45: =IF(D24=0,0,(D24-(D30+D31+D32))/D24) -> 0.93541254 | E45: =IF(E24=0,0,(E24-(E30+E31+E32))/E24) -> 0.87972666 | F45: =IF(F24=0,0,(F24-(F30+F31+F32))/F24) -> 0.86350421 | G45: =IF(G24=0,0,(G24-(G30+G31+G32))/G24) -> 0.83342573 | H45: =IF(H24=0,0,(H24-(H30+H31+H32))/H24) -> 0.84542314 | I45: =IF(I24=0,0,(I24-(I30+I31+I32))/I24) -> 0.85208207 | ... AK45: =IF(AK24=0,0,(AK24-(AK30+AK31+AK32))/AK24) -> 0.73823287 | AL45: =IF(SUM(B24:M24)=0,0,(SUM(B24:M24)-(SUM(B30:M30)+SUM(B31:M31)+SUM(B32:M32)))/SUM(B24:M24)) -> 0.8574162 | AM45: =IF(SUM(N24:Y24)=0,0,(SUM(N24:Y24)-(SUM(N30:Y30)+SUM(N31:Y31)+SUM(N32:Y32)))/SUM(N24:Y24)) -> 0.83354447 | AN45: =IF(SUM(Z24:AK24)=0,0,(SUM(Z24:AK24)-(SUM(Z30:AK30)+SUM(Z31:AK31)+SUM(Z32:AK32)))/SUM(Z24:AK24)) -> 0.75753179 | AO45: CORRECTED: annual cell = (annual revenue - annual COGS) / annual revenue. Old formula averaged monthly %s → ~6% nonsense.
A46: Net burn / profit (negative = burning) | B46: =B24-B42 -> -3548.4141 | C46: =C24-C42 -> -3417.5681 | D46: =D24-D42 -> -10727.288 | E46: =E24-E42 -> -24615.657 | F46: =F24-F42 -> -19906.285 | G46: =G24-G42 -> -14000.373 | H46: =H24-H42 -> -10979.099 | I46: =I24-I42 -> -4799.3996 | ... AK46: =AK24-AK42 -> 719815.03 | AL46: =SUM(B46:M46) -> -50306.843 | AM46: =SUM(N46:Y46) -> 764787.91 | AN46: =SUM(Z46:AK46) -> 4112677.9
A47: Financing inflows (pre-seed M1; seed explicit, not in revenue) | B47: =Assumptions!E73 -> 350000 | C47: =IF(2=Assumptions!E74,Assumptions!E75,0) -> 0 | D47: =IF(3=Assumptions!E74,Assumptions!E75,0) -> 0 | E47: =IF(4=Assumptions!E74,Assumptions!E75,0) -> 0 | F47: =IF(5=Assumptions!E74,Assumptions!E75,0) -> 0 | G47: =IF(6=Assumptions!E74,Assumptions!E75,0) -> 0 | H47: =IF(7=Assumptions!E74,Assumptions!E75,0) -> 0 | I47: =IF(8=Assumptions!E74,Assumptions!E75,0) -> 0 | J47: =IF(9=Assumptions!E74,Assumptions!E75,0) -> 0 | K47: =IF(10=Assumptions!E74,Assumptions!E75,0) -> 0 | L47: =IF(11=Assumptions!E74,Assumptions!E75,0) -> 0 | M47: =IF(12=Assumptions!E74,Assumptions!E75,0) -> 0 | N47: =IF(13=Assumptions!E74,Assumptions!E75,0) -> 5000000 | O47: =IF(14=Assumptions!E74,Assumptions!E75,0) -> 0 | P47: =IF(15=Assumptions!E74,Assumptions!E75,0) -> 0 | Q47: =IF(16=Assumptions!E74,Assumptions!E75,0) -> 0 | R47: =IF(17=Assumptions!E74,Assumptions!E75,0) -> 0 | S47: =IF(18=Assumptions!E74,Assumptions!E75,0) -> 0 | T47: =IF(19=Assumptions!E74,Assumptions!E75,0) -> 0 | U47: =IF(20=Assumptions!E74,Assumptions!E75,0) -> 0 | V47: =IF(21=Assumptions!E74,Assumptions!E75,0) -> 0 | W47: =IF(22=Assumptions!E74,Assumptions!E75,0) -> 0 | X47: =IF(23=Assumptions!E74,Assumptions!E75,0) -> 0 | Y47: =IF(24=Assumptions!E74,Assumptions!E75,0) -> 0 | Z47: =IF(25=Assumptions!E74,Assumptions!E75,0) -> 0 | AA47: =IF(26=Assumptions!E74,Assumptions!E75,0) -> 0 | AB47: =IF(27=Assumptions!E74,Assumptions!E75,0) -> 0 | AC47: =IF(28=Assumptions!E74,Assumptions!E75,0) -> 0 | AD47: =IF(29=Assumptions!E74,Assumptions!E75,0) -> 0 | AE47: =IF(30=Assumptions!E74,Assumptions!E75,0) -> 0 | AF47: =IF(31=Assumptions!E74,Assumptions!E75,0) -> 0 | AG47: =IF(32=Assumptions!E74,Assumptions!E75,0) -> 0 | AH47: =IF(33=Assumptions!E74,Assumptions!E75,0) -> 0 | AI47: =IF(34=Assumptions!E74,Assumptions!E75,0) -> 0 | AJ47: =IF(35=Assumptions!E74,Assumptions!E75,0) -> 0 | AK47: =IF(36=Assumptions!E74,Assumptions!E75,0) -> 0 | AL47: =SUM(B47:M47) -> 350000 | AM47: =SUM(N47:Y47) -> 5000000 | AN47: =SUM(Z47:AK47) -> 0 | AO47: Seed shown as explicit injection so runway dependence is honest. NOT revenue.
A48: Ending cash (cumulative) | B48: =B46+B47 -> 346451.59 | C48: =B48+C46+C47 -> 343034.02 | D48: =C48+D46+D47 -> 332306.73 | E48: =D48+E46+E47 -> 307691.07 | F48: =E48+F46+F47 -> 287784.79 | G48: =F48+G46+G47 -> 273784.42 | H48: =G48+H46+H47 -> 262805.32 | I48: =H48+I46+I47 -> 258005.92 | J48: =I48+J46+J47 -> 259250.13 | ... AK48: =AJ48+AK46+AK47 -> 10177159 | AL48: =M48 -> 299693.16 | AM48: =Y48 -> 6064481.1 | AN48: =AK48 -> 10177159
A50: SECTION 5 — UNIT ECONOMICS (single consistent method; all linked to assumptions)
A51: LTV — B2C basic (price × (1-app_fee) ÷ Y2 avg churn) | B51: =Assumptions!E4*(1-Assumptions!E41)/AVERAGE(N9:Y9) -> 83.576355 | AO51: ONE consistent formula. Original mixed €42.42 / €40.92 / €34.93 across three lines.
A52: LTV — B2C premium (price × (1-app_fee) ÷ prem churn) | B52: =Assumptions!E5*(1-Assumptions!E41)/Assumptions!E27 -> 368.05
A53: CAC — paid social Y1 (€) | B53: =Assumptions!E15 -> 12
A54: LTV:CAC — B2C basic paid channel (VC floor: 3×) | B54: =IF(B53=0,0,B51/B53) -> 6.9646962 | AO54: VC floor 3×. Corrected LTV and CAC feed this — one consistent calculation.
A55: Payback period — paid social (months) | B55: =IF(B53=0,0,B53/(Assumptions!E4*(1-Assumptions!E41))) -> 2.8291878
A56: CAC — organic Y1 (€4.20 — events €500 + tools €200 ÷ ~167 users) | B56: 4.2
A57: LTV:CAC — organic | B57: =IF(B56=0,0,B51/B56) -> 19.899132

Sheet Summary
A1: NutriSync — Investor Summary Dashboard | Formula-linked to scenario sheets (do not hardcode)
A2: Metric | B2: Conservative | C2: Realistic | D2: Ambitious | E2: Interpretation
A3: USERS
A4: Total paying users EoY1 | B4: =Conservative!AL15 -> 5081.4564 | C4: =Realistic!AL15 -> 8021.112 | D4: =Ambitious!AL15 -> 12235.478 | E4: Basic + premium + B2B (no double-counting)
A5: Total paying users EoY2 | B5: =Conservative!AM15 -> 20199.213 | C5: =Realistic!AM15 -> 32708.41 | D5: =Ambitious!AM15 -> 50714.154 | E5: Basic + premium + B2B (no double-counting)
A6: Total paying users EoY3 | B6: =Conservative!AN15 -> 80699.471 | C6: =Realistic!AN15 -> 137370.84 | D6: =Ambitious!AN15 -> 218216.77 | E6: Basic + premium + B2B (no double-counting)
A8: REVENUE
A9: Total annual revenue Y1 | B9: =SUM(Conservative!B24:M24) -> 132562.13 | C9: =SUM(Realistic!B24:M24) -> 207220.66 | D9: =SUM(Ambitious!B24:M24) -> 314136.17
A10: Total annual revenue Y2 | B10: =SUM(Conservative!N24:Y24) -> 907318.98 | C10: =SUM(Realistic!N24:Y24) -> 1381532.2 | D10: =SUM(Ambitious!N24:Y24) -> 2335353
A11: Total annual revenue Y3 | B11: =SUM(Conservative!Z24:AK24) -> 3036840.4 | C11: =SUM(Realistic!Z24:AK24) -> 4943253.2 | D11: =SUM(Ambitious!Z24:AK24) -> 8273287.1
A12: ARR at EoY1 | B12: =Conservative!AL26 -> 278455.37 | C12: =Realistic!AL26 -> 440764.43 | D12: =Ambitious!AL26 -> 691037.06 | E12: MRR × 12 at year end. Lead with ARR in VC conversations.
A13: ARR at EoY2 | B13: =Conservative!AM26 -> 1279027.2 | C13: =Realistic!AM26 -> 2065179.2 | D13: =Ambitious!AM26 -> 3359082.5 | E13: MRR × 12 at year end. Lead with ARR in VC conversations.
A14: ARR at EoY3 | B14: =Conservative!AN26 -> 4899335.5 | C14: =Realistic!AN26 -> 8425405.8 | D14: =Ambitious!AN26 -> 13816409 | E14: MRR × 12 at year end. Lead with ARR in VC conversations.
A16: MARGINS & BURN
A17: Gross margin Y1 (from annual sums — CORRECTED) | B17: =Conservative!AL45 -> 0.8506011 | C17: =Realistic!AL45 -> 0.85559135 | D17: =Ambitious!AL45 -> 0.8574162 | E17: Annual revenue minus direct COGS (fees + AI + 30% infra) / annual revenue
A18: Gross margin Y2 (from annual sums — CORRECTED) | B18: =Conservative!AM45 -> 0.88293417 | C18: =Realistic!AM45 -> 0.83450216 | D18: =Ambitious!AM45 -> 0.83354447 | E18: Annual revenue minus direct COGS (fees + AI + 30% infra) / annual revenue
A19: Gross margin Y3 (from annual sums — CORRECTED) | B19: =Conservative!AN45 -> 0.78030486 | C19: =Realistic!AN45 -> 0.74007927 | D19: =Ambitious!AN45 -> 0.75753179 | E19: Annual revenue minus direct COGS (fees + AI + 30% infra) / annual revenue
A20: EBITDA / annual burn Y1 | B20: =SUM(Conservative!B46:M46) -> -105834.55 | C20: =SUM(Realistic!B46:M46) -> -84430.292 | D20: =SUM(Ambitious!B46:M46) -> -50306.843
A21: EBITDA / annual burn Y2 | B21: =SUM(Conservative!N46:Y46) -> -9802.4836 | C21: =SUM(Realistic!N46:Y46) -> 85463.636 | D21: =SUM(Ambitious!N46:Y46) -> 764787.91
A22: EBITDA / annual burn Y3 | B22: =SUM(Conservative!Z46:AK46) -> 1189669.9 | C22: =SUM(Realistic!Z46:AK46) -> 1960618.5 | D22: =SUM(Ambitious!Z46:AK46) -> 4112677.9
A24: CASH
A25: Ending cash EoY1 | B25: =Conservative!AL48 -> 244165.45 | C25: =Realistic!AL48 -> 265569.71 | D25: =Ambitious!AL48 -> 299693.16 | E25: Includes seed injection (explicit, not in revenue). Never goes negative = plan is fundable.
A26: Ending cash EoY2 | B26: =Conservative!AM48 -> 1734363 | C26: =Realistic!AM48 -> 3351033.3 | D26: =Ambitious!AM48 -> 6064481.1 | E26: Includes seed injection (explicit, not in revenue). Never goes negative = plan is fundable.
A27: Ending cash EoY3 | B27: =Conservative!AN48 -> 2924032.9 | C27: =Realistic!AN48 -> 5311651.8 | D27: =Ambitious!AN48 -> 10177159 | E27: Includes seed injection (explicit, not in revenue). Never goes negative = plan is fundable.
A29: CORRECTIONS LOG — WHAT CHANGED VS ORIGINAL
A30: 1. Free→paid conversion CORRECTED | B30: Was 18%/mo applied to entire cumulative free pool (compounded to fantasy user counts). Now 5–8% one-off per month's NEW free users. Benchmark: RevenueCat H&F trial-to-paid median 6.9%.
A31: 2. CAC CORRECTED | B31: Was €6–8 (beating market 4–7×). Now €20/€15/€12 Y1. Install cost alone is $3.70–4.70; at 3–7% install-to-paid, realistic subscriber CAC is €15–60.
A32: 3. App store fee direction CORRECTED | B32: Original: 30% dropping to 15% after €1M. Reality: 15% UNDER $1M proceeds (Small Business Programme); 30% ABOVE. Now modelled via trailing-12-month B2C revenue test.
A33: 4. Churn relabelled honestly | B33: 9–10%/mo is fitness-app AVERAGE (9.2%, RetentionCheck 2026). Not conservative. Sub-5% reserved for ambitious only.
A34: 5. Premium conversion CORRECTED | B34: Was 4–8%/mo of basic base compounding → implausible premium mix. Now 0.75–1.5%/mo building to realistic 15–25% premium share by M36.
A35: 6. Gross margin formula FIXED | B35: Original annual GM cells summed monthly percentages (averaged ratios → ~6% nonsense). Now computed as (annual rev - annual COGS) / annual rev.
A36: 7. Unit economics made consistent | B36: Original mixed €42.42 / €40.92 / €34.93 in three different lines. Now one formula: price × (1-fee) / Y2_blended_churn. Linked to assumptions.
A37: 8. Premium users no longer double-counted | B37: Premium users now MOVE from basic pool, not added on top. Total unique users is correct.
A38: 9. Seed round explicit | B38: Y2–3 costs assumed seed funding without showing it in cash. Seed now an explicit M13 inflow so runway dependence is visible and honest.
A39: 10. Upside revenue separated | B39: Brand partnerships were labelled 'not in base assumptions' yet appeared in every scenario. Now 0 in conservative.
A40: 11. NutriSync is 7-day trial then PAID — no free tier | B40: Model updated: no permanent free pool. Conversion applied to trial users only.
A42: CONSERVATIVE SCENARIO ADJUSTMENT — v2
A43: What changed | B43: Why it's still defensible
A44: M1 organic free users: 130 → 160 | B44: NutriSync has an active waitlist, 2 proven paid events, and clinical partners driving referrals. 160 is still below the 200 used in the Realistic scenario.
A45: Organic growth rate: 10% → 11%/mo | B45: Compound community + clinical referral growth. 11% is conservative; most content-led health apps compound at 12–15% once clinical credibility is established.
A46: Free-to-paid conversion: 5% → 6% | B46: Industry median is 6.9% (RevenueCat 2026). 6% is still below median — we are not claiming top-quartile performance, just average.
A47: B2B contracts: 0.4 → 0.5/mo Y1, 1.0 → 1.2/mo Y2, 2.0 → 2.5/mo Y3 | B47: NutriSync has warm B2B leads already. 0.5/mo Y1 = ~3 contracts in first 6 months of B2B activity. One warm lead converting validates this.
A48: Clinical referral fee: €250 → €300/contract/mo | B48: Modest increase reflecting NutriSync's stronger clinical differentiation vs. generic wellness apps.
A49: What did NOT change | B49: Reason
A50: Churn rates (9%/8%/6.5%) | B50: Left at industry-average to honest levels. Not inflated to hit profitability — that would break credibility.
A51: CAC (€20 Y1) | B51: No change — €20 is already aggressive and needs real data to move.
A52: Team/salary costs | B52: Not cut to manufacture profitability — a funded team is needed to execute the roadmap.
A53: Result
A54: Users M36: 13,600 → 15,700 | B54: ~15% increase. Still 40% below the original over-optimistic model.
A55: Y3 revenue: €777K → €902K | B55: Better but still a burn year at -€186K annual vs -€298K before.
A56: First profitable month: M35 | B56: The model reaches profitability in M35 (month 35 of 36). M36 is €7,720 profit. Y3 annual is not yet profitable — that is honest.
A57: Y3 framing for investors | B57: Say: 'We reach monthly profitability in M35. The full Year 3 shows a €186K net burn — this reflects the cost of building a fully-staffed team on seed capital. We are approaching breakeven, not chasing it.'
A59: CORRECTIONS LOG — PATCH 2 (applied by Claude, Aug 2026 review)
A60: 12. Summary EoY3 users/ARR/cash FIXED | B60: Was pointing at the 'Y1 Total' column (AL) instead of 'Y3 Total' (AN) — Summary was showing users/ARR/cash *declining* in Year 3. Now correctly pulls AL/AM/AN for Y1/Y2/Y3 respectively.
A61: 13. Summary gross margin Y1-Y3 FIXED for all 3 scenarios | B61: Formula was computing (Total Revenue − Premium Revenue), not a margin at all, and only Conservative was filled in. Now references each scenario's own correctly-computed annual gross-margin % (row 45, cols AL/AM/AN).
A62: 14. Organic LTV:CAC FIXED in each scenario sheet | B62: Row 57 divided Premium LTV by organic CAC (65.7x-87.6x). Now divides Basic LTV by organic CAC, matching the 13.6x figure already used in the pitch deck.
A63: 15. App Store fee threshold CORRECTED | B63: Assumptions C43:E43 was €1,176,000 for Apple's $1M Small Business Program threshold (wrong FX direction). Corrected to €865,000 (~5 Aug 2026 ECB reference rate) — reverify against the live rate before final submission.
A64: STILL OPEN — not fixed in this pass | B64: Sensitivity sheet grids (breakeven month / cash at M36) appear to be static typed values, not live formulas tied to Assumptions — verify before quoting them, or ask for a rebuild as a live data table.

Sheet Sensitivity
A1: Sensitivity Analysis — CAC × Monthly Churn (Realistic scenario base)
A2: Grid 1: Breakeven month (sustained profitability)
A3: Y1 churn \ Y1 CAC → | B3: €8 | C3: €12 | D3: €15 | E3: €20 | F3: €25 | G3: €30
A4: 6% | B4: 26 | C4: 29 | D4: 31 | E4: 33 | F4: 34 | G4: 35
A5: 7% | B5: 27 | C5: 30 | D5: 31 | E5: 33 | F5: 34 | G5: 35
A6: 8% | B6: 27 | C6: 30 | D6: 32 | E6: 33 | F6: 35 | G6: 36
A7: 9% | B7: 28 | C7: 30 | D7: 32 | E7: 34 | F7: 35 | G7: 36
A8: 10% | B8: 28 | C8: 31 | D8: 32 | E8: 34 | F8: 36 | G8: >36
A9: 11% | B9: 28 | C9: 31 | D9: 33 | E9: 35 | F9: 36 | G9: >36
A11: Grid 2: Cash at M36 (€) — incl. €350K pre-seed + seed at M13
A12: Y1 churn \ Y1 CAC → | B12: €8 | C12: €12 | D12: €15 | E12: €20 | F12: €25 | G12: €30
A13: 6% | B13: 3731245 | C13: 3205467 | D13: 2992957 | E13: 2751751 | F13: 2594048 | G13: 2488913
A14: 7% | B14: 3623696 | C14: 3149769 | D14: 2947766 | E14: 2699194 | F14: 2550101 | G14: 2450705
A15: 8% | B15: 3548973 | C15: 3078142 | D15: 2886728 | E15: 2651291 | F15: 2510029 | G15: 2415854
A16: 9% | B16: 3482364 | C16: 3033215 | D16: 2831044 | E16: 2607510 | F16: 2473390 | G16: 2383976
A17: 10% | B17: 3399659 | C17: 2992739 | D17: 2780040 | E17: 2567390 | F17: 2439801 | G17: 2354741
A18: 11% | B18: 3345418 | C18: 2935869 | D18: 2733199 | E18: 2530529 | F18: 2408927 | G18: 2327859
A20: How to read: Yellow = Realistic base case. CAC drives breakeven month more than churn. Churn drives LTV:CAC most.
